Workbook

Sheet Channel_Listings
A1: Marketplace | B1: Category | C1: Channel_SKU | D1: Pack_SKU | E1: Listing_Status | F1: ASIN_FSN_ID | G1: Listing_URL | H1: Last_Updated | I1: Comment
A2: Amazon | B2: {=IF(D2="","", INDEX(Product_Master!A:A, MATCH( INDEX(Pack_Master!B:B, MATCH(D2, Pack_Master!A:A, 0)), Product_Master!B:B, 0 ) ))} -> Apparel_ArmSleeves | C2: 14-32DR-R138 | D2: ARMSLEEVES-HALF-BLACK | E2: LIVE
A3: Amazon | B3: {=IF(D3="","", INDEX(Product_Master!A:A, MATCH( INDEX(Pack_Master!B:B, MATCH(D3, Pack_Master!A:A, 0)), Product_Master!B:B, 0 ) ))} -> Automotive_FaceMasks | C3: 2L-4L4E-SECU | D3: BANDANA-PATTERN-MULTICOLOR-PK10 | E3: LIVE
A4: Amazon | B4: {=IF(D4="","", INDEX(Product_Master!A:A, MATCH( INDEX(Pack_Master!B:B, MATCH(D4, Pack_Master!A:A, 0)), Product_Master!B:B, 0 ) ))} -> Apparel_Caps_Beanies | C4: 2W-LKH7-FA8Z | D4: CAP-BASEBALL-PLAIN-WHITE | E4: LIVE
A5: Amazon | B5: {=IF(D5="","", INDEX(Product_Master!A:A, MATCH( INDEX(Pack_Master!B:B, MATCH(D5, Pack_Master!A:A, 0)), Product_Master!B:B, 0 ) ))} -> Automotive_FaceMasks | C5: 48-J9LB-ACWM | D5: MASK-HALF-BLUE-PK1 | E5: LIVE
A6: Amazon | B6: {=IF(D6="","", INDEX(Product_Master!A:A, MATCH( INDEX(Pack_Master!B:B, MATCH(D6, Pack_Master!A:A, 0)), Product_Master!B:B, 0 ) ))} -> Apparel_Caps_Beanies | C6: 59-10E8-ZXMS | D6: CAP-GOLF-CHARCOAL | E6: LIVE
A7: Amazon | B7: {=IF(D7="","", INDEX(Product_Master!A:A, MATCH( INDEX(Pack_Master!B:B, MATCH(D7, Pack_Master!A:A, 0)), Product_Master!B:B, 0 ) ))} -> Automotive_FaceMasks | C7: 8D-6GQZ-DKR2 | D7: BANDANA-PATTERN-MULTICOLOR-PK5 | E7: LIVE
A8: Amazon | B8: {=IF(D8="","", INDEX(Product_Master!A:A, MATCH( INDEX(Pack_Master!B:B, MATCH(D8, Pack_Master!A:A, 0)), Product_Master!B:B, 0 ) ))} -> Apparel_ArmSleeves | C8: 96-7KTF-QMRW | D8: ARMSLEEVES-HALF-BLACK | E8: LIVE
A9: Amazon | B9: {=IF(D9="","", INDEX(Product_Master!A:A, MATCH( INDEX(Pack_Master!B:B, MATCH(D9, Pack_Master!A:A, 0)), Product_Master!B:B, 0 ) ))} -> Apparel_Tshirts | C9: A-TSHIRT-BLACK-PRINT-AMPM-L | D9: TSHIRT-BLACK-L | E9: LIVE | F9: B0DH3D29MC
A10: Amazon | B10: {=IF(D10="","", INDEX(Product_Master!A:A, MATCH( INDEX(Pack_Master!B:B, MATCH(D10, Pack_Master!A:A, 0)), Product_Master!B:B, 0 ) ))} -> Apparel_Tshirts | C10: A-TSHIRT-BLACK-PRINT-AMPM-M | D10: TSHIRT-BLACK-M | E10: LIVE | F10: B0DH3F2MKH
A11: Amazon | B11: {=IF(D11="","", INDEX(Product_Master!A:A, MATCH( INDEX(Pack_Master!B:B, MATCH(D11, Pack_Master!A:A, 0)), Product_Master!B:B, 0 ) ))} -> Apparel_Tshirts | C11: A-TSHIRT-BLACK-PRINT-AMPM-XL | D11: TSHIRT-BLACK-XL | E11: LIVE | F11: B0DH3DKJPF
A12: Amazon | B12: {=IF(D12="","", INDEX(Product_Master!A:A, MATCH( INDEX(Pack_Master!B:B, MATCH(D12, Pack_Master!A:A, 0)), Product_Master!B:B, 0 ) ))} -> Apparel_Tshirts | C12: A-TSHIRT-BLACK-PRINT-AMPM-XXL | D12: TSHIRT-BLACK-XXL | E12: LIVE | F12: B0DH3CL2GX
A13: Amazon | B13: {=IF(D13="","", INDEX(Product_Master!A:A, MATCH( INDEX(Pack_Master!B:B, MATCH(D13, Pack_Master!A:A, 0)), Product_Master!B:B, 0 ) ))} -> Apparel_Tshirts | C13: A-TSHIRT-BLACK-PRINT-ARTISLIFE-L | D13: TSHIRT-BLACK-L | E13: LIVE | F13: B0DH3D1GBY
A14: Amazon | B14: {=IF(D14="","", INDEX(Product_Master!A:A, MATCH( INDEX(Pack_Master!B:B, MATCH(D14, Pack_Master!A:A, 0)), Product_Master!B:B, 0 ) ))} -> Apparel_Tshirts | C14: A-TSHIRT-BLACK-PRINT-ARTISLIFE-M | D14: TSHIRT-BLACK-M | E14: LIVE | F14: B0DH3DHTX8
A15: Amazon | B15: {=IF(D15="","", INDEX(Product_Master!A:A, MATCH( INDEX(Pack_Master!B:B, MATCH(D15, Pack_Master!A:A, 0)), Product_Master!B:B, 0 ) ))} -> Apparel_Tshirts | C15: A-TSHIRT-BLACK-PRINT-ARTISLIFE-XL | D15: TSHIRT-BLACK-XL | E15: LIVE | F15: B0DH3F9Y8R
A16: Amazon | B16: {=IF(D16="","", INDEX(Product_Master!A:A, MATCH( INDEX(Pack_Master!B:B, MATCH(D16, Pack_Master!A:A, 0)), Product_Master!B:B, 0 ) ))} -> Apparel_Tshirts | C16: A-TSHIRT-BLACK-PRINT-ARTISLIFE-XXL | D16: TSHIRT-BLACK-XXL | E16: LIVE | F16: B0DH3CVPR8
A17: Amazon | B17: {=IF(D17="","", INDEX(Product_Master!A:A, MATCH( INDEX(Pack_Master!B:B, MATCH(D17, Pack_Master!A:A, 0)), Product_Master!B:B, 0 ) ))} -> Apparel_Tshirts | C17: A-TSHIRT-BLACK-PRINT-BETHEUNIQUEONE-L | D17: TSHIRT-BLACK-L | E17: LIVE | F17: B0DH3DKDT2
A18: Amazon | B18: {=IF(D18="","", INDEX(Product_Master!A:A, MATCH( INDEX(Pack_Master!B:B, MATCH(D18, Pack_Master!A:A, 0)), Product_Master!B:B, 0 ) ))} -> Apparel_Tshirts | C18: A-TSHIRT-BLACK-PRINT-BETHEUNIQUEONE-M | D18: TSHIRT-BLACK-M | E18: LIVE | F18: B0DH3DHLVL
A19: Amazon | B19: {=IF(D19="","", INDEX(Product_Master!A:A, MATCH( INDEX(Pack_Master!B:B, MATCH(D19, Pack_Master!A:A, 0)), Product_Master!B:B, 0 ) ))} -> Apparel_Tshirts | C19: A-TSHIRT-BLACK-PRINT-BETHEUNIQUEONE-XL | D19: TSHIRT-BLACK-XL | E19: LIVE | F19: B0DH3FGBRD
A20: Amazon | B20: {=IF(D20="","", INDEX(Product_Master!A:A, MATCH( INDEX(Pack_Master!B:B, MATCH(D20, Pack_Master!A:A, 0)), Product_Master!B:B, 0 ) ))} -> Apparel_Tshirts | C20: A-TSHIRT-BLACK-PRINT-BETHEUNIQUEONE-XXL | D20: TSHIRT-BLACK-XXL | E20: LIVE | F20: B0DH3FJBS8
... A60: Amazon | B60: {=IF(D60="","", INDEX(Product_Master!A:A, MATCH( INDEX(Pack_Master!B:B, MATCH(D60, Pack_Master!A:A, 0)), Product_Master!B:B, 0 ) ))} -> Apparel_Tshirts | C60: A-TSHIRT-BLACK-PRINT-THEMOON-XXL | D60: TSHIRT-BLACK-XXL | E60: LIVE | F60: B0DH3DL9JD
A61: Amazon | B61: {=IF(D61="","", INDEX(Product_Master!A:A, MATCH( INDEX(Pack_Master!B:B, MATCH(D61, Pack_Master!A:A, 0)), Product_Master!B:B, 0 ) ))} -> Apparel_ArmSleeves | C61: AG-MFT8-S8CP | D61: ARMSLEEVES-HALF-WHITE | E61: LIVE
A62: Amazon | B62: {=IF(D62="","", INDEX(Product_Master!A:A, MATCH( INDEX(Pack_Master!B:B, MATCH(D62, Pack_Master!A:A, 0)), Product_Master!B:B, 0 ) ))} -> Apparel_Accessories_Winter | C62: AJ-BMGV-XM6S | D62: MUFFLER-STRIPE-GREY | E62: LIVE
A63: Amazon | B63: {=IF(D63="","", INDEX(Product_Master!A:A, MATCH( INDEX(Pack_Master!B:B, MATCH(D63, Pack_Master!A:A, 0)), Product_Master!B:B, 0 ) ))} -> Apparel_Caps_Beanies | C63: AK-O5V0-6K6W | D63: CAP-BASEBALL-PLAIN-RED | E63: LIVE
A64: Amazon | B64: {=IF(D64="","", INDEX(Product_Master!A:A, MATCH( INDEX(Pack_Master!B:B, MATCH(D64, Pack_Master!A:A, 0)), Product_Master!B:B, 0 ) ))} -> Automotive_FaceMasks | C64: AK-ZZR6-ZP97 | D64: MASK-HALF-BLUE-PK1 | E64: LIVE
A65: Amazon | B65: {=IF(D65="","", INDEX(Product_Master!A:A, MATCH( INDEX(Pack_Master!B:B, MATCH(D65, Pack_Master!A:A, 0)), Product_Master!B:B, 0 ) ))} -> Apparel_ArmSleeves | C65: Arm-Full-Black | D65: ARMSLEEVES-FULL-BLACK | E65: LIVE
A66: Amazon | B66: {=IF(D66="","", INDEX(Product_Master!A:A, MATCH( INDEX(Pack_Master!B:B, MATCH(D66, Pack_Master!A:A, 0)), Product_Master!B:B, 0 ) ))} -> Apparel_Accessories_Winter | C66: BANDANA-HANKY-PAISLEY-BLACK | D66: BANDANA-HANKY-PAISLEY-BLACK | E66: LIVE | F66: B09DXJNDMW
A67: Amazon | B67: {=IF(D67="","", INDEX(Product_Master!A:A, MATCH( INDEX(Pack_Master!B:B, MATCH(D67, Pack_Master!A:A, 0)), Product_Master!B:B, 0 ) ))} -> Apparel_Accessories_Winter | C67: BANDANA-HANKY-PAISLEY-GREEN | D67: BANDANA-HANKY-PAISLEY-GREEN | E67: LIVE | F67: B0BNNHMQLR
A68: Amazon | B68: {=IF(D68="","", INDEX(Product_Master!A:A, MATCH( INDEX(Pack_Master!B:B, MATCH(D68, Pack_Master!A:A, 0)), Product_Master!B:B, 0 ) ))} -> Apparel_Accessories_Winter | C68: BANDANA-HANKY-PAISLEY-MAROON | D68: BANDANA-HANKY-PAISLEY-MAROON | E68: LIVE | F68: B09FJDN4TS
A69: Amazon | B69: {=IF(D69="","", INDEX(Product_Master!A:A, MATCH( INDEX(Pack_Master!B:B, MATCH(D69, Pack_Master!A:A, 0)), Product_Master!B:B, 0 ) ))} -> Apparel_Accessories_Winter | C69: BANDANA-HANKY-PAISLEY-NAVYBLUE | D69: BANDANA-HANKY-PAISLEY-NAVYBLUE | E69: LIVE | F69: B09DXHWHGF
A70: Amazon | B70: {=IF(D70="","", INDEX(Product_Master!A:A, MATCH( INDEX(Pack_Master!B:B, MATCH(D70, Pack_Master!A:A, 0)), Product_Master!B:B, 0 ) ))} -> Apparel_Accessories_Winter | C70: BANDANA-HANKY-PAISLEY-ORANGE | D70: BANDANA-HANKY-PAISLEY-ORANGE | E70: LIVE | F70: B09FJDBMYQ
A71: Amazon | B71: {=IF(D71="","", INDEX(Product_Master!A:A, MATCH( INDEX(Pack_Master!B:B, MATCH(D71, Pack_Master!A:A, 0)), Product_Master!B:B, 0 ) ))} -> Apparel_Accessories_Winter | C71: BANDANA-HANKY-PAISLEY-PURPLE | D71: BANDANA-HANKY-PAISLEY-PURPLE | E71: LIVE | F71: B09FJD5NJY
A72: Amazon | B72: {=IF(D72="","", INDEX(Product_Master!A:A, MATCH( INDEX(Pack_Master!B:B, MATCH(D72, Pack_Master!A:A, 0)), Product_Master!B:B, 0 ) ))} -> Apparel_Accessories_Winter | C72: BANDANA-HANKY-PAISLEY-RED | D72: BANDANA-HANKY-PAISLEY-RED | E72: LIVE | F72: B09DXJ9C1J
A73: Amazon | B73: {=IF(D73="","", INDEX(Product_Master!A:A, MATCH( INDEX(Pack_Master!B:B, MATCH(D73, Pack_Master!A:A, 0)), Product_Master!B:B, 0 ) ))} -> Apparel_Accessories_Winter | C73: BANDANA-HANKY-PAISLEY-TURQUOISE | D73: BANDANA-HANKY-PAISLEY-TURQUOISE | E73: LIVE | F73: B09FJCW1MX
A74: Amazon | B74: {=IF(D74="","", INDEX(Product_Master!A:A, MATCH( INDEX(Pack_Master!B:B, MATCH(D74, Pack_Master!A:A, 0)), Product_Master!B:B, 0 ) ))} -> Apparel_Accessories_Winter | C74: BANDANA-HANKY-PAISLEY-WHITE | D74: BANDANA-HANKY-PAISLEY-WHITE | E74: LIVE | F74: B09DXHDRJV
A75: Amazon | B75: {=IF(D75="","", INDEX(Product_Master!A:A, MATCH( INDEX(Pack_Master!B:B, MATCH(D75, Pack_Master!A:A, 0)), Product_Master!B:B, 0 ) ))} -> Apparel_Accessories_Winter | C75: BANDANA-HANKY-PAISLEY-YELLOW | D75: BANDANA-HANKY-PAISLEY-YELLOW | E75: LIVE | F75: B0BNNGY2SM
A76: Amazon | B76: {=IF(D76="","", INDEX(Product_Master!A:A, MATCH( INDEX(Pack_Master!B:B, MATCH(D76, Pack_Master!A:A, 0)), Product_Master!B:B, 0 ) ))} -> Apparel_Accessories_Winter | C76: BANDANA-HANKY-PAISLEYPO3-BLACKBLUEORANGE | D76: BANDANA-HANKY-PAISLEYPO3-BLACKBLUEORANGE | E76: LIVE | F76: 6161142043042
A77: Amazon | B77: {=IF(D77="","", INDEX(Product_Master!A:A, MATCH( INDEX(Pack_Master!B:B, MATCH(D77, Pack_Master!A:A, 0)), Product_Master!B:B, 0 ) ))} -> Apparel_Accessories_Winter | C77: BANDANA-HANKY-PAISLEYPO3-BLACKNAVYWHITE | D77: BANDANA-HANKY-PAISLEYPO3-BLACKNAVYWHITE | E77: LIVE | F77: 6161142044339
A78: Amazon | B78: {=IF(D78="","", INDEX(Product_Master!A:A, MATCH( INDEX(Pack_Master!B:B, MATCH(D78, Pack_Master!A:A, 0)), Product_Master!B:B, 0 ) ))} -> Apparel_Accessories_Winter | C78: BANDANA-HANKY-PAISLEYPO3-BLACKREDWHITE | D78: BANDANA-HANKY-PAISLEYPO3-BLACKREDWHITE | E78: LIVE | F78: 6161142045008
A79: Amazon | B79: {=IF(D79="","", INDEX(Product_Master!A:A, MATCH( INDEX(Pack_Master!B:B, MATCH(D79, Pack_Master!A:A, 0)), Product_Master!B:B, 0 ) ))} -> Apparel_Accessories_Winter | C79: BANDANA-HANKY-PAISLEYPO3-ORANGENAVYWHITE | D79: BANDANA-HANKY-PAISLEYPO3-ORANGENAVYWHITE | E79: LIVE | F79: 6161142043769
A80: Amazon | B80: {=IF(D80="","", INDEX(Product_Master!A:A, MATCH( INDEX(Pack_Master!B:B, MATCH(D80, Pack_Master!A:A, 0)), Product_Master!B:B, 0 ) ))} -> Apparel_Accessories_Winter | C80: BANDANA-HANKY-PAISLEYPO3-ORANGEREDMAROON | D80: BANDANA-HANKY-PAISLEYPO3-ORANGEREDMAROON | E80: LIVE | F80: 6161142038109
A81: Amazon | B81: {=IF(D81="","", INDEX(Product_Master!A:A, MATCH( INDEX(Pack_Master!B:B, MATCH(D81, Pack_Master!A:A, 0)), Product_Master!B:B, 0 ) ))} -> Apparel_Accessories_Winter | C81: BANDANA-HANKY-PAISLEYPO3-REDNAVYWHITE | D81: BANDANA-HANKY-PAISLEYPO3-REDNAVYWHITE | E81: LIVE | F81: 6161142047057
A82: Amazon | B82: {=IF(D82="","", INDEX(Product_Master!A:A, MATCH( INDEX(Pack_Master!B:B, MATCH(D82, Pack_Master!A:A, 0)), Product_Master!B:B, 0 ) ))} -> Automotive_FaceMasks | C82: BANDANA-PACKOF10 | D82: BANDANA-PATTERN-MULTICOLOR-PK10 | E82: LIVE
A83: Amazon | B83: {=IF(D83="","", INDEX(Product_Master!A:A, MATCH( INDEX(Pack_Master!B:B, MATCH(D83, Pack_Master!A:A, 0)), Product_Master!B:B, 0 ) ))} -> Automotive_FaceMasks | C83: BANDANA-PACKOF5-PATTERN-BLACK | D83: BANDANA-PATTERN-BLACK-PK5 | E83: LIVE | F83: 6161142040270
A84: Amazon | B84: {=IF(D84="","", INDEX(Product_Master!A:A, MATCH( INDEX(Pack_Master!B:B, MATCH(D84, Pack_Master!A:A, 0)), Product_Master!B:B, 0 ) ))} -> Automotive_FaceMasks | C84: BANDANA-PACKOF5-PATTERN-BLUE | D84: BANDANA-PATTERN-BLUE-PK5 | E84: LIVE | F84: 6161142044940
A85: Amazon | B85: {=IF(D85="","", INDEX(Product_Master!A:A, MATCH( INDEX(Pack_Master!B:B, MATCH(D85, Pack_Master!A:A, 0)), Product_Master!B:B, 0 ) ))} -> Automotive_FaceMasks | C85: BANDANA-PACKOF5-PATTERN-CAMOREGULAR | D85: BANDANA-PATTERN-CAMOREGULAR-PK5 | E85: LIVE | F85: 6161142042465
A86: Amazon | B86: {=IF(D86="","", INDEX(Product_Master!A:A, MATCH( INDEX(Pack_Master!B:B, MATCH(D86, Pack_Master!A:A, 0)), Product_Master!B:B, 0 ) ))} -> Automotive_FaceMasks | C86: BANDANA-PACKOF5-PATTERN-MULTICOLOR | D86: BANDANA-PATTERN-MULTICOLOR-PK5 | E86: LIVE | F86: 6161142038611
A87: Amazon | B87: {=IF(D87="","", INDEX(Product_Master!A:A, MATCH( INDEX(Pack_Master!B:B, MATCH(D87, Pack_Master!A:A, 0)), Product_Master!B:B, 0 ) ))} -> Automotive_FaceMasks | C87: BANDANA-PACKOF5-PATTERN-SKULL | D87: BANDANA-PATTERN-SKULL-PK5 | E87: LIVE | F87: 6161142039427
A88: Amazon | B88: {=IF(D88="","", INDEX(Product_Master!A:A, MATCH( INDEX(Pack_Master!B:B, MATCH(D88, Pack_Master!A:A, 0)), Product_Master!B:B, 0 ) ))} -> Automotive_FaceMasks | C88: BANDANA-PACKOF5-SOLID-BLACK | D88: BANDANA-SOLID-BLACK-PK5 | E88: LIVE | F88: 6161142042243
A89: Amazon | B89: {=IF(D89="","", INDEX(Product_Master!A:A, MATCH( INDEX(Pack_Master!B:B, MATCH(D89, Pack_Master!A:A, 0)), Product_Master!B:B, 0 ) ))} -> Apparel_Caps_Beanies | C89: BEANIE-FOLD-2PLAIN-BLUE | D89: BEANIE-FOLD-2PLAIN-BLUE | E89: LIVE | F89: B0DNW1JRPF
A90: Amazon | B90: {=IF(D90="","", INDEX(Product_Master!A:A, MATCH( INDEX(Pack_Master!B:B, MATCH(D90, Pack_Master!A:A, 0)), Product_Master!B:B, 0 ) ))} -> Apparel_Caps_Beanies | C90: BEANIE-FOLD-2PLAIN-BROWN | D90: BEANIE-FOLD-2PLAIN-BROWN | E90: LIVE | F90: B0DNW43R4Q
A91: Amazon | B91: {=IF(D91="","", INDEX(Product_Master!A:A, MATCH( INDEX(Pack_Master!B:B, MATCH(D91, Pack_Master!A:A, 0)), Product_Master!B:B, 0 ) ))} -> Apparel_Caps_Beanies | C91: BEANIE-FOLD-2PLAIN-GREEN | D91: BEANIE-FOLD-2PLAIN-GREEN | E91: LIVE | F91: B0DNW3N6QQ
A92: Amazon | B92: {=IF(D92="","", INDEX(Product_Master!A:A, MATCH( INDEX(Pack_Master!B:B, MATCH(D92, Pack_Master!A:A, 0)), Product_Master!B:B, 0 ) ))} -> Apparel_Caps_Beanies | C92: BEANIE-FOLD-2PLAIN-MAROON | D92: BEANIE-FOLD-2PLAIN-MAROON | E92: LIVE | F92: B0DNW428ZZ
A93: Amazon | B93: {=IF(D93="","", INDEX(Product_Master!A:A, MATCH( INDEX(Pack_Master!B:B, MATCH(D93, Pack_Master!A:A, 0)), Product_Master!B:B, 0 ) ))} -> Apparel_Caps_Beanies | C93: BEANIE-FOLD-2PLAIN-OLIVE | D93: BEANIE-FOLD-2PLAIN-OLIVE | E93: LIVE | F93: B0DNW2JGFK
A94: Amazon | B94: {=IF(D94="","", INDEX(Product_Master!A:A, MATCH( INDEX(Pack_Master!B:B, MATCH(D94, Pack_Master!A:A, 0)), Product_Master!B:B, 0 ) ))} -> Apparel_Caps_Beanies | C94: BEANIE-FOLD-2PLAIN-YELLOW | D94: BEANIE-FOLD-2PLAIN-YELLOW | E94: LIVE | F94: B0DNW46NHN
A95: Amazon | B95: {=IF(D95="","", INDEX(Product_Master!A:A, MATCH( INDEX(Pack_Master!B:B, MATCH(D95, Pack_Master!A:A, 0)), Product_Master!B:B, 0 ) ))} -> Apparel_Caps_Beanies | C95: BEANIE-FOLD-BINGO-BLUE | D95: BEANIE-FOLD-BINGO-BLUE | E95: LIVE | F95: B0DRCQ3FG6
A96: Amazon | B96: {=IF(D96="","", INDEX(Product_Master!A:A, MATCH( INDEX(Pack_Master!B:B, MATCH(D96, Pack_Master!A:A, 0)), Product_Master!B:B, 0 ) ))} -> Apparel_Caps_Beanies | C96: BEANIE-FOLD-BINGO-BRICK | D96: BEANIE-FOLD-BINGO-BRICK | E96: LIVE | F96: B0DRCRZFYB
A97: Amazon | B97: {=IF(D97="","", INDEX(Product_Master!A:A, MATCH( INDEX(Pack_Master!B:B, MATCH(D97, Pack_Master!A:A, 0)), Product_Master!B:B, 0 ) ))} -> Apparel_Caps_Beanies | C97: BEANIE-FOLD-BINGO-BROWN | D97: BEANIE-FOLD-BINGO-BROWN | E97: LIVE | F97: B0DRCSXQPJ
A98: Amazon | B98: {=IF(D98="","", INDEX(Product_Master!A:A, MATCH( INDEX(Pack_Master!B:B, MATCH(D98, Pack_Master!A:A, 0)), Product_Master!B:B, 0 ) ))} -> Apparel_Caps_Beanies | C98: BEANIE-FOLD-BINGO-GREEN | D98: BEANIE-FOLD-BINGO-GREEN | E98: LIVE | F98: B0DRCRZV1M
A99: Amazon | B99: {=IF(D99="","", INDEX(Product_Master!A:A, MATCH( INDEX(Pack_Master!B:B, MATCH(D99, Pack_Master!A:A, 0)), Product_Master!B:B, 0 ) ))} -> Apparel_Caps_Beanies | C99: BEANIE-FOLD-BINGO-GREY | D99: BEANIE-FOLD-BINGO-GREY | E99: LIVE | F99: B0DRCSXH2Y
A100: Amazon | B100: {=IF(D100="","", INDEX(Product_Master!A:A, MATCH( INDEX(Pack_Master!B:B, MATCH(D100, Pack_Master!A:A, 0)), Product_Master!B:B, 0 ) ))} -> Apparel_Caps_Beanies | C100: BEANIE-FOLD-BINGO-LIGHTBROWN | D100: BEANIE-FOLD-BINGO-LIGHTBROWN | E100: LIVE | F100: B0DRCT14JQ
... A124: Amazon | B124: {=IF(D124="","", INDEX(Product_Master!A:A, MATCH( INDEX(Pack_Master!B:B, MATCH(D124, Pack_Master!A:A, 0)), Product_Master!B:B, 0 ) ))} -> Apparel_Caps_Beanies | C124: BEANIE-FOLD-PLAIN-SKIN | D124: BEANIE-FOLD-PLAIN-SKIN | E124: LIVE | F124: B0DK91PJY1
A125: Amazon | B125: {=IF(D125="","", INDEX(Product_Master!A:A, MATCH( INDEX(Pack_Master!B:B, MATCH(D125, Pack_Master!A:A, 0)), Product_Master!B:B, 0 ) ))} -> Apparel_Caps_Beanies | C125: BEANIE-FUR-SHORT-BEIGE | D125: BEANIE-SHORTFUR-BEIGE | E125: LIVE
A126: Amazon | B126: {=IF(D126="","", INDEX(Product_Master!A:A, MATCH( INDEX(Pack_Master!B:B, MATCH(D126, Pack_Master!A:A, 0)), Product_Master!B:B, 0 ) ))} -> Apparel_Caps_Beanies | C126: BEANIE-FUR-SHORT-BLACK | D126: BEANIE-SHORTFUR-BLACK | E126: LIVE
A127: Amazon | B127: {=IF(D127="","", INDEX(Product_Master!A:A, MATCH( INDEX(Pack_Master!B:B, MATCH(D127, Pack_Master!A:A, 0)), Product_Master!B:B, 0 ) ))} -> Apparel_Caps_Beanies | C127: BEANIE-FUR-SHORT-BLUE | D127: BEANIE-SHORTFUR-NAVYBLUE | E127: LIVE
A128: Amazon | B128: {=IF(D128="","", INDEX(Product_Master!A:A, MATCH( INDEX(Pack_Master!B:B, MATCH(D128, Pack_Master!A:A, 0)), Product_Master!B:B, 0 ) ))} -> Apparel_Caps_Beanies | C128: BEANIE-FUR-SHORT-BROWN | D128: BEANIE-SHORTFUR-BROWN | E128: LIVE
A129: Amazon | B129: {=IF(D129="","", INDEX(Product_Master!A:A, MATCH( INDEX(Pack_Master!B:B, MATCH(D129, Pack_Master!A:A, 0)), Product_Master!B:B, 0 ) ))} -> Apparel_Caps_Beanies | C129: BEANIE-FUR-SHORT-GREEN | D129: BEANIE-LONGFUR-GREEN | E129: LIVE
A130: Amazon | B130: {=IF(D130="","", INDEX(Product_Master!A:A, MATCH( INDEX(Pack_Master!B:B, MATCH(D130, Pack_Master!A:A, 0)), Product_Master!B:B, 0 ) ))} -> Apparel_Caps_Beanies | C130: BEANIE-FUR-SHORT-GREY | D130: BEANIE-SHORTFUR-GREY | E130: LIVE
A131: Amazon | B131: {=IF(D131="","", INDEX(Product_Master!A:A, MATCH( INDEX(Pack_Master!B:B, MATCH(D131, Pack_Master!A:A, 0)), Product_Master!B:B, 0 ) ))} -> Apparel_Caps_Beanies | C131: BEANIE-FUR-SHORT-MAROON | D131: BEANIE-SHORTFUR-RED | E131: LIVE
A132: Amazon | B132: {=IF(D132="","", INDEX(Product_Master!A:A, MATCH( INDEX(Pack_Master!B:B, MATCH(D132, Pack_Master!A:A, 0)), Product_Master!B:B, 0 ) ))} -> Apparel_Caps_Beanies | C132: BEANIE-FUR-SHORT-PURPLE | D132: BEANIE-SHORTFUR-PURPLE | E132: LIVE
A133: Amazon | B133: {=IF(D133="","", INDEX(Product_Master!A:A, MATCH( INDEX(Pack_Master!B:B, MATCH(D133, Pack_Master!A:A, 0)), Product_Master!B:B, 0 ) ))} -> Apparel_Caps_Beanies | C133: BEANIE-FUR-SHORT-RED | D133: BEANIE-SHORTFUR-RED | E133: LIVE
A134: Amazon | B134: {=IF(D134="","", INDEX(Product_Master!A:A, MATCH( INDEX(Pack_Master!B:B, MATCH(D134, Pack_Master!A:A, 0)), Product_Master!B:B, 0 ) ))} -> Apparel_Caps_Beanies | C134: BEANIE-FUR-SHORT-YELLOW | D134: BEANIE-FUR-SHORT-YELLOW | E134: LIVE | F134: 6161142038222
A135: Amazon | B135: {=IF(D135="","", INDEX(Product_Master!A:A, MATCH( INDEX(Pack_Master!B:B, MATCH(D135, Pack_Master!A:A, 0)), Product_Master!B:B, 0 ) ))} -> Apparel_Caps_Beanies | C135: BEANIE-FUROUT-SHORT-BLACK | D135: BEANIE-SHORT-FUROUT-BLACK | E135: LIVE
A136: Amazon | B136: {=IF(D136="","", INDEX(Product_Master!A:A, MATCH( INDEX(Pack_Master!B:B, MATCH(D136, Pack_Master!A:A, 0)), Product_Master!B:B, 0 ) ))} -> Apparel_Caps_Beanies | C136: BEANIE-FUROUT-SHORT-BLUE | D136: BEANIE-SHORT-FUROUT-BLUE | E136: LIVE
A137: Amazon | B137: {=IF(D137="","", INDEX(Product_Master!A:A, MATCH( INDEX(Pack_Master!B:B, MATCH(D137, Pack_Master!A:A, 0)), Product_Master!B:B, 0 ) ))} -> Apparel_Caps_Beanies | C137: BEANIE-FUROUT-SHORT-MAROON | D137: BEANIE-SHORT-FUROUT-MAROON | E137: LIVE
A138: Amazon | B138: {=IF(D138="","", INDEX(Product_Master!A:A, MATCH( INDEX(Pack_Master!B:B, MATCH(D138, Pack_Master!A:A, 0)), Product_Master!B:B, 0 ) ))} -> Apparel_Caps_Beanies | C138: BEANIE-LONG-SLOUCHY-BLACK | D138: BEANIE-LONGFUR-BLACK | E138: LIVE | F138: B0BKXMQQZQ
A139: Amazon | B139: {=IF(D139="","", INDEX(Product_Master!A:A, MATCH( INDEX(Pack_Master!B:B, MATCH(D139, Pack_Master!A:A, 0)), Product_Master!B:B, 0 ) ))} -> Apparel_Caps_Beanies | C139: BEANIE-LONGFUR-BEIGE | D139: BEANIE-LONGFUR-BEIGE | E139: LIVE | F139: B09J23GML8
A140: Amazon | B140: {=IF(D140="","", INDEX(Product_Master!A:A, MATCH( INDEX(Pack_Master!B:B, MATCH(D140, Pack_Master!A:A, 0)), Product_Master!B:B, 0 ) ))} -> Apparel_Caps_Beanies | C140: BEANIE-LONGFUR-BLACK | D140: BEANIE-LONGFUR-BLACK | E140: LIVE | F140: B09J242G5H
A141: Amazon | B141: {=IF(D141="","", INDEX(Product_Master!A:A, MATCH( INDEX(Pack_Master!B:B, MATCH(D141, Pack_Master!A:A, 0)), Product_Master!B:B, 0 ) ))} -> Apparel_Caps_Beanies | C141: BEANIE-LONGFUR-BROWN | D141: BEANIE-LONGFUR-BROWN | E141: LIVE | F141: B09M69R11K
A142: Amazon | B142: {=IF(D142="","", INDEX(Product_Master!A:A, MATCH( INDEX(Pack_Master!B:B, MATCH(D142, Pack_Master!A:A, 0)), Product_Master!B:B, 0 ) ))} -> Apparel_Caps_Beanies | C142: BEANIE-LONGFUR-CHARCOAL | D142: BEANIE-LONGFUR-CHARCOAL | E142: LIVE | F142: B09J23SY56
A143: Amazon | B143: {=IF(D143="","", INDEX(Product_Master!A:A, MATCH( INDEX(Pack_Master!B:B, MATCH(D143, Pack_Master!A:A, 0)), Product_Master!B:B, 0 ) ))} -> Apparel_Caps_Beanies | C143: BEANIE-LONGFUR-GREEN | D143: BEANIE-LONGFUR-GREEN | E143: LIVE | F143: B09M6KF88F
A144: Amazon | B144: {=IF(D144="","", INDEX(Product_Master!A:A, MATCH( INDEX(Pack_Master!B:B, MATCH(D144, Pack_Master!A:A, 0)), Product_Master!B:B, 0 ) ))} -> Apparel_Caps_Beanies | C144: BEANIE-LONGFUR-MAROON | D144: BEANIE-LONGFUR-MAROON | E144: LIVE | F144: B09J24DSYS
A145: Amazon | B145: {=IF(D145="","", INDEX(Product_Master!A:A, MATCH( INDEX(Pack_Master!B:B, MATCH(D145, Pack_Master!A:A, 0)), Product_Master!B:B, 0 ) ))} -> Apparel_Caps_Beanies | C145: BEANIE-LONGFUR-NAVYBLUE | D145: BEANIE-LONGFUR-NAVYBLUE | E145: LIVE | F145: B09J23JYDP
A146: Amazon | B146: {=IF(D146="","", INDEX(Product_Master!A:A, MATCH( INDEX(Pack_Master!B:B, MATCH(D146, Pack_Master!A:A, 0)), Product_Master!B:B, 0 ) ))} -> Apparel_Caps_Beanies | C146: BEANIE-SHORT-ZIPPER-MAROON-PRIME | D146: BEANIE-SHORT-ZIPPER-MAROON | E146: LIVE
A147: Amazon | B147: {=IF(D147="","", INDEX(Product_Master!A:A, MATCH( INDEX(Pack_Master!B:B, MATCH(D147, Pack_Master!A:A, 0)), Product_Master!B:B, 0 ) ))} -> Apparel_Caps_Beanies | C147: BEANIE-SHORTFUR-BEIGE | D147: BEANIE-SHORTFUR-BEIGE | E147: LIVE | F147: B09LQWYXSQ
A148: Amazon | B148: {=IF(D148="","", INDEX(Product_Master!A:A, MATCH( INDEX(Pack_Master!B:B, MATCH(D148, Pack_Master!A:A, 0)), Product_Master!B:B, 0 ) ))} -> Apparel_Caps_Beanies | C148: BEANIE-SHORTFUR-BLACK | D148: BEANIE-SHORTFUR-BLACK | E148: LIVE | F148: B09LQZTFV3
A149: Amazon | B149: {=IF(D149="","", INDEX(Product_Master!A:A, MATCH( INDEX(Pack_Master!B:B, MATCH(D149, Pack_Master!A:A, 0)), Product_Master!B:B, 0 ) ))} -> Apparel_Caps_Beanies | C149: BEANIE-SHORTFUR-BLUE | D149: BEANIE-SHORTFUR-NAVYBLUE | E149: LIVE | F149: B09LR4DFPZ
A150: Amazon | B150: {=IF(D150="","", INDEX(Product_Master!A:A, MATCH( INDEX(Pack_Master!B:B, MATCH(D150, Pack_Master!A:A, 0)), Product_Master!B:B, 0 ) ))} -> Apparel_Caps_Beanies | C150: BEANIE-SHORTFUR-BROWN | D150: BEANIE-SHORTFUR-BROWN | E150: LIVE | F150: B09N1SK8BT
A151: Amazon | B151: {=IF(D151="","", INDEX(Product_Master!A:A, MATCH( INDEX(Pack_Master!B:B, MATCH(D151, Pack_Master!A:A, 0)), Product_Master!B:B, 0 ) ))} -> Apparel_Caps_Beanies | C151: BEANIE-SHORTFUR-CHARCOAL | D151: BEANIE-SHORTFUR-GREY | E151: LIVE | F151: B09LQWL46Y
A152: Amazon | B152: {=IF(D152="","", INDEX(Product_Master!A:A, MATCH( INDEX(Pack_Master!B:B, MATCH(D152, Pack_Master!A:A, 0)), Product_Master!B:B, 0 ) ))} -> Apparel_Caps_Beanies | C152: BEANIE-SHORTFUR-GREY | D152: BEANIE-SHORTFUR-GREY | E152: LIVE | F152: B09LQY57XD
A153: Amazon | B153: {=IF(D153="","", INDEX(Product_Master!A:A, MATCH( INDEX(Pack_Master!B:B, MATCH(D153, Pack_Master!A:A, 0)), Product_Master!B:B, 0 ) ))} -> Apparel_Caps_Beanies | C153: BEANIE-SHORTFUR-MESH-BEIGE | D153: BEANIE-SHORTFUR-MESH-BEIGE | E153: LIVE | F153: B09L7RB9BL
A154: Amazon | B154: {=IF(D154="","", INDEX(Product_Master!A:A, MATCH( INDEX(Pack_Master!B:B, MATCH(D154, Pack_Master!A:A, 0)), Product_Master!B:B, 0 ) ))} -> Apparel_Caps_Beanies | C154: BEANIE-SHORTFUR-MESH-BLACK | D154: BEANIE-SHORTFUR-MESH-BLACK | E154: LIVE | F154: B09L7S56FL
A155: Amazon | B155: {=IF(D155="","", INDEX(Product_Master!A:A, MATCH( INDEX(Pack_Master!B:B, MATCH(D155, Pack_Master!A:A, 0)), Product_Master!B:B, 0 ) ))} -> Apparel_Caps_Beanies | C155: BEANIE-SHORTFUR-MESH-GREEN | D155: BEANIE-SHORTFUR-MESH-GREEN | E155: LIVE | F155: B09L7S42W4
A156: Amazon | B156: {=IF(D156="","", INDEX(Product_Master!A:A, MATCH( INDEX(Pack_Master!B:B, MATCH(D156, Pack_Master!A:A, 0)), Product_Master!B:B, 0 ) ))} -> Apparel_Caps_Beanies | C156: BEANIE-SHORTFUR-MESH-MAROON | D156: BEANIE-SHORTFUR-MESH-MAROON | E156: LIVE | F156: B09L7QY9CZ
A157: Amazon | B157: {=IF(D157="","", INDEX(Product_Master!A:A, MATCH( INDEX(Pack_Master!B:B, MATCH(D157, Pack_Master!A:A, 0)), Product_Master!B:B, 0 ) ))} -> Apparel_Caps_Beanies | C157: BEANIE-SHORTFUR-MESH-NAVYBLUE | D157: BEANIE-SHORTFUR-MESH-NAVYBLUE | E157: LIVE | F157: B09L7SFHHT
A158: Amazon | B158: {=IF(D158="","", INDEX(Product_Master!A:A, MATCH( INDEX(Pack_Master!B:B, MATCH(D158, Pack_Master!A:A, 0)), Product_Master!B:B, 0 ) ))} -> Apparel_Caps_Beanies | C158: BEANIE-SHORTFUR-NAVYBLUE | D158: BEANIE-SHORTFUR-NAVYBLUE | E158: LIVE | F158: B09LQWD4PM
... A166: Amazon | B166: {=IF(D166="","", INDEX(Product_Master!A:A, MATCH( INDEX(Pack_Master!B:B, MATCH(D166, Pack_Master!A:A, 0)), Product_Master!B:B, 0 ) ))} -> Apparel_Caps_Beanies | C166: BEANIE-SLOUCHY-LONG-MAROON | D166: BEANIE-LONGFUR-MAROON | E166: LIVE | F166: B083ZZLNCS
A167: Amazon | B167: {=IF(D167="","", INDEX(Product_Master!A:A, MATCH( INDEX(Pack_Master!B:B, MATCH(D167, Pack_Master!A:A, 0)), Product_Master!B:B, 0 ) ))} -> Apparel_Caps_Beanies | C167: BEANIE-SLOUCHY-LONG-NAVYBLUE | D167: BEANIE-LONGFUR-NAVYBLUE | E167: LIVE
A168: Amazon | B168: {=IF(D168="","", INDEX(Product_Master!A:A, MATCH( INDEX(Pack_Master!B:B, MATCH(D168, Pack_Master!A:A, 0)), Product_Master!B:B, 0 ) ))} -> Apparel_Caps_Beanies | C168: BEANIE-WOOL-CREAM | D168: BEANIE-WOOL-CREAM | E168: LIVE
A169: Amazon | B169: {=IF(D169="","", INDEX(Product_Master!A:A, MATCH( INDEX(Pack_Master!B:B, MATCH(D169, Pack_Master!A:A, 0)), Product_Master!B:B, 0 ) ))} -> Apparel_Caps_Beanies | C169: BEANIE-WOOL-OFFWHITE | D169: BEANIE-WOOL-OFFWHITE | E169: LIVE
...

Sheet Product_Master
A1: Category | B1: Master_SKU | C1: Suppier_Code | D1: Supplier | E1: Mfg_Cost | F1: Unit_Box_Cost | G1: Labeling_Labor | H1: Inbound_Transport | I1: Total_Unit_COGS | J1: HSN | K1: GST_Rate | L1: Brand | M1: Lifecycle_Status
A2: Apparel_Caps_Beanies | B2: BEANIE-FOLD-2PLAIN-BLUE | C2: tbd | D2: Dearex Hosiery Factory | E2: 99 | F2: 5 | G2: 2 | H2: 1 | I2: =ROUND(E2 + F2 + G2 + H2, 2) -> 107 | K2: 5 | M2: Active
A3: Apparel_Caps_Beanies | B3: BEANIE-FOLD-2PLAIN-BROWN | C3: tbd | D3: Dearex Hosiery Factory | E3: 99 | F3: 5 | G3: 2 | H3: 1 | I3: =ROUND(E3 + F3 + G3 + H3, 2) -> 107 | K3: 5 | M3: Active
A4: Apparel_Caps_Beanies | B4: BEANIE-FOLD-2PLAIN-GREEN | C4: tbd | D4: Dearex Hosiery Factory | E4: 99 | F4: 5 | G4: 2 | H4: 1 | I4: =ROUND(E4 + F4 + G4 + H4, 2) -> 107 | K4: 5 | M4: Active
A5: Apparel_Caps_Beanies | B5: BEANIE-FOLD-2PLAIN-MAROON | C5: tbd | D5: Dearex Hosiery Factory | E5: 99 | F5: 5 | G5: 2 | H5: 1 | I5: =ROUND(E5 + F5 + G5 + H5, 2) -> 107 | K5: 5 | M5: Active
A6: Apparel_Caps_Beanies | B6: BEANIE-FOLD-2PLAIN-OLIVE | C6: tbd | D6: Dearex Hosiery Factory | E6: 99 | F6: 5 | G6: 2 | H6: 1 | I6: =ROUND(E6 + F6 + G6 + H6, 2) -> 107 | K6: 5 | M6: Active
A7: Apparel_Caps_Beanies | B7: BEANIE-FOLD-2PLAIN-YELLOW | C7: tbd | D7: Dearex Hosiery Factory | E7: 99 | F7: 5 | G7: 2 | H7: 1 | I7: =ROUND(E7 + F7 + G7 + H7, 2) -> 107 | K7: 5 | M7: Active
A8: Apparel_Caps_Beanies | B8: BEANIE-FOLD-BINGO-BLUE | C8: tbd | D8: Dearex Hosiery Factory | E8: 99 | F8: 5 | G8: 2 | H8: 1 | I8: =ROUND(E8 + F8 + G8 + H8, 2) -> 107 | K8: 5 | M8: Active
A9: Apparel_Caps_Beanies | B9: BEANIE-FOLD-BINGO-BRICK | C9: tbd | D9: Dearex Hosiery Factory | E9: 99 | F9: 5 | G9: 2 | H9: 1 | I9: =ROUND(E9 + F9 + G9 + H9, 2) -> 107 | K9: 5 | M9: Active
A10: Apparel_Caps_Beanies | B10: BEANIE-FOLD-BINGO-BROWN | C10: tbd | D10: Dearex Hosiery Factory | E10: 99 | F10: 5 | G10: 2 | H10: 1 | I10: =ROUND(E10 + F10 + G10 + H10, 2) -> 107 | K10: 5 | M10: Active
A11: Apparel_Caps_Beanies | B11: BEANIE-FOLD-BINGO-GREEN | C11: tbd | D11: Dearex Hosiery Factory | E11: 99 | F11: 5 | G11: 2 | H11: 1 | I11: =ROUND(E11 + F11 + G11 + H11, 2) -> 107 | K11: 5 | M11: Active
A12: Apparel_Caps_Beanies | B12: BEANIE-FOLD-BINGO-GREY | C12: tbd | D12: Dearex Hosiery Factory | E12: 99 | F12: 5 | G12: 2 | H12: 1 | I12: =ROUND(E12 + F12 + G12 + H12, 2) -> 107 | K12: 5 | M12: Active
A13: Apparel_Caps_Beanies | B13: BEANIE-FOLD-BINGO-LIGHTBROWN | C13: tbd | D13: Dearex Hosiery Factory | E13: 99 | F13: 5 | G13: 2 | H13: 1 | I13: =ROUND(E13 + F13 + G13 + H13, 2) -> 107 | K13: 5 | M13: Active
A14: Apparel_Caps_Beanies | B14: BEANIE-FOLD-BRAND-BLUE | C14: Brand Fold Fur | D14: Dearex Hosiery Factory | E14: 99 | F14: 5 | G14: 2 | H14: 1 | I14: =ROUND(E14 + F14 + G14 + H14, 2) -> 107 | K14: 5
A15: Apparel_Caps_Beanies | B15: BEANIE-FOLD-BRAND-GREEN | C15: Brand Fold Fur | D15: Dearex Hosiery Factory | E15: 99 | F15: 5 | G15: 2 | H15: 1 | I15: =ROUND(E15 + F15 + G15 + H15, 2) -> 107 | K15: 5
A16: Apparel_Caps_Beanies | B16: BEANIE-FOLD-BRAND-GREY | C16: Brand Fold Fur | D16: Dearex Hosiery Factory | E16: 99 | F16: 5 | G16: 2 | H16: 1 | I16: =ROUND(E16 + F16 + G16 + H16, 2) -> 107 | K16: 5
A17: Apparel_Caps_Beanies | B17: BEANIE-FOLD-BRAND-LIGHTBROWN | C17: Brand Fold Fur | D17: Dearex Hosiery Factory | E17: 99 | F17: 5 | G17: 2 | H17: 1 | I17: =ROUND(E17 + F17 + G17 + H17, 2) -> 107 | K17: 5
A18: Apparel_Caps_Beanies | B18: BEANIE-FOLD-BRAND-MAROON | C18: Brand Fold Fur | D18: Dearex Hosiery Factory | E18: 99 | F18: 5 | G18: 2 | H18: 1 | I18: =ROUND(E18 + F18 + G18 + H18, 2) -> 107 | K18: 5
A19: Apparel_Caps_Beanies | B19: BEANIE-FOLD-BRAND-SKIN | C19: Brand Fold Fur | D19: Dearex Hosiery Factory | E19: 99 | F19: 5 | G19: 2 | H19: 1 | I19: =ROUND(E19 + F19 + G19 + H19, 2) -> 107 | K19: 5
A20: Apparel_Caps_Beanies | B20: BEANIE-FOLD-CHECK-BLUE | C20: tbd | D20: Dearex Hosiery Factory | E20: 99 | F20: 5 | G20: 2 | H20: 1 | I20: =ROUND(E20 + F20 + G20 + H20, 2) -> 107 | K20: 5 | M20: Active
A21: Apparel_Caps_Beanies | B21: BEANIE-FOLD-CHECK-GREY | C21: tbd | D21: Dearex Hosiery Factory | E21: 99 | F21: 5 | G21: 2 | H21: 1 | I21: =ROUND(E21 + F21 + G21 + H21, 2) -> 107 | K21: 5 | M21: Active
A22: Apparel_Caps_Beanies | B22: BEANIE-FOLD-CHECK-LIGHTBROWN | C22: tbd | D22: Dearex Hosiery Factory | E22: 99 | F22: 5 | G22: 2 | H22: 1 | I22: =ROUND(E22 + F22 + G22 + H22, 2) -> 107 | K22: 5 | M22: Active
A23: Apparel_Caps_Beanies | B23: BEANIE-FOLD-CHECK-MAROON | C23: tbd | D23: Dearex Hosiery Factory | E23: 99 | F23: 5 | G23: 2 | H23: 1 | I23: =ROUND(E23 + F23 + G23 + H23, 2) -> 107 | K23: 5 | M23: Active
A24: Apparel_Caps_Beanies | B24: BEANIE-FOLD-CHECK-OLIVE | C24: tbd | D24: Dearex Hosiery Factory | E24: 99 | F24: 5 | G24: 2 | H24: 1 | I24: =ROUND(E24 + F24 + G24 + H24, 2) -> 107 | K24: 5 | M24: Active
A25: Apparel_Caps_Beanies | B25: BEANIE-FOLD-KING-ASHGREEN | C25: tbd | D25: Dearex Hosiery Factory | E25: 99 | F25: 5 | G25: 2 | H25: 1 | I25: =ROUND(E25 + F25 + G25 + H25, 2) -> 107 | K25: 5
A26: Apparel_Caps_Beanies | B26: BEANIE-FOLD-KING-BLUE | C26: tbd | D26: Dearex Hosiery Factory | E26: 99 | F26: 5 | G26: 2 | H26: 1 | I26: =ROUND(E26 + F26 + G26 + H26, 2) -> 107 | K26: 5 | M26: Active
A27: Apparel_Caps_Beanies | B27: BEANIE-FOLD-KING-BROWN | C27: tbd | D27: Dearex Hosiery Factory | E27: 99 | F27: 5 | G27: 2 | H27: 1 | I27: =ROUND(E27 + F27 + G27 + H27, 2) -> 107 | K27: 5 | M27: Active
A28: Apparel_Caps_Beanies | B28: BEANIE-FOLD-KING-GREEN | C28: tbd | D28: Dearex Hosiery Factory | E28: 99 | F28: 5 | G28: 2 | H28: 1 | I28: =ROUND(E28 + F28 + G28 + H28, 2) -> 107 | K28: 5 | M28: Active
A29: Apparel_Caps_Beanies | B29: BEANIE-FOLD-KING-GREY | C29: tbd | D29: Dearex Hosiery Factory | E29: 99 | F29: 5 | G29: 2 | H29: 1 | I29: =ROUND(E29 + F29 + G29 + H29, 2) -> 107 | K29: 5 | M29: Active
A30: Apparel_Caps_Beanies | B30: BEANIE-FOLD-KING-LIGHT GREEN | C30: tbd | D30: Dearex Hosiery Factory | E30: 99 | F30: 5 | G30: 2 | H30: 1 | I30: =ROUND(E30 + F30 + G30 + H30, 2) -> 107 | K30: 5 | M30: Active
A31: Apparel_Caps_Beanies | B31: BEANIE-FOLD-KING-LIGHTGREEN | C31: tbd | D31: Dearex Hosiery Factory | I31: =ROUND(E31 + F31 + G31 + H31, 2) -> 0 | K31: 5
A32: Apparel_Caps_Beanies | B32: BEANIE-FOLD-KING-MAROON | C32: tbd | D32: Dearex Hosiery Factory | E32: 99 | F32: 5 | G32: 2 | H32: 1 | I32: =ROUND(E32 + F32 + G32 + H32, 2) -> 107 | K32: 5 | M32: Active
A33: Apparel_Caps_Beanies | B33: BEANIE-FOLD-PLAIN-BLACK | C33: tbd | D33: Dearex Hosiery Factory | E33: 99 | F33: 5 | G33: 2 | H33: 1 | I33: =ROUND(E33 + F33 + G33 + H33, 2) -> 107 | K33: 5
A34: Apparel_Caps_Beanies | B34: BEANIE-FOLD-PLAIN-BLUE | C34: tbd | D34: Dearex Hosiery Factory | E34: 99 | F34: 5 | G34: 2 | H34: 1 | I34: =ROUND(E34 + F34 + G34 + H34, 2) -> 107 | K34: 5
A35: Apparel_Caps_Beanies | B35: BEANIE-FOLD-PLAIN-DARKGREEN | C35: tbd | D35: Dearex Hosiery Factory | E35: 99 | F35: 5 | G35: 2 | H35: 1 | I35: =ROUND(E35 + F35 + G35 + H35, 2) -> 107 | K35: 5
A36: Apparel_Caps_Beanies | B36: BEANIE-FOLD-PLAIN-GREEN | C36: tbd | D36: Dearex Hosiery Factory | E36: 99 | F36: 5 | G36: 2 | H36: 1 | I36: =ROUND(E36 + F36 + G36 + H36, 2) -> 107 | K36: 5
A37: Apparel_Caps_Beanies | B37: BEANIE-FOLD-PLAIN-GREY | C37: tbd | D37: Dearex Hosiery Factory | E37: 99 | F37: 5 | G37: 2 | H37: 1 | I37: =ROUND(E37 + F37 + G37 + H37, 2) -> 107 | K37: 5
A38: Apparel_Caps_Beanies | B38: BEANIE-FOLD-PLAIN-OLIVE | C38: tbd | E38: 99 | F38: 5 | G38: 2 | H38: 1 | I38: =ROUND(E38 + F38 + G38 + H38, 2) -> 107 | K38: 5
A39: Apparel_Caps_Beanies | B39: BEANIE-FOLD-PLAIN-SKIN | C39: tbd | E39: 99 | F39: 5 | G39: 2 | H39: 1 | I39: =ROUND(E39 + F39 + G39 + H39, 2) -> 107 | K39: 5
A40: Apparel_Caps_Beanies | B40: BEANIE-FUR-SHORT-RED | C40: tbd | E40: 99 | F40: 5 | G40: 2 | H40: 1 | I40: =ROUND(E40 + F40 + G40 + H40, 2) -> 107 | K40: 5 | M40: Active
A41: Apparel_Caps_Beanies | B41: BEANIE-FUR-SHORT-YELLOW | C41: tbd | E41: 99 | F41: 5 | G41: 2 | H41: 1 | I41: =ROUND(E41 + F41 + G41 + H41, 2) -> 107 | K41: 5 | M41: Active
A42: Apparel_Caps_Beanies | B42: BEANIE-LONGFUR-BEIGE | C42: tbd | E42: 99 | F42: 5 | G42: 2 | H42: 1 | I42: =ROUND(E42 + F42 + G42 + H42, 2) -> 107 | K42: 5 | M42: Active
A43: Apparel_Caps_Beanies | B43: BEANIE-LONGFUR-BLACK | C43: tbd | E43: 99 | F43: 5 | G43: 2 | H43: 1 | I43: =ROUND(E43 + F43 + G43 + H43, 2) -> 107 | K43: 5 | M43: Active
A44: Apparel_Caps_Beanies | B44: BEANIE-LONGFUR-BROWN | C44: tbd | E44: 99 | F44: 5 | G44: 2 | H44: 1 | I44: =ROUND(E44 + F44 + G44 + H44, 2) -> 107 | K44: 5 | M44: Active
A45: Apparel_Caps_Beanies | B45: BEANIE-LONGFUR-CHARCOAL | C45: tbd | E45: 99 | F45: 5 | G45: 2 | H45: 1 | I45: =ROUND(E45 + F45 + G45 + H45, 2) -> 107 | K45: 5 | M45: Active
A46: Apparel_Caps_Beanies | B46: BEANIE-LONGFUR-GREEN | C46: tbd | E46: 99 | F46: 5 | G46: 2 | H46: 1 | I46: =ROUND(E46 + F46 + G46 + H46, 2) -> 107 | K46: 5 | M46: Inactive
A47: Apparel_Caps_Beanies | B47: BEANIE-LONGFUR-MAROON | C47: tbd | E47: 99 | F47: 5 | G47: 2 | H47: 1 | I47: =ROUND(E47 + F47 + G47 + H47, 2) -> 107 | K47: 5 | M47: Active
A48: Apparel_Caps_Beanies | B48: BEANIE-LONGFUR-NAVYBLUE | C48: tbd | E48: 99 | F48: 5 | G48: 2 | H48: 1 | I48: =ROUND(E48 + F48 + G48 + H48, 2) -> 107 | K48: 5 | M48: Active
A49: Apparel_Caps_Beanies | B49: BEANIE-SHORTFUR-BEIGE | C49: tbd | E49: 99 | F49: 5 | G49: 2 | H49: 1 | I49: =ROUND(E49 + F49 + G49 + H49, 2) -> 107 | K49: 5 | M49: Active
A50: Apparel_Caps_Beanies | B50: BEANIE-SHORTFUR-BLACK | C50: tbd | E50: 99 | F50: 5 | G50: 2 | H50: 1 | I50: =ROUND(E50 + F50 + G50 + H50, 2) -> 107 | K50: 5 | M50: Active
A51: Apparel_Caps_Beanies | B51: BEANIE-SHORTFUR-BROWN | C51: tbd | E51: 99 | F51: 5 | G51: 2 | H51: 1 | I51: =ROUND(E51 + F51 + G51 + H51, 2) -> 107 | K51: 5 | M51: Active
... A65: Apparel_Caps_Beanies | B65: BEANIE-WOOL-OFFWHITE | C65: tbd | E65: 99 | F65: 5 | G65: 2 | H65: 1 | I65: =ROUND(E65 + F65 + G65 + H65, 2) -> 107 | K65: 5 | M65: Inactive
A66: Apparel_Caps_Beanies | B66: CAP-BASEBALL-FULLNET-BLACK | C66: tbd | I66: =ROUND(E66 + F66 + G66 + H66, 2) -> 0 | K66: 5
A67: Apparel_Caps_Beanies | B67: CAP-BASEBALL-FULLNET-WHITE | C67: tbd | I67: =ROUND(E67 + F67 + G67 + H67, 2) -> 0 | K67: 5
A68: Apparel_Caps_Beanies | B68: CAP-BASEBALL-LO | C68: tbd | E68: 99 | F68: 5 | G68: 2 | H68: 1 | I68: =ROUND(E68 + F68 + G68 + H68, 2) -> 107 | K68: 5 | M68: Inactive
A69: Apparel_Caps_Beanies | B69: CAP-BASEBALL-NET-HALF-BLACK | C69: tbd | E69: 60 | F69: 5 | G69: 2 | H69: 1 | I69: =ROUND(E69 + F69 + G69 + H69, 2) -> 68 | K69: 5
A70: Apparel_Caps_Beanies | B70: CAP-BASEBALL-NET-HALF-CHARCOAL | C70: tbd | K70: 5
A71: Apparel_Caps_Beanies | B71: CAP-BASEBALL-NET-HALF-GREY | C71: tbd | K71: 5
A72: Apparel_Caps_Beanies | B72: CAP-BASEBALL-NET-HALF-NAVYBLUE | C72: tbd | K72: 5
A73: Apparel_Caps_Beanies | B73: CAP-BASEBALL-NET-HALF-OLIVE | C73: tbd | K73: 5
A74: Apparel_Caps_Beanies | B74: CAP-BASEBALL-NET-HALF-PINK | C74: tbd | E74: 60 | F74: 5 | G74: 2 | H74: 1 | I74: =ROUND(E74 + F74 + G74 + H74, 2) -> 68 | K74: 5
A75: Apparel_Caps_Beanies | B75: CAP-BASEBALL-NET-HALF-RED | C75: tbd | K75: 5
A76: Apparel_Caps_Beanies | B76: CAP-BASEBALL-NET-HALF-WHITE | C76: tbd | E76: 60 | F76: 5 | G76: 2 | H76: 1 | I76: =ROUND(E76 + F76 + G76 + H76, 2) -> 68 | K76: 5
A77: Apparel_Caps_Beanies | B77: CAP-BASEBALL-NY-BLACKBLACK | C77: tbd | I77: =ROUND(E77 + F77 + G77 + H77, 2) -> 0 | K77: 5
A78: Apparel_Caps_Beanies | B78: CAP-BASEBALL-NY-BLACKWHITE | C78: tbd | I78: =ROUND(E78 + F78 + G78 + H78, 2) -> 0 | K78: 5
A79: Apparel_Caps_Beanies | B79: CAP-BASEBALL-NY-CHARCOALWHITE | C79: NY Charcoal | E79: 100 | F79: 2 | G79: 1 | H79: 1 | I79: =ROUND(E79 + F79 + G79 + H79, 2) -> 104 | K79: 5 | M79: Active
A80: Apparel_Caps_Beanies | B80: CAP-BASEBALL-NY-GREYWHITE | C80: tbd | I80: =ROUND(E80 + F80 + G80 + H80, 2) -> 0 | K80: 5
A81: Apparel_Caps_Beanies | B81: CAP-BASEBALL-NY-NAVYWHITE | C81: tbd | I81: =ROUND(E81 + F81 + G81 + H81, 2) -> 0 | K81: 5
A82: Apparel_Caps_Beanies | B82: CAP-BASEBALL-NY-PO2-BLACKBLACK | C82: tbd | E82: 99 | F82: 5 | G82: 2 | H82: 1 | I82: =ROUND(E82 + F82 + G82 + H82, 2) -> 107 | K82: 5 | M82: InActive
A83: Apparel_Caps_Beanies | B83: CAP-BASEBALL-NY-PO2-BLACKOLIVE | C83: tbd | E83: 99 | F83: 5 | G83: 2 | H83: 1 | I83: =ROUND(E83 + F83 + G83 + H83, 2) -> 107 | K83: 5 | M83: InActive
A84: Apparel_Caps_Beanies | B84: CAP-BASEBALL-NY-PO2-GREYBLACK | C84: tbd | I84: =ROUND(E84 + F84 + G84 + H84, 2) -> 0 | K84: 5
A85: Apparel_Caps_Beanies | B85: CAP-BASEBALL-NY-PO2-NAVYBLACK | C85: tbd | E85: 99 | F85: 5 | G85: 2 | H85: 1 | I85: =ROUND(E85 + F85 + G85 + H85, 2) -> 107 | K85: 5 | M85: InActive
A86: Apparel_Caps_Beanies | B86: CAP-BASEBALL-NY-PO2-WHITEBLACK | C86: tbd | I86: =ROUND(E86 + F86 + G86 + H86, 2) -> 0 | K86: 5
A87: Apparel_Caps_Beanies | B87: CAP-BASEBALL-NY-WHITEBLACK | C87: tbd | I87: =ROUND(E87 + F87 + G87 + H87, 2) -> 0 | K87: 5
A88: Apparel_Caps_Beanies | B88: CAP-BASEBALL-PLAIN-AQUA | C88: tbd | D88: Rahaman Caps | E88: 83 | F88: 2 | G88: 1 | H88: 1 | I88: =ROUND(E88 + F88 + G88 + H88, 2) -> 87 | J88: 6505 | K88: 5 | M88: Active
A89: Apparel_Caps_Beanies | B89: CAP-BASEBALL-PLAIN-BEIGE | C89: C - 29 - Beige | D89: A.M Traders | E89: 83 | F89: 2 | G89: 1 | H89: 1 | I89: =ROUND(E89 + F89 + G89 + H89, 2) -> 87 | J89: 6505 | K89: 5 | M89: Active
A90: Apparel_Caps_Beanies | B90: CAP-BASEBALL-PLAIN-BLACK | C90: C - 29 - Black | D90: A.M Traders | E90: 83 | F90: 2 | G90: 1 | H90: 1 | I90: =ROUND(E90 + F90 + G90 + H90, 2) -> 87 | J90: 6505 | K90: 5 | M90: Active
A91: Apparel_Caps_Beanies | B91: CAP-BASEBALL-PLAIN-BLUE | C91: tbd | D91: Rahaman Caps | E91: 83 | F91: 2 | G91: 1 | H91: 1 | I91: =ROUND(E91 + F91 + G91 + H91, 2) -> 87 | J91: 6505 | K91: 5 | M91: Active
A92: Apparel_Caps_Beanies | B92: CAP-BASEBALL-PLAIN-CAMOUFLAGE | C92: tbd | D92: Rahaman Caps | E92: 83 | F92: 2 | G92: 1 | H92: 1 | I92: =ROUND(E92 + F92 + G92 + H92, 2) -> 87 | J92: 6505 | K92: 5 | M92: Active
A93: Apparel_Caps_Beanies | B93: CAP-BASEBALL-PLAIN-CHARCOAL | C93: C - 29 - Dark Grey | D93: A.M Traders | E93: 83 | F93: 2 | G93: 1 | H93: 1 | I93: =ROUND(E93 + F93 + G93 + H93, 2) -> 87 | J93: 6505 | K93: 5 | M93: Active
A94: Apparel_Caps_Beanies | B94: CAP-BASEBALL-PLAIN-GREY | C94: C - 29 - Grey(5) | D94: A.M Traders | E94: 83 | F94: 2 | G94: 1 | H94: 1 | I94: =ROUND(E94 + F94 + G94 + H94, 2) -> 87 | J94: 6505 | K94: 5 | M94: Active
A95: Apparel_Caps_Beanies | B95: CAP-BASEBALL-PLAIN-MAROON | C95: tbd | D95: Rahaman Caps | E95: 83 | F95: 2 | G95: 1 | H95: 1 | I95: =ROUND(E95 + F95 + G95 + H95, 2) -> 87 | J95: 6505 | K95: 5 | M95: Active
A96: Apparel_Caps_Beanies | B96: CAP-BASEBALL-PLAIN-MUSTARD | C96: tbd | D96: Rahaman Caps | E96: 83 | F96: 2 | G96: 1 | H96: 1 | I96: =ROUND(E96 + F96 + G96 + H96, 2) -> 87 | J96: 6505 | K96: 5 | M96: Active
A97: Apparel_Caps_Beanies | B97: CAP-BASEBALL-PLAIN-NAVYBLUE | C97: C - 29 - Navy Blue | D97: A.M Traders | E97: 83 | F97: 2 | G97: 1 | H97: 1 | I97: =ROUND(E97 + F97 + G97 + H97, 2) -> 87 | J97: 6505 | K97: 5 | M97: Active
A98: Apparel_Caps_Beanies | B98: CAP-BASEBALL-PLAIN-OLIVEGREEN | C98: C - 29 - Olive | D98: A.M Traders | E98: 83 | F98: 2 | G98: 1 | H98: 1 | I98: =ROUND(E98 + F98 + G98 + H98, 2) -> 87 | J98: 6505 | K98: 5 | M98: Active
A99: Apparel_Caps_Beanies | B99: CAP-BASEBALL-PLAIN-ORANGE | C99: tbd | D99: Rahaman Caps | E99: 83 | F99: 2 | G99: 1 | H99: 1 | I99: =ROUND(E99 + F99 + G99 + H99, 2) -> 87 | J99: 6505 | K99: 5 | M99: Active
... A103: Apparel_Caps_Beanies | B103: CAP-BASEBALL-PLAIN-WHITE | C103: C - 29 - White | D103: A.M Traders | E103: 83 | F103: 2 | G103: 1 | H103: 1 | I103: =ROUND(E103 + F103 + G103 + H103, 2) -> 87 | J103: 6505 | K103: 5 | M103: Active
A104: Apparel_Caps_Beanies | B104: CAP-BASEBALL-PO2-BEIGEMAROON | C104: tbd | K104: 5
A105: Apparel_Caps_Beanies | B105: CAP-BASEBALL-PO2-BEIGENAVYBLUE | C105: tbd | K105: 5
A106: Apparel_Caps_Beanies | B106: CAP-BASEBALL-PO2-BLACKCHARCOAL | C106: tbd | K106: 5
A107: Apparel_Caps_Beanies | B107: CAP-BASEBALL-PO2-BLACKGREY | C107: tbd | K107: 5
A108: Apparel_Caps_Beanies | B108: CAP-BASEBALL-PO2-BLACKORANGE | C108: tbd | K108: 5
A109: Apparel_Caps_Beanies | B109: CAP-BASEBALL-PO2-BLACKPINK | C109: tbd | K109: 5
A110: Apparel_Caps_Beanies | B110: CAP-BASEBALL-PO2-BLACKWHITE | C110: tbd | K110: 5
A111: Apparel_Caps_Beanies | B111: CAP-BASEBALL-PO2-BLACKYELLOW | C111: tbd | K111: 5
A112: Apparel_Caps_Beanies | B112: CAP-BASEBALL-PO2-CHARCOALWHITE | C112: tbd | K112: 5
A113: Apparel_Caps_Beanies | B113: CAP-BASEBALL-PO2-GREENRED | C113: tbd | K113: 5
A114: Apparel_Caps_Beanies | B114: CAP-BASEBALL-PO2-GREYCHARCOAL | C114: tbd | K114: 5
A115: Apparel_Caps_Beanies | B115: CAP-BASEBALL-PO2-GREYWHITE | C115: tbd | K115: 5
... A126: Apparel_Caps_Beanies | B126: CAP-BASEBALL-PO2-CORALRED | C126: tbd | K126: 5
...

Sheet Pack_Master
A1: Pack_SKU | B1: Master_SKU | C1: Pack_Qty | D1: Packaging_COGS | E1: Final_L | F1: Final_W | G1: Final_H | H1: Final_Wt_Kg
A2: BEANIE-FOLD-2PLAIN-BLUE | B2: BEANIE-FOLD-2PLAIN-BLUE | C2: 1 | D2: 2 | E2: 25 | F2: 25 | G2: 3 | H2: 0.5
A3: BEANIE-FOLD-2PLAIN-BROWN | B3: BEANIE-FOLD-2PLAIN-BROWN | C3: 1 | D3: 2 | E3: 25 | F3: 25 | G3: 3 | H3: 0.5
A4: BEANIE-FOLD-2PLAIN-GREEN | B4: BEANIE-FOLD-2PLAIN-GREEN | C4: 1 | D4: 2 | E4: 25 | F4: 25 | G4: 3 | H4: 0.5
A5: BEANIE-FOLD-2PLAIN-MAROON | B5: BEANIE-FOLD-2PLAIN-MAROON | C5: 1 | D5: 2 | E5: 25 | F5: 25 | G5: 3 | H5: 0.5
A6: BEANIE-FOLD-2PLAIN-OLIVE | B6: BEANIE-FOLD-2PLAIN-OLIVE | C6: 1 | D6: 2 | E6: 25 | F6: 25 | G6: 3 | H6: 0.5
A7: BEANIE-FOLD-2PLAIN-YELLOW | B7: BEANIE-FOLD-2PLAIN-YELLOW | C7: 1 | D7: 2 | E7: 25 | F7: 25 | G7: 3 | H7: 0.5
A8: BEANIE-FOLD-BINGO-BLUE | B8: BEANIE-FOLD-BINGO-BLUE | C8: 1 | D8: 2 | E8: 25 | F8: 25 | G8: 3 | H8: 0.5
A9: BEANIE-FOLD-BINGO-BRICK | B9: BEANIE-FOLD-BINGO-BRICK | C9: 1 | D9: 2 | E9: 25 | F9: 25 | G9: 3 | H9: 0.5
A10: BEANIE-FOLD-BINGO-BROWN | B10: BEANIE-FOLD-BINGO-BROWN | C10: 1 | D10: 2 | E10: 25 | F10: 25 | G10: 3 | H10: 0.5
A11: BEANIE-FOLD-BINGO-GREEN | B11: BEANIE-FOLD-BINGO-GREEN | C11: 1 | D11: 2 | E11: 25 | F11: 25 | G11: 3 | H11: 0.5
A12: BEANIE-FOLD-BINGO-GREY | B12: BEANIE-FOLD-BINGO-GREY | C12: 1 | D12: 2 | E12: 25 | F12: 25 | G12: 3 | H12: 0.5
A13: BEANIE-FOLD-BINGO-LIGHTBROWN | B13: BEANIE-FOLD-BINGO-LIGHTBROWN | C13: 1 | D13: 2 | E13: 25 | F13: 25 | G13: 3 | H13: 0.5
... A429: CAP-GOLF-CHARCOAL | B429: CAP-GOLF-CHARCOAL | C429: 1 | D429: 0 | E429: 0 | F429: 0 | G429: 0 | H429: 0

Sheet Pricing_&_Profit_Control
A1: Marketplace | B1: Category | C1: Channel_SKU | D1: Pack_SKU | E1: Selling_Price | F1: Total_COGS | G1: Volumetric_Wt | H1: Billable_Weight | I1: Shipping_Fee | J1: Platform_Fees | K1: Net_Profit | L1: Profit_Margin
A2: Amazon | B2: {=IF(D2="","", INDEX(Product_Master!A:A, MATCH( INDEX(Pack_Master!B:B, MATCH(D2, Pack_Master!A:A, 0)), Product_Master!B:B, 0 ) ))} -> #N/A | C2: ABC1 | D2: ABC-PK1 | E2: 999 | F2: {=IFERROR( VALUE( INDEX(Product_Master!$I:$I, MATCH( INDEX(Pack_Master!$B:$B, MATCH($D2, Pack_Master!$A:$A, 0)), Product_Master!$B:$B, 0) )) * VALUE( INDEX(Pack_Master!$C:$C, MATCH($D2, Pack_Master!$A:$A, 0)) ) + VALUE( INDEX(Pack_Master!$D:$D, MATCH($D2, Pack_Master!$A:$A, 0)) ), "")} | G2: {=IFERROR( ( INDEX(Pack_Master!E:E, MATCH($D2, Pack_Master!A:A, 0)) * INDEX(Pack_Master!F:F, MATCH($D2, Pack_Master!A:A, 0)) * INDEX(Pack_Master!G:G, MATCH($D2, Pack_Master!A:A, 0)) ) / INDEX(Config!C:C, MATCH($A2, Config!A:A, 0)), "")} | H2: {=MAX( INDEX(Pack_Master!H:H, MATCH($D2, Pack_Master!A:A, 0)), IFERROR(G2, 0) )} -> #N/A | I2: =IFERROR(__xludf.DUMMYFUNCTION("IFERROR( INDEX( FILTER(Shipping_Rate_Card!B:F, Shipping_Rate_Card!A:A=$A2), MATCH($H2, FILTER(Shipping_Rate_Card!B:B, Shipping_Rate_Card!A:A=$A2), 1), IF( INDEX(Config!B:B, MATCH($A2, Config!A:A, 0))=""Local"", 2, IF( INDEX(Config!B:B, MATC"&"H($A2, Config!A:A, 0))=""Regional"", 3, 4 ) ) ), """") "),"") | J2: =IFERROR(__xludf.DUMMYFUNCTION("IFERROR( ( E2 * INDEX(FILTER(Pricing_Rules!E:E, Pricing_Rules!A:A=A2, Pricing_Rules!B:B=B2, Pricing_Rules!C:C<=E2, Pricing_Rules!D:D>=E2), 1) + INDEX(FILTER(Pricing_Rules!F:F, Pricing_Rules!A:A=A2, Pricing_Rules!B:B=B2, Pricing_Rules!C:C<=E2, Pricing_"&"Rules!D:D>=E2), 1) ) * (1 + IFERROR( INDEX(Config!D:D, MATCH(A2, Config!A:A, 0)), 0 )), """") "),"") | K2: =IFERROR(E2 - F2 - I2 - J2, "") -> 999 | L2: =IFERROR(K2 / E2, "") -> 1
A3: Amazon | B3: {=IF(D3="","", INDEX(Product_Master!A:A, MATCH( INDEX(Pack_Master!B:B, MATCH(D3, Pack_Master!A:A, 0)), Product_Master!B:B, 0 ) ))} -> #N/A | C3: ABC_Pack2 | D3: ABC-PK2 | E3: 1899 | F3: {=IFERROR( VALUE( INDEX(Product_Master!$I:$I, MATCH( INDEX(Pack_Master!$B:$B, MATCH($D3, Pack_Master!$A:$A, 0)), Product_Master!$B:$B, 0) )) * VALUE( INDEX(Pack_Master!$C:$C, MATCH($D3, Pack_Master!$A:$A, 0)) ) + VALUE( INDEX(Pack_Master!$D:$D, MATCH($D3, Pack_Master!$A:$A, 0)) ), "")} | G3: {=IFERROR( ( INDEX(Pack_Master!E:E, MATCH($D3, Pack_Master!A:A, 0)) * INDEX(Pack_Master!F:F, MATCH($D3, Pack_Master!A:A, 0)) * INDEX(Pack_Master!G:G, MATCH($D3, Pack_Master!A:A, 0)) ) / INDEX(Config!C:C, MATCH($A3, Config!A:A, 0)), "")} | H3: {=MAX( INDEX(Pack_Master!H:H, MATCH($D3, Pack_Master!A:A, 0)), IFERROR(G3, 0) )} -> #N/A | I3: =IFERROR(__xludf.DUMMYFUNCTION("IFERROR( INDEX( FILTER(Shipping_Rate_Card!B:F, Shipping_Rate_Card!A:A=$A3), MATCH($H3, FILTER(Shipping_Rate_Card!B:B, Shipping_Rate_Card!A:A=$A3), 1), IF( INDEX(Config!B:B, MATCH($A3, Config!A:A, 0))=""Local"", 2, IF( INDEX(Config!B:B, MATC"&"H($A3, Config!A:A, 0))=""Regional"", 3, 4 ) ) ), """") "),"") | J3: =IFERROR(__xludf.DUMMYFUNCTION("IFERROR( ( E3 * INDEX(FILTER(Pricing_Rules!E:E, Pricing_Rules!A:A=A3, Pricing_Rules!B:B=B3, Pricing_Rules!C:C<=E3, Pricing_Rules!D:D>=E3), 1) + INDEX(FILTER(Pricing_Rules!F:F, Pricing_Rules!A:A=A3, Pricing_Rules!B:B=B3, Pricing_Rules!C:C<=E3, Pricing_"&"Rules!D:D>=E3), 1) ) * (1 + IFERROR( INDEX(Config!D:D, MATCH(A3, Config!A:A, 0)), 0 )), """") "),"") | K3: =IFERROR(E3 - F3 - I3 - J3, "") -> 1899 | L3: =IFERROR(K3 / E3, "") -> 1
A4: Amazon | B4: {=IF(D4="","", INDEX(Product_Master!A:A, MATCH( INDEX(Pack_Master!B:B, MATCH(D4, Pack_Master!A:A, 0)), Product_Master!B:B, 0 ) ))} -> Apparel_Caps_Beanies | C4: BEANIE-FOLD-2PLAIN-BLUE | D4: BEANIE-FOLD-2PLAIN-BLUE | E4: 299 | F4: {=IFERROR( VALUE( INDEX(Product_Master!$I:$I, MATCH( INDEX(Pack_Master!$B:$B, MATCH($D4, Pack_Master!$A:$A, 0)), Product_Master!$B:$B, 0) )) * VALUE( INDEX(Pack_Master!$C:$C, MATCH($D4, Pack_Master!$A:$A, 0)) ) + VALUE( INDEX(Pack_Master!$D:$D, MATCH($D4, Pack_Master!$A:$A, 0)) ), "")} -> 109 | G4: {=IFERROR( ( INDEX(Pack_Master!E:E, MATCH($D4, Pack_Master!A:A, 0)) * INDEX(Pack_Master!F:F, MATCH($D4, Pack_Master!A:A, 0)) * INDEX(Pack_Master!G:G, MATCH($D4, Pack_Master!A:A, 0)) ) / INDEX(Config!C:C, MATCH($A4, Config!A:A, 0)), "")} -> 0.375 | H4: {=MAX( INDEX(Pack_Master!H:H, MATCH($D4, Pack_Master!A:A, 0)), IFERROR(G4, 0) )} -> 0.5 | I4: =IFERROR(__xludf.DUMMYFUNCTION("IFERROR( INDEX( FILTER(Shipping_Rate_Card!B:F, Shipping_Rate_Card!A:A=$A4), MATCH($H4, FILTER(Shipping_Rate_Card!B:B, Shipping_Rate_Card!A:A=$A4), 1), IF( INDEX(Config!B:B, MATCH($A4, Config!A:A, 0))=""Local"", 2, IF( INDEX(Config!B:B, MATC"&"H($A4, Config!A:A, 0))=""Regional"", 3, 4 ) ) ), """") "),67.0) -> 67 | J4: =IFERROR(__xludf.DUMMYFUNCTION("IFERROR( ( E4 * INDEX(FILTER(Pricing_Rules!E:E, Pricing_Rules!A:A=A4, Pricing_Rules!B:B=B4, Pricing_Rules!C:C<=E4, Pricing_Rules!D:D>=E4), 1) + INDEX(FILTER(Pricing_Rules!F:F, Pricing_Rules!A:A=A4, Pricing_Rules!B:B=B4, Pricing_Rules!C:C<=E4, Pricing_"&"Rules!D:D>=E4), 1) ) * (1 + IFERROR( INDEX(Config!D:D, MATCH(A4, Config!A:A, 0)), 0 )), """") "),5.8999999999999995) -> 5.9 | K4: =IFERROR(E4 - F4 - I4 - J4, "") -> 117.1 | L4: =IFERROR(K4 / E4, "") -> 0.3916388
A5: Amazon | B5: {=IF(D5="","", INDEX(Product_Master!A:A, MATCH( INDEX(Pack_Master!B:B, MATCH(D5, Pack_Master!A:A, 0)), Product_Master!B:B, 0 ) ))} -> Apparel_Caps_Beanies | C5: BEANIE-FOLD-2PLAIN-BROWN | D5: BEANIE-FOLD-2PLAIN-BROWN | E5: 299 | F5: {=IFERROR( VALUE( INDEX(Product_Master!$I:$I, MATCH( INDEX(Pack_Master!$B:$B, MATCH($D5, Pack_Master!$A:$A, 0)), Product_Master!$B:$B, 0) )) * VALUE( INDEX(Pack_Master!$C:$C, MATCH($D5, Pack_Master!$A:$A, 0)) ) + VALUE( INDEX(Pack_Master!$D:$D, MATCH($D5, Pack_Master!$A:$A, 0)) ), "")} -> 109 | G5: {=IFERROR( ( INDEX(Pack_Master!E:E, MATCH($D5, Pack_Master!A:A, 0)) * INDEX(Pack_Master!F:F, MATCH($D5, Pack_Master!A:A, 0)) * INDEX(Pack_Master!G:G, MATCH($D5, Pack_Master!A:A, 0)) ) / INDEX(Config!C:C, MATCH($A5, Config!A:A, 0)), "")} -> 0.375 | H5: {=MAX( INDEX(Pack_Master!H:H, MATCH($D5, Pack_Master!A:A, 0)), IFERROR(G5, 0) )} -> 0.5 | I5: =IFERROR(__xludf.DUMMYFUNCTION("IFERROR( INDEX( FILTER(Shipping_Rate_Card!B:F, Shipping_Rate_Card!A:A=$A5), MATCH($H5, FILTER(Shipping_Rate_Card!B:B, Shipping_Rate_Card!A:A=$A5), 1), IF( INDEX(Config!B:B, MATCH($A5, Config!A:A, 0))=""Local"", 2, IF( INDEX(Config!B:B, MATC"&"H($A5, Config!A:A, 0))=""Regional"", 3, 4 ) ) ), """") "),67.0) -> 67 | J5: =IFERROR(__xludf.DUMMYFUNCTION("IFERROR( ( E5 * INDEX(FILTER(Pricing_Rules!E:E, Pricing_Rules!A:A=A5, Pricing_Rules!B:B=B5, Pricing_Rules!C:C<=E5, Pricing_Rules!D:D>=E5), 1) + INDEX(FILTER(Pricing_Rules!F:F, Pricing_Rules!A:A=A5, Pricing_Rules!B:B=B5, Pricing_Rules!C:C<=E5, Pricing_"&"Rules!D:D>=E5), 1) ) * (1 + IFERROR( INDEX(Config!D:D, MATCH(A5, Config!A:A, 0)), 0 )), """") "),5.8999999999999995) -> 5.9 | K5: =IFERROR(E5 - F5 - I5 - J5, "") -> 117.1 | L5: =IFERROR(K5 / E5, "") -> 0.3916388
A6: Amazon | B6: {=IF(D6="","", INDEX(Product_Master!A:A, MATCH( INDEX(Pack_Master!B:B, MATCH(D6, Pack_Master!A:A, 0)), Product_Master!B:B, 0 ) ))} -> Apparel_Caps_Beanies | C6: BEANIE-FOLD-2PLAIN-GREEN | D6: BEANIE-FOLD-2PLAIN-GREEN | E6: 299 | F6: {=IFERROR( VALUE( INDEX(Product_Master!$I:$I, MATCH( INDEX(Pack_Master!$B:$B, MATCH($D6, Pack_Master!$A:$A, 0)), Product_Master!$B:$B, 0) )) * VALUE( INDEX(Pack_Master!$C:$C, MATCH($D6, Pack_Master!$A:$A, 0)) ) + VALUE( INDEX(Pack_Master!$D:$D, MATCH($D6, Pack_Master!$A:$A, 0)) ), "")} -> 109 | G6: {=IFERROR( ( INDEX(Pack_Master!E:E, MATCH($D6, Pack_Master!A:A, 0)) * INDEX(Pack_Master!F:F, MATCH($D6, Pack_Master!A:A, 0)) * INDEX(Pack_Master!G:G, MATCH($D6, Pack_Master!A:A, 0)) ) / INDEX(Config!C:C, MATCH($A6, Config!A:A, 0)), "")} -> 0.375 | H6: {=MAX( INDEX(Pack_Master!H:H, MATCH($D6, Pack_Master!A:A, 0)), IFERROR(G6, 0) )} -> 0.5 | I6: =IFERROR(__xludf.DUMMYFUNCTION("IFERROR( INDEX( FILTER(Shipping_Rate_Card!B:F, Shipping_Rate_Card!A:A=$A6), MATCH($H6, FILTER(Shipping_Rate_Card!B:B, Shipping_Rate_Card!A:A=$A6), 1), IF( INDEX(Config!B:B, MATCH($A6, Config!A:A, 0))=""Local"", 2, IF( INDEX(Config!B:B, MATC"&"H($A6, Config!A:A, 0))=""Regional"", 3, 4 ) ) ), """") "),67.0) -> 67 | J6: =IFERROR(__xludf.DUMMYFUNCTION("IFERROR( ( E6 * INDEX(FILTER(Pricing_Rules!E:E, Pricing_Rules!A:A=A6, Pricing_Rules!B:B=B6, Pricing_Rules!C:C<=E6, Pricing_Rules!D:D>=E6), 1) + INDEX(FILTER(Pricing_Rules!F:F, Pricing_Rules!A:A=A6, Pricing_Rules!B:B=B6, Pricing_Rules!C:C<=E6, Pricing_"&"Rules!D:D>=E6), 1) ) * (1 + IFERROR( INDEX(Config!D:D, MATCH(A6, Config!A:A, 0)), 0 )), """") "),5.8999999999999995) -> 5.9 | K6: =IFERROR(E6 - F6 - I6 - J6, "") -> 117.1 | L6: =IFERROR(K6 / E6, "") -> 0.3916388
A7: Amazon | B7: {=IF(D7="","", INDEX(Product_Master!A:A, MATCH( INDEX(Pack_Master!B:B, MATCH(D7, Pack_Master!A:A, 0)), Product_Master!B:B, 0 ) ))} -> Apparel_Caps_Beanies | C7: BEANIE-FOLD-2PLAIN-MAROON | D7: BEANIE-FOLD-2PLAIN-MAROON | E7: 299 | F7: {=IFERROR( VALUE( INDEX(Product_Master!$I:$I, MATCH( INDEX(Pack_Master!$B:$B, MATCH($D7, Pack_Master!$A:$A, 0)), Product_Master!$B:$B, 0) )) * VALUE( INDEX(Pack_Master!$C:$C, MATCH($D7, Pack_Master!$A:$A, 0)) ) + VALUE( INDEX(Pack_Master!$D:$D, MATCH($D7, Pack_Master!$A:$A, 0)) ), "")} -> 109 | G7: {=IFERROR( ( INDEX(Pack_Master!E:E, MATCH($D7, Pack_Master!A:A, 0)) * INDEX(Pack_Master!F:F, MATCH($D7, Pack_Master!A:A, 0)) * INDEX(Pack_Master!G:G, MATCH($D7, Pack_Master!A:A, 0)) ) / INDEX(Config!C:C, MATCH($A7, Config!A:A, 0)), "")} -> 0.375 | H7: {=MAX( INDEX(Pack_Master!H:H, MATCH($D7, Pack_Master!A:A, 0)), IFERROR(G7, 0) )} -> 0.5 | I7: =IFERROR(__xludf.DUMMYFUNCTION("IFERROR( INDEX( FILTER(Shipping_Rate_Card!B:F, Shipping_Rate_Card!A:A=$A7), MATCH($H7, FILTER(Shipping_Rate_Card!B:B, Shipping_Rate_Card!A:A=$A7), 1), IF( INDEX(Config!B:B, MATCH($A7, Config!A:A, 0))=""Local"", 2, IF( INDEX(Config!B:B, MATC"&"H($A7, Config!A:A, 0))=""Regional"", 3, 4 ) ) ), """") "),67.0) -> 67 | J7: =IFERROR(__xludf.DUMMYFUNCTION("IFERROR( ( E7 * INDEX(FILTER(Pricing_Rules!E:E, Pricing_Rules!A:A=A7, Pricing_Rules!B:B=B7, Pricing_Rules!C:C<=E7, Pricing_Rules!D:D>=E7), 1) + INDEX(FILTER(Pricing_Rules!F:F, Pricing_Rules!A:A=A7, Pricing_Rules!B:B=B7, Pricing_Rules!C:C<=E7, Pricing_"&"Rules!D:D>=E7), 1) ) * (1 + IFERROR( INDEX(Config!D:D, MATCH(A7, Config!A:A, 0)), 0 )), """") "),5.8999999999999995) -> 5.9 | K7: =IFERROR(E7 - F7 - I7 - J7, "") -> 117.1 | L7: =IFERROR(K7 / E7, "") -> 0.3916388
A8: Amazon | B8: {=IF(D8="","", INDEX(Product_Master!A:A, MATCH( INDEX(Pack_Master!B:B, MATCH(D8, Pack_Master!A:A, 0)), Product_Master!B:B, 0 ) ))} -> Apparel_Caps_Beanies | C8: BEANIE-FOLD-2PLAIN-OLIVE | D8: BEANIE-FOLD-2PLAIN-OLIVE | E8: 299 | F8: {=IFERROR( VALUE( INDEX(Product_Master!$I:$I, MATCH( INDEX(Pack_Master!$B:$B, MATCH($D8, Pack_Master!$A:$A, 0)), Product_Master!$B:$B, 0) )) * VALUE( INDEX(Pack_Master!$C:$C, MATCH($D8, Pack_Master!$A:$A, 0)) ) + VALUE( INDEX(Pack_Master!$D:$D, MATCH($D8, Pack_Master!$A:$A, 0)) ), "")} -> 109 | G8: {=IFERROR( ( INDEX(Pack_Master!E:E, MATCH($D8, Pack_Master!A:A, 0)) * INDEX(Pack_Master!F:F, MATCH($D8, Pack_Master!A:A, 0)) * INDEX(Pack_Master!G:G, MATCH($D8, Pack_Master!A:A, 0)) ) / INDEX(Config!C:C, MATCH($A8, Config!A:A, 0)), "")} -> 0.375 | H8: {=MAX( INDEX(Pack_Master!H:H, MATCH($D8, Pack_Master!A:A, 0)), IFERROR(G8, 0) )} -> 0.5 | I8: =IFERROR(__xludf.DUMMYFUNCTION("IFERROR( INDEX( FILTER(Shipping_Rate_Card!B:F, Shipping_Rate_Card!A:A=$A8), MATCH($H8, FILTER(Shipping_Rate_Card!B:B, Shipping_Rate_Card!A:A=$A8), 1), IF( INDEX(Config!B:B, MATCH($A8, Config!A:A, 0))=""Local"", 2, IF( INDEX(Config!B:B, MATC"&"H($A8, Config!A:A, 0))=""Regional"", 3, 4 ) ) ), """") "),67.0) -> 67 | J8: =IFERROR(__xludf.DUMMYFUNCTION("IFERROR( ( E8 * INDEX(FILTER(Pricing_Rules!E:E, Pricing_Rules!A:A=A8, Pricing_Rules!B:B=B8, Pricing_Rules!C:C<=E8, Pricing_Rules!D:D>=E8), 1) + INDEX(FILTER(Pricing_Rules!F:F, Pricing_Rules!A:A=A8, Pricing_Rules!B:B=B8, Pricing_Rules!C:C<=E8, Pricing_"&"Rules!D:D>=E8), 1) ) * (1 + IFERROR( INDEX(Config!D:D, MATCH(A8, Config!A:A, 0)), 0 )), """") "),5.8999999999999995) -> 5.9 | K8: =IFERROR(E8 - F8 - I8 - J8, "") -> 117.1 | L8: =IFERROR(K8 / E8, "") -> 0.3916388
A9: Amazon | B9: {=IF(D9="","", INDEX(Product_Master!A:A, MATCH( INDEX(Pack_Master!B:B, MATCH(D9, Pack_Master!A:A, 0)), Product_Master!B:B, 0 ) ))} -> Apparel_Caps_Beanies | C9: BEANIE-FOLD-2PLAIN-YELLOW | D9: BEANIE-FOLD-2PLAIN-YELLOW | E9: 299 | F9: {=IFERROR( VALUE( INDEX(Product_Master!$I:$I, MATCH( INDEX(Pack_Master!$B:$B, MATCH($D9, Pack_Master!$A:$A, 0)), Product_Master!$B:$B, 0) )) * VALUE( INDEX(Pack_Master!$C:$C, MATCH($D9, Pack_Master!$A:$A, 0)) ) + VALUE( INDEX(Pack_Master!$D:$D, MATCH($D9, Pack_Master!$A:$A, 0)) ), "")} -> 109 | G9: {=IFERROR( ( INDEX(Pack_Master!E:E, MATCH($D9, Pack_Master!A:A, 0)) * INDEX(Pack_Master!F:F, MATCH($D9, Pack_Master!A:A, 0)) * INDEX(Pack_Master!G:G, MATCH($D9, Pack_Master!A:A, 0)) ) / INDEX(Config!C:C, MATCH($A9, Config!A:A, 0)), "")} -> 0.375 | H9: {=MAX( INDEX(Pack_Master!H:H, MATCH($D9, Pack_Master!A:A, 0)), IFERROR(G9, 0) )} -> 0.5 | I9: =IFERROR(__xludf.DUMMYFUNCTION("IFERROR( INDEX( FILTER(Shipping_Rate_Card!B:F, Shipping_Rate_Card!A:A=$A9), MATCH($H9, FILTER(Shipping_Rate_Card!B:B, Shipping_Rate_Card!A:A=$A9), 1), IF( INDEX(Config!B:B, MATCH($A9, Config!A:A, 0))=""Local"", 2, IF( INDEX(Config!B:B, MATC"&"H($A9, Config!A:A, 0))=""Regional"", 3, 4 ) ) ), """") "),67.0) -> 67 | J9: =IFERROR(__xludf.DUMMYFUNCTION("IFERROR( ( E9 * INDEX(FILTER(Pricing_Rules!E:E, Pricing_Rules!A:A=A9, Pricing_Rules!B:B=B9, Pricing_Rules!C:C<=E9, Pricing_Rules!D:D>=E9), 1) + INDEX(FILTER(Pricing_Rules!F:F, Pricing_Rules!A:A=A9, Pricing_Rules!B:B=B9, Pricing_Rules!C:C<=E9, Pricing_"&"Rules!D:D>=E9), 1) ) * (1 + IFERROR( INDEX(Config!D:D, MATCH(A9, Config!A:A, 0)), 0 )), """") "),5.8999999999999995) -> 5.9 | K9: =IFERROR(E9 - F9 - I9 - J9, "") -> 117.1 | L9: =IFERROR(K9 / E9, "") -> 0.3916388
A10: Amazon | B10: {=IF(D10="","", INDEX(Product_Master!A:A, MATCH( INDEX(Pack_Master!B:B, MATCH(D10, Pack_Master!A:A, 0)), Product_Master!B:B, 0 ) ))} -> Apparel_Caps_Beanies | C10: BEANIE-FOLD-BINGO-BLUE | D10: BEANIE-FOLD-BINGO-BLUE | E10: 299 | F10: {=IFERROR( VALUE( INDEX(Product_Master!$I:$I, MATCH( INDEX(Pack_Master!$B:$B, MATCH($D10, Pack_Master!$A:$A, 0)), Product_Master!$B:$B, 0) )) * VALUE( INDEX(Pack_Master!$C:$C, MATCH($D10, Pack_Master!$A:$A, 0)) ) + VALUE( INDEX(Pack_Master!$D:$D, MATCH($D10, Pack_Master!$A:$A, 0)) ), "")} -> 109 | G10: {=IFERROR( ( INDEX(Pack_Master!E:E, MATCH($D10, Pack_Master!A:A, 0)) * INDEX(Pack_Master!F:F, MATCH($D10, Pack_Master!A:A, 0)) * INDEX(Pack_Master!G:G, MATCH($D10, Pack_Master!A:A, 0)) ) / INDEX(Config!C:C, MATCH($A10, Config!A:A, 0)), "")} -> 0.375 | H10: {=MAX( INDEX(Pack_Master!H:H, MATCH($D10, Pack_Master!A:A, 0)), IFERROR(G10, 0) )} -> 0.5 | I10: =IFERROR(__xludf.DUMMYFUNCTION("IFERROR( INDEX( FILTER(Shipping_Rate_Card!B:F, Shipping_Rate_Card!A:A=$A10), MATCH($H10, FILTER(Shipping_Rate_Card!B:B, Shipping_Rate_Card!A:A=$A10), 1), IF( INDEX(Config!B:B, MATCH($A10, Config!A:A, 0))=""Local"", 2, IF( INDEX(Config!B:B, "&"MATCH($A10, Config!A:A, 0))=""Regional"", 3, 4 ) ) ), """") "),67.0) -> 67 | J10: =IFERROR(__xludf.DUMMYFUNCTION("IFERROR( ( E10 * INDEX(FILTER(Pricing_Rules!E:E, Pricing_Rules!A:A=A10, Pricing_Rules!B:B=B10, Pricing_Rules!C:C<=E10, Pricing_Rules!D:D>=E10), 1) + INDEX(FILTER(Pricing_Rules!F:F, Pricing_Rules!A:A=A10, Pricing_Rules!B:B=B10, Pricing_Rules!C:C<=E10, "&"Pricing_Rules!D:D>=E10), 1) ) * (1 + IFERROR( INDEX(Config!D:D, MATCH(A10, Config!A:A, 0)), 0 )), """") "),5.8999999999999995) -> 5.9 | K10: =IFERROR(E10 - F10 - I10 - J10, "") -> 117.1 | L10: =IFERROR(K10 / E10, "") -> 0.3916388
A11: Amazon | B11: {=IF(D11="","", INDEX(Product_Master!A:A, MATCH( INDEX(Pack_Master!B:B, MATCH(D11, Pack_Master!A:A, 0)), Product_Master!B:B, 0 ) ))} -> Apparel_Caps_Beanies | C11: BEANIE-FOLD-BINGO-BRICK | D11: BEANIE-FOLD-BINGO-BRICK | E11: 299 | F11: {=IFERROR( VALUE( INDEX(Product_Master!$I:$I, MATCH( INDEX(Pack_Master!$B:$B, MATCH($D11, Pack_Master!$A:$A, 0)), Product_Master!$B:$B, 0) )) * VALUE( INDEX(Pack_Master!$C:$C, MATCH($D11, Pack_Master!$A:$A, 0)) ) + VALUE( INDEX(Pack_Master!$D:$D, MATCH($D11, Pack_Master!$A:$A, 0)) ), "")} -> 109 | G11: {=IFERROR( ( INDEX(Pack_Master!E:E, MATCH($D11, Pack_Master!A:A, 0)) * INDEX(Pack_Master!F:F, MATCH($D11, Pack_Master!A:A, 0)) * INDEX(Pack_Master!G:G, MATCH($D11, Pack_Master!A:A, 0)) ) / INDEX(Config!C:C, MATCH($A11, Config!A:A, 0)), "")} -> 0.375 | H11: {=MAX( INDEX(Pack_Master!H:H, MATCH($D11, Pack_Master!A:A, 0)), IFERROR(G11, 0) )} -> 0.5 | I11: =IFERROR(__xludf.DUMMYFUNCTION("IFERROR( INDEX( FILTER(Shipping_Rate_Card!B:F, Shipping_Rate_Card!A:A=$A11), MATCH($H11, FILTER(Shipping_Rate_Card!B:B, Shipping_Rate_Card!A:A=$A11), 1), IF( INDEX(Config!B:B, MATCH($A11, Config!A:A, 0))=""Local"", 2, IF( INDEX(Config!B:B, "&"MATCH($A11, Config!A:A, 0))=""Regional"", 3, 4 ) ) ), """") "),67.0) -> 67 | J11: =IFERROR(__xludf.DUMMYFUNCTION("IFERROR( ( E11 * INDEX(FILTER(Pricing_Rules!E:E, Pricing_Rules!A:A=A11, Pricing_Rules!B:B=B11, Pricing_Rules!C:C<=E11, Pricing_Rules!D:D>=E11), 1) + INDEX(FILTER(Pricing_Rules!F:F, Pricing_Rules!A:A=A11, Pricing_Rules!B:B=B11, Pricing_Rules!C:C<=E11, "&"Pricing_Rules!D:D>=E11), 1) ) * (1 + IFERROR( INDEX(Config!D:D, MATCH(A11, Config!A:A, 0)), 0 )), """") "),5.8999999999999995) -> 5.9 | K11: =IFERROR(E11 - F11 - I11 - J11, "") -> 117.1 | L11: =IFERROR(K11 / E11, "") -> 0.3916388
A12: Amazon | B12: {=IF(D12="","", INDEX(Product_Master!A:A, MATCH( INDEX(Pack_Master!B:B, MATCH(D12, Pack_Master!A:A, 0)), Product_Master!B:B, 0 ) ))} -> Apparel_Caps_Beanies | C12: BEANIE-FOLD-BINGO-BROWN | D12: BEANIE-FOLD-BINGO-BROWN | E12: 299 | F12: {=IFERROR( VALUE( INDEX(Product_Master!$I:$I, MATCH( INDEX(Pack_Master!$B:$B, MATCH($D12, Pack_Master!$A:$A, 0)), Product_Master!$B:$B, 0) )) * VALUE( INDEX(Pack_Master!$C:$C, MATCH($D12, Pack_Master!$A:$A, 0)) ) + VALUE( INDEX(Pack_Master!$D:$D, MATCH($D12, Pack_Master!$A:$A, 0)) ), "")} -> 109 | G12: {=IFERROR( ( INDEX(Pack_Master!E:E, MATCH($D12, Pack_Master!A:A, 0)) * INDEX(Pack_Master!F:F, MATCH($D12, Pack_Master!A:A, 0)) * INDEX(Pack_Master!G:G, MATCH($D12, Pack_Master!A:A, 0)) ) / INDEX(Config!C:C, MATCH($A12, Config!A:A, 0)), "")} -> 0.375 | H12: {=MAX( INDEX(Pack_Master!H:H, MATCH($D12, Pack_Master!A:A, 0)), IFERROR(G12, 0) )} -> 0.5 | I12: =IFERROR(__xludf.DUMMYFUNCTION("IFERROR( INDEX( FILTER(Shipping_Rate_Card!B:F, Shipping_Rate_Card!A:A=$A12), MATCH($H12, FILTER(Shipping_Rate_Card!B:B, Shipping_Rate_Card!A:A=$A12), 1), IF( INDEX(Config!B:B, MATCH($A12, Config!A:A, 0))=""Local"", 2, IF( INDEX(Config!B:B, "&"MATCH($A12, Config!A:A, 0))=""Regional"", 3, 4 ) ) ), """") "),67.0) -> 67 | J12: =IFERROR(__xludf.DUMMYFUNCTION("IFERROR( ( E12 * INDEX(FILTER(Pricing_Rules!E:E, Pricing_Rules!A:A=A12, Pricing_Rules!B:B=B12, Pricing_Rules!C:C<=E12, Pricing_Rules!D:D>=E12), 1) + INDEX(FILTER(Pricing_Rules!F:F, Pricing_Rules!A:A=A12, Pricing_Rules!B:B=B12, Pricing_Rules!C:C<=E12, "&"Pricing_Rules!D:D>=E12), 1) ) * (1 + IFERROR( INDEX(Config!D:D, MATCH(A12, Config!A:A, 0)), 0 )), """") "),5.8999999999999995) -> 5.9 | K12: =IFERROR(E12 - F12 - I12 - J12, "") -> 117.1 | L12: =IFERROR(K12 / E12, "") -> 0.3916388
A13: Amazon | B13: {=IF(D13="","", INDEX(Product_Master!A:A, MATCH( INDEX(Pack_Master!B:B, MATCH(D13, Pack_Master!A:A, 0)), Product_Master!B:B, 0 ) ))} -> Apparel_Caps_Beanies | C13: BEANIE-FOLD-BINGO-GREEN | D13: BEANIE-FOLD-BINGO-GREEN | E13: 299 | F13: {=IFERROR( VALUE( INDEX(Product_Master!$I:$I, MATCH( INDEX(Pack_Master!$B:$B, MATCH($D13, Pack_Master!$A:$A, 0)), Product_Master!$B:$B, 0) )) * VALUE( INDEX(Pack_Master!$C:$C, MATCH($D13, Pack_Master!$A:$A, 0)) ) + VALUE( INDEX(Pack_Master!$D:$D, MATCH($D13, Pack_Master!$A:$A, 0)) ), "")} -> 109 | G13: {=IFERROR( ( INDEX(Pack_Master!E:E, MATCH($D13, Pack_Master!A:A, 0)) * INDEX(Pack_Master!F:F, MATCH($D13, Pack_Master!A:A, 0)) * INDEX(Pack_Master!G:G, MATCH($D13, Pack_Master!A:A, 0)) ) / INDEX(Config!C:C, MATCH($A13, Config!A:A, 0)), "")} -> 0.375 | H13: {=MAX( INDEX(Pack_Master!H:H, MATCH($D13, Pack_Master!A:A, 0)), IFERROR(G13, 0) )} -> 0.5 | I13: =IFERROR(__xludf.DUMMYFUNCTION("IFERROR( INDEX( FILTER(Shipping_Rate_Card!B:F, Shipping_Rate_Card!A:A=$A13), MATCH($H13, FILTER(Shipping_Rate_Card!B:B, Shipping_Rate_Card!A:A=$A13), 1), IF( INDEX(Config!B:B, MATCH($A13, Config!A:A, 0))=""Local"", 2, IF( INDEX(Config!B:B, "&"MATCH($A13, Config!A:A, 0))=""Regional"", 3, 4 ) ) ), """") "),67.0) -> 67 | J13: =IFERROR(__xludf.DUMMYFUNCTION("IFERROR( ( E13 * INDEX(FILTER(Pricing_Rules!E:E, Pricing_Rules!A:A=A13, Pricing_Rules!B:B=B13, Pricing_Rules!C:C<=E13, Pricing_Rules!D:D>=E13), 1) + INDEX(FILTER(Pricing_Rules!F:F, Pricing_Rules!A:A=A13, Pricing_Rules!B:B=B13, Pricing_Rules!C:C<=E13, "&"Pricing_Rules!D:D>=E13), 1) ) * (1 + IFERROR( INDEX(Config!D:D, MATCH(A13, Config!A:A, 0)), 0 )), """") "),5.8999999999999995) -> 5.9 | K13: =IFERROR(E13 - F13 - I13 - J13, "") -> 117.1 | L13: =IFERROR(K13 / E13, "") -> 0.3916388
A14: Amazon | B14: {=IF(D14="","", INDEX(Product_Master!A:A, MATCH( INDEX(Pack_Master!B:B, MATCH(D14, Pack_Master!A:A, 0)), Product_Master!B:B, 0 ) ))} -> Apparel_Caps_Beanies | C14: BEANIE-FOLD-BINGO-GREY | D14: BEANIE-FOLD-BINGO-GREY | E14: 299 | F14: {=IFERROR( VALUE( INDEX(Product_Master!$I:$I, MATCH( INDEX(Pack_Master!$B:$B, MATCH($D14, Pack_Master!$A:$A, 0)), Product_Master!$B:$B, 0) )) * VALUE( INDEX(Pack_Master!$C:$C, MATCH($D14, Pack_Master!$A:$A, 0)) ) + VALUE( INDEX(Pack_Master!$D:$D, MATCH($D14, Pack_Master!$A:$A, 0)) ), "")} -> 109 | G14: {=IFERROR( ( INDEX(Pack_Master!E:E, MATCH($D14, Pack_Master!A:A, 0)) * INDEX(Pack_Master!F:F, MATCH($D14, Pack_Master!A:A, 0)) * INDEX(Pack_Master!G:G, MATCH($D14, Pack_Master!A:A, 0)) ) / INDEX(Config!C:C, MATCH($A14, Config!A:A, 0)), "")} -> 0.375 | H14: {=MAX( INDEX(Pack_Master!H:H, MATCH($D14, Pack_Master!A:A, 0)), IFERROR(G14, 0) )} -> 0.5 | I14: =IFERROR(__xludf.DUMMYFUNCTION("IFERROR( INDEX( FILTER(Shipping_Rate_Card!B:F, Shipping_Rate_Card!A:A=$A14), MATCH($H14, FILTER(Shipping_Rate_Card!B:B, Shipping_Rate_Card!A:A=$A14), 1), IF( INDEX(Config!B:B, MATCH($A14, Config!A:A, 0))=""Local"", 2, IF( INDEX(Config!B:B, "&"MATCH($A14, Config!A:A, 0))=""Regional"", 3, 4 ) ) ), """") "),67.0) -> 67 | J14: =IFERROR(__xludf.DUMMYFUNCTION("IFERROR( ( E14 * INDEX(FILTER(Pricing_Rules!E:E, Pricing_Rules!A:A=A14, Pricing_Rules!B:B=B14, Pricing_Rules!C:C<=E14, Pricing_Rules!D:D>=E14), 1) + INDEX(FILTER(Pricing_Rules!F:F, Pricing_Rules!A:A=A14, Pricing_Rules!B:B=B14, Pricing_Rules!C:C<=E14, "&"Pricing_Rules!D:D>=E14), 1) ) * (1 + IFERROR( INDEX(Config!D:D, MATCH(A14, Config!A:A, 0)), 0 )), """") "),5.8999999999999995) -> 5.9 | K14: =IFERROR(E14 - F14 - I14 - J14, "") -> 117.1 | L14: =IFERROR(K14 / E14, "") -> 0.3916388
A15: Amazon | B15: {=IF(D15="","", INDEX(Product_Master!A:A, MATCH( INDEX(Pack_Master!B:B, MATCH(D15, Pack_Master!A:A, 0)), Product_Master!B:B, 0 ) ))} -> Apparel_Caps_Beanies | C15: BEANIE-FOLD-BINGO-LIGHTBROWN | D15: BEANIE-FOLD-BINGO-LIGHTBROWN | E15: 299 | F15: {=IFERROR( VALUE( INDEX(Product_Master!$I:$I, MATCH( INDEX(Pack_Master!$B:$B, MATCH($D15, Pack_Master!$A:$A, 0)), Product_Master!$B:$B, 0) )) * VALUE( INDEX(Pack_Master!$C:$C, MATCH($D15, Pack_Master!$A:$A, 0)) ) + VALUE( INDEX(Pack_Master!$D:$D, MATCH($D15, Pack_Master!$A:$A, 0)) ), "")} -> 109 | G15: {=IFERROR( ( INDEX(Pack_Master!E:E, MATCH($D15, Pack_Master!A:A, 0)) * INDEX(Pack_Master!F:F, MATCH($D15, Pack_Master!A:A, 0)) * INDEX(Pack_Master!G:G, MATCH($D15, Pack_Master!A:A, 0)) ) / INDEX(Config!C:C, MATCH($A15, Config!A:A, 0)), "")} -> 0.375 | H15: {=MAX( INDEX(Pack_Master!H:H, MATCH($D15, Pack_Master!A:A, 0)), IFERROR(G15, 0) )} -> 0.5 | I15: =IFERROR(__xludf.DUMMYFUNCTION("IFERROR( INDEX( FILTER(Shipping_Rate_Card!B:F, Shipping_Rate_Card!A:A=$A15), MATCH($H15, FILTER(Shipping_Rate_Card!B:B, Shipping_Rate_Card!A:A=$A15), 1), IF( INDEX(Config!B:B, MATCH($A15, Config!A:A, 0))=""Local"", 2, IF( INDEX(Config!B:B, "&"MATCH($A15, Config!A:A, 0))=""Regional"", 3, 4 ) ) ), """") "),67.0) -> 67 | J15: =IFERROR(__xludf.DUMMYFUNCTION("IFERROR( ( E15 * INDEX(FILTER(Pricing_Rules!E:E, Pricing_Rules!A:A=A15, Pricing_Rules!B:B=B15, Pricing_Rules!C:C<=E15, Pricing_Rules!D:D>=E15), 1) + INDEX(FILTER(Pricing_Rules!F:F, Pricing_Rules!A:A=A15, Pricing_Rules!B:B=B15, Pricing_Rules!C:C<=E15, "&"Pricing_Rules!D:D>=E15), 1) ) * (1 + IFERROR( INDEX(Config!D:D, MATCH(A15, Config!A:A, 0)), 0 )), """") "),5.8999999999999995) -> 5.9 | K15: =IFERROR(E15 - F15 - I15 - J15, "") -> 117.1 | L15: =IFERROR(K15 / E15, "") -> 0.3916388
A16: Amazon | B16: {=IF(D16="","", INDEX(Product_Master!A:A, MATCH( INDEX(Pack_Master!B:B, MATCH(D16, Pack_Master!A:A, 0)), Product_Master!B:B, 0 ) ))} -> Apparel_Caps_Beanies | C16: BEANIE-FOLD-CHECK-BLUE | D16: BEANIE-FOLD-CHECK-BLUE | E16: 299 | F16: {=IFERROR( VALUE( INDEX(Product_Master!$I:$I, MATCH( INDEX(Pack_Master!$B:$B, MATCH($D16, Pack_Master!$A:$A, 0)), Product_Master!$B:$B, 0) )) * VALUE( INDEX(Pack_Master!$C:$C, MATCH($D16, Pack_Master!$A:$A, 0)) ) + VALUE( INDEX(Pack_Master!$D:$D, MATCH($D16, Pack_Master!$A:$A, 0)) ), "")} -> 109 | G16: {=IFERROR( ( INDEX(Pack_Master!E:E, MATCH($D16, Pack_Master!A:A, 0)) * INDEX(Pack_Master!F:F, MATCH($D16, Pack_Master!A:A, 0)) * INDEX(Pack_Master!G:G, MATCH($D16, Pack_Master!A:A, 0)) ) / INDEX(Config!C:C, MATCH($A16, Config!A:A, 0)), "")} -> 0.375 | H16: {=MAX( INDEX(Pack_Master!H:H, MATCH($D16, Pack_Master!A:A, 0)), IFERROR(G16, 0) )} -> 0.5 | I16: =IFERROR(__xludf.DUMMYFUNCTION("IFERROR( INDEX( FILTER(Shipping_Rate_Card!B:F, Shipping_Rate_Card!A:A=$A16), MATCH($H16, FILTER(Shipping_Rate_Card!B:B, Shipping_Rate_Card!A:A=$A16), 1), IF( INDEX(Config!B:B, MATCH($A16, Config!A:A, 0))=""Local"", 2, IF( INDEX(Config!B:B, "&"MATCH($A16, Config!A:A, 0))=""Regional"", 3, 4 ) ) ), """") "),67.0) -> 67 | J16: =IFERROR(__xludf.DUMMYFUNCTION("IFERROR( ( E16 * INDEX(FILTER(Pricing_Rules!E:E, Pricing_Rules!A:A=A16, Pricing_Rules!B:B=B16, Pricing_Rules!C:C<=E16, Pricing_Rules!D:D>=E16), 1) + INDEX(FILTER(Pricing_Rules!F:F, Pricing_Rules!A:A=A16, Pricing_Rules!B:B=B16, Pricing_Rules!C:C<=E16, "&"Pricing_Rules!D:D>=E16), 1) ) * (1 + IFERROR( INDEX(Config!D:D, MATCH(A16, Config!A:A, 0)), 0 )), """") "),5.8999999999999995) -> 5.9 | K16: =IFERROR(E16 - F16 - I16 - J16, "") -> 117.1 | L16: =IFERROR(K16 / E16, "") -> 0.3916388
A17: Amazon | B17: {=IF(D17="","", INDEX(Product_Master!A:A, MATCH( INDEX(Pack_Master!B:B, MATCH(D17, Pack_Master!A:A, 0)), Product_Master!B:B, 0 ) ))} -> Apparel_Caps_Beanies | C17: BEANIE-FOLD-CHECK-GREY | D17: BEANIE-FOLD-CHECK-GREY | E17: 299 | F17: {=IFERROR( VALUE( INDEX(Product_Master!$I:$I, MATCH( INDEX(Pack_Master!$B:$B, MATCH($D17, Pack_Master!$A:$A, 0)), Product_Master!$B:$B, 0) )) * VALUE( INDEX(Pack_Master!$C:$C, MATCH($D17, Pack_Master!$A:$A, 0)) ) + VALUE( INDEX(Pack_Master!$D:$D, MATCH($D17, Pack_Master!$A:$A, 0)) ), "")} -> 109 | G17: {=IFERROR( ( INDEX(Pack_Master!E:E, MATCH($D17, Pack_Master!A:A, 0)) * INDEX(Pack_Master!F:F, MATCH($D17, Pack_Master!A:A, 0)) * INDEX(Pack_Master!G:G, MATCH($D17, Pack_Master!A:A, 0)) ) / INDEX(Config!C:C, MATCH($A17, Config!A:A, 0)), "")} -> 0.375 | H17: {=MAX( INDEX(Pack_Master!H:H, MATCH($D17, Pack_Master!A:A, 0)), IFERROR(G17, 0) )} -> 0.5 | I17: =IFERROR(__xludf.DUMMYFUNCTION("IFERROR( INDEX( FILTER(Shipping_Rate_Card!B:F, Shipping_Rate_Card!A:A=$A17), MATCH($H17, FILTER(Shipping_Rate_Card!B:B, Shipping_Rate_Card!A:A=$A17), 1), IF( INDEX(Config!B:B, MATCH($A17, Config!A:A, 0))=""Local"", 2, IF( INDEX(Config!B:B, "&"MATCH($A17, Config!A:A, 0))=""Regional"", 3, 4 ) ) ), """") "),67.0) -> 67 | J17: =IFERROR(__xludf.DUMMYFUNCTION("IFERROR( ( E17 * INDEX(FILTER(Pricing_Rules!E:E, Pricing_Rules!A:A=A17, Pricing_Rules!B:B=B17, Pricing_Rules!C:C<=E17, Pricing_Rules!D:D>=E17), 1) + INDEX(FILTER(Pricing_Rules!F:F, Pricing_Rules!A:A=A17, Pricing_Rules!B:B=B17, Pricing_Rules!C:C<=E17, "&"Pricing_Rules!D:D>=E17), 1) ) * (1 + IFERROR( INDEX(Config!D:D, MATCH(A17, Config!A:A, 0)), 0 )), """") "),5.8999999999999995) -> 5.9 | K17: =IFERROR(E17 - F17 - I17 - J17, "") -> 117.1 | L17: =IFERROR(K17 / E17, "") -> 0.3916388
A18: Amazon | B18: {=IF(D18="","", INDEX(Product_Master!A:A, MATCH( INDEX(Pack_Master!B:B, MATCH(D18, Pack_Master!A:A, 0)), Product_Master!B:B, 0 ) ))} -> Apparel_Caps_Beanies | C18: BEANIE-FOLD-CHECK-LIGHTBROWN | D18: BEANIE-FOLD-CHECK-LIGHTBROWN | E18: 299 | F18: {=IFERROR( VALUE( INDEX(Product_Master!$I:$I, MATCH( INDEX(Pack_Master!$B:$B, MATCH($D18, Pack_Master!$A:$A, 0)), Product_Master!$B:$B, 0) )) * VALUE( INDEX(Pack_Master!$C:$C, MATCH($D18, Pack_Master!$A:$A, 0)) ) + VALUE( INDEX(Pack_Master!$D:$D, MATCH($D18, Pack_Master!$A:$A, 0)) ), "")} -> 109 | G18: {=IFERROR( ( INDEX(Pack_Master!E:E, MATCH($D18, Pack_Master!A:A, 0)) * INDEX(Pack_Master!F:F, MATCH($D18, Pack_Master!A:A, 0)) * INDEX(Pack_Master!G:G, MATCH($D18, Pack_Master!A:A, 0)) ) / INDEX(Config!C:C, MATCH($A18, Config!A:A, 0)), "")} -> 0.375 | H18: {=MAX( INDEX(Pack_Master!H:H, MATCH($D18, Pack_Master!A:A, 0)), IFERROR(G18, 0) )} -> 0.5 | I18: =IFERROR(__xludf.DUMMYFUNCTION("IFERROR( INDEX( FILTER(Shipping_Rate_Card!B:F, Shipping_Rate_Card!A:A=$A18), MATCH($H18, FILTER(Shipping_Rate_Card!B:B, Shipping_Rate_Card!A:A=$A18), 1), IF( INDEX(Config!B:B, MATCH($A18, Config!A:A, 0))=""Local"", 2, IF( INDEX(Config!B:B, "&"MATCH($A18, Config!A:A, 0))=""Regional"", 3, 4 ) ) ), """") "),67.0) -> 67 | J18: =IFERROR(__xludf.DUMMYFUNCTION("IFERROR( ( E18 * INDEX(FILTER(Pricing_Rules!E:E, Pricing_Rules!A:A=A18, Pricing_Rules!B:B=B18, Pricing_Rules!C:C<=E18, Pricing_Rules!D:D>=E18), 1) + INDEX(FILTER(Pricing_Rules!F:F, Pricing_Rules!A:A=A18, Pricing_Rules!B:B=B18, Pricing_Rules!C:C<=E18, "&"Pricing_Rules!D:D>=E18), 1) ) * (1 + IFERROR( INDEX(Config!D:D, MATCH(A18, Config!A:A, 0)), 0 )), """") "),5.8999999999999995) -> 5.9 | K18: =IFERROR(E18 - F18 - I18 - J18, "") -> 117.1 | L18: =IFERROR(K18 / E18, "") -> 0.3916388
A19: Amazon | B19: {=IF(D19="","", INDEX(Product_Master!A:A, MATCH( INDEX(Pack_Master!B:B, MATCH(D19, Pack_Master!A:A, 0)), Product_Master!B:B, 0 ) ))} -> Apparel_Caps_Beanies | C19: BEANIE-FOLD-CHECK-MAROON | D19: BEANIE-FOLD-CHECK-MAROON | E19: 299 | F19: {=IFERROR( VALUE( INDEX(Product_Master!$I:$I, MATCH( INDEX(Pack_Master!$B:$B, MATCH($D19, Pack_Master!$A:$A, 0)), Product_Master!$B:$B, 0) )) * VALUE( INDEX(Pack_Master!$C:$C, MATCH($D19, Pack_Master!$A:$A, 0)) ) + VALUE( INDEX(Pack_Master!$D:$D, MATCH($D19, Pack_Master!$A:$A, 0)) ), "")} -> 109 | G19: {=IFERROR( ( INDEX(Pack_Master!E:E, MATCH($D19, Pack_Master!A:A, 0)) * INDEX(Pack_Master!F:F, MATCH($D19, Pack_Master!A:A, 0)) * INDEX(Pack_Master!G:G, MATCH($D19, Pack_Master!A:A, 0)) ) / INDEX(Config!C:C, MATCH($A19, Config!A:A, 0)), "")} -> 0.375 | H19: {=MAX( INDEX(Pack_Master!H:H, MATCH($D19, Pack_Master!A:A, 0)), IFERROR(G19, 0) )} -> 0.5 | I19: =IFERROR(__xludf.DUMMYFUNCTION("IFERROR( INDEX( FILTER(Shipping_Rate_Card!B:F, Shipping_Rate_Card!A:A=$A19), MATCH($H19, FILTER(Shipping_Rate_Card!B:B, Shipping_Rate_Card!A:A=$A19), 1), IF( INDEX(Config!B:B, MATCH($A19, Config!A:A, 0))=""Local"", 2, IF( INDEX(Config!B:B, "&"MATCH($A19, Config!A:A, 0))=""Regional"", 3, 4 ) ) ), """") "),67.0) -> 67 | J19: =IFERROR(__xludf.DUMMYFUNCTION("IFERROR( ( E19 * INDEX(FILTER(Pricing_Rules!E:E, Pricing_Rules!A:A=A19, Pricing_Rules!B:B=B19, Pricing_Rules!C:C<=E19, Pricing_Rules!D:D>=E19), 1) + INDEX(FILTER(Pricing_Rules!F:F, Pricing_Rules!A:A=A19, Pricing_Rules!B:B=B19, Pricing_Rules!C:C<=E19, "&"Pricing_Rules!D:D>=E19), 1) ) * (1 + IFERROR( INDEX(Config!D:D, MATCH(A19, Config!A:A, 0)), 0 )), """") "),5.8999999999999995) -> 5.9 | K19: =IFERROR(E19 - F19 - I19 - J19, "") -> 117.1 | L19: =IFERROR(K19 / E19, "") -> 0.3916388
A20: Amazon | B20: {=IF(D20="","", INDEX(Product_Master!A:A, MATCH( INDEX(Pack_Master!B:B, MATCH(D20, Pack_Master!A:A, 0)), Product_Master!B:B, 0 ) ))} -> Apparel_Caps_Beanies | C20: BEANIE-FOLD-CHECK-OLIVE | D20: BEANIE-FOLD-CHECK-OLIVE | E20: 299 | F20: {=IFERROR( VALUE( INDEX(Product_Master!$I:$I, MATCH( INDEX(Pack_Master!$B:$B, MATCH($D20, Pack_Master!$A:$A, 0)), Product_Master!$B:$B, 0) )) * VALUE( INDEX(Pack_Master!$C:$C, MATCH($D20, Pack_Master!$A:$A, 0)) ) + VALUE( INDEX(Pack_Master!$D:$D, MATCH($D20, Pack_Master!$A:$A, 0)) ), "")} -> 109 | G20: {=IFERROR( ( INDEX(Pack_Master!E:E, MATCH($D20, Pack_Master!A:A, 0)) * INDEX(Pack_Master!F:F, MATCH($D20, Pack_Master!A:A, 0)) * INDEX(Pack_Master!G:G, MATCH($D20, Pack_Master!A:A, 0)) ) / INDEX(Config!C:C, MATCH($A20, Config!A:A, 0)), "")} -> 0.375 | H20: {=MAX( INDEX(Pack_Master!H:H, MATCH($D20, Pack_Master!A:A, 0)), IFERROR(G20, 0) )} -> 0.5 | I20: =IFERROR(__xludf.DUMMYFUNCTION("IFERROR( INDEX( FILTER(Shipping_Rate_Card!B:F, Shipping_Rate_Card!A:A=$A20), MATCH($H20, FILTER(Shipping_Rate_Card!B:B, Shipping_Rate_Card!A:A=$A20), 1), IF( INDEX(Config!B:B, MATCH($A20, Config!A:A, 0))=""Local"", 2, IF( INDEX(Config!B:B, "&"MATCH($A20, Config!A:A, 0))=""Regional"", 3, 4 ) ) ), """") "),67.0) -> 67 | J20: =IFERROR(__xludf.DUMMYFUNCTION("IFERROR( ( E20 * INDEX(FILTER(Pricing_Rules!E:E, Pricing_Rules!A:A=A20, Pricing_Rules!B:B=B20, Pricing_Rules!C:C<=E20, Pricing_Rules!D:D>=E20), 1) + INDEX(FILTER(Pricing_Rules!F:F, Pricing_Rules!A:A=A20, Pricing_Rules!B:B=B20, Pricing_Rules!C:C<=E20, "&"Pricing_Rules!D:D>=E20), 1) ) * (1 + IFERROR( INDEX(Config!D:D, MATCH(A20, Config!A:A, 0)), 0 )), """") "),5.8999999999999995) -> 5.9 | K20: =IFERROR(E20 - F20 - I20 - J20, "") -> 117.1 | L20: =IFERROR(K20 / E20, "") -> 0.3916388
A21: Amazon | B21: {=IF(D21="","", INDEX(Product_Master!A:A, MATCH( INDEX(Pack_Master!B:B, MATCH(D21, Pack_Master!A:A, 0)), Product_Master!B:B, 0 ) ))} -> Apparel_Caps_Beanies | C21: BEANIE-FOLD-KING-BLUE | D21: BEANIE-FOLD-KING-BLUE | E21: 299 | F21: {=IFERROR( VALUE( INDEX(Product_Master!$I:$I, MATCH( INDEX(Pack_Master!$B:$B, MATCH($D21, Pack_Master!$A:$A, 0)), Product_Master!$B:$B, 0) )) * VALUE( INDEX(Pack_Master!$C:$C, MATCH($D21, Pack_Master!$A:$A, 0)) ) + VALUE( INDEX(Pack_Master!$D:$D, MATCH($D21, Pack_Master!$A:$A, 0)) ), "")} -> 109 | G21: {=IFERROR( ( INDEX(Pack_Master!E:E, MATCH($D21, Pack_Master!A:A, 0)) * INDEX(Pack_Master!F:F, MATCH($D21, Pack_Master!A:A, 0)) * INDEX(Pack_Master!G:G, MATCH($D21, Pack_Master!A:A, 0)) ) / INDEX(Config!C:C, MATCH($A21, Config!A:A, 0)), "")} -> 0.375 | H21: {=MAX( INDEX(Pack_Master!H:H, MATCH($D21, Pack_Master!A:A, 0)), IFERROR(G21, 0) )} -> 0.5 | I21: =IFERROR(__xludf.DUMMYFUNCTION("IFERROR( INDEX( FILTER(Shipping_Rate_Card!B:F, Shipping_Rate_Card!A:A=$A21), MATCH($H21, FILTER(Shipping_Rate_Card!B:B, Shipping_Rate_Card!A:A=$A21), 1), IF( INDEX(Config!B:B, MATCH($A21, Config!A:A, 0))=""Local"", 2, IF( INDEX(Config!B:B, "&"MATCH($A21, Config!A:A, 0))=""Regional"", 3, 4 ) ) ), """") "),67.0) -> 67 | J21: =IFERROR(__xludf.DUMMYFUNCTION("IFERROR( ( E21 * INDEX(FILTER(Pricing_Rules!E:E, Pricing_Rules!A:A=A21, Pricing_Rules!B:B=B21, Pricing_Rules!C:C<=E21, Pricing_Rules!D:D>=E21), 1) + INDEX(FILTER(Pricing_Rules!F:F, Pricing_Rules!A:A=A21, Pricing_Rules!B:B=B21, Pricing_Rules!C:C<=E21, "&"Pricing_Rules!D:D>=E21), 1) ) * (1 + IFERROR( INDEX(Config!D:D, MATCH(A21, Config!A:A, 0)), 0 )), """") "),5.8999999999999995) -> 5.9 | K21: =IFERROR(E21 - F21 - I21 - J21, "") -> 117.1 | L21: =IFERROR(K21 / E21, "") -> 0.3916388
A22: Amazon | B22: {=IF(D22="","", INDEX(Product_Master!A:A, MATCH( INDEX(Pack_Master!B:B, MATCH(D22, Pack_Master!A:A, 0)), Product_Master!B:B, 0 ) ))} -> Apparel_Caps_Beanies | C22: BEANIE-FOLD-KING-BROWN | D22: BEANIE-FOLD-KING-BROWN | E22: 299 | F22: {=IFERROR( VALUE( INDEX(Product_Master!$I:$I, MATCH( INDEX(Pack_Master!$B:$B, MATCH($D22, Pack_Master!$A:$A, 0)), Product_Master!$B:$B, 0) )) * VALUE( INDEX(Pack_Master!$C:$C, MATCH($D22, Pack_Master!$A:$A, 0)) ) + VALUE( INDEX(Pack_Master!$D:$D, MATCH($D22, Pack_Master!$A:$A, 0)) ), "")} -> 109 | G22: {=IFERROR( ( INDEX(Pack_Master!E:E, MATCH($D22, Pack_Master!A:A, 0)) * INDEX(Pack_Master!F:F, MATCH($D22, Pack_Master!A:A, 0)) * INDEX(Pack_Master!G:G, MATCH($D22, Pack_Master!A:A, 0)) ) / INDEX(Config!C:C, MATCH($A22, Config!A:A, 0)), "")} -> 0.375 | H22: {=MAX( INDEX(Pack_Master!H:H, MATCH($D22, Pack_Master!A:A, 0)), IFERROR(G22, 0) )} -> 0.5 | I22: =IFERROR(__xludf.DUMMYFUNCTION("IFERROR( INDEX( FILTER(Shipping_Rate_Card!B:F, Shipping_Rate_Card!A:A=$A22), MATCH($H22, FILTER(Shipping_Rate_Card!B:B, Shipping_Rate_Card!A:A=$A22), 1), IF( INDEX(Config!B:B, MATCH($A22, Config!A:A, 0))=""Local"", 2, IF( INDEX(Config!B:B, "&"MATCH($A22, Config!A:A, 0))=""Regional"", 3, 4 ) ) ), """") "),67.0) -> 67 | J22: =IFERROR(__xludf.DUMMYFUNCTION("IFERROR( ( E22 * INDEX(FILTER(Pricing_Rules!E:E, Pricing_Rules!A:A=A22, Pricing_Rules!B:B=B22, Pricing_Rules!C:C<=E22, Pricing_Rules!D:D>=E22), 1) + INDEX(FILTER(Pricing_Rules!F:F, Pricing_Rules!A:A=A22, Pricing_Rules!B:B=B22, Pricing_Rules!C:C<=E22, "&"Pricing_Rules!D:D>=E22), 1) ) * (1 + IFERROR( INDEX(Config!D:D, MATCH(A22, Config!A:A, 0)), 0 )), """") "),5.8999999999999995) -> 5.9 | K22: =IFERROR(E22 - F22 - I22 - J22, "") -> 117.1 | L22: =IFERROR(K22 / E22, "") -> 0.3916388
A23: Amazon | B23: {=IF(D23="","", INDEX(Product_Master!A:A, MATCH( INDEX(Pack_Master!B:B, MATCH(D23, Pack_Master!A:A, 0)), Product_Master!B:B, 0 ) ))} -> Apparel_Caps_Beanies | C23: BEANIE-FOLD-KING-GREEN | D23: BEANIE-FOLD-KING-GREEN | E23: 299 | F23: {=IFERROR( VALUE( INDEX(Product_Master!$I:$I, MATCH( INDEX(Pack_Master!$B:$B, MATCH($D23, Pack_Master!$A:$A, 0)), Product_Master!$B:$B, 0) )) * VALUE( INDEX(Pack_Master!$C:$C, MATCH($D23, Pack_Master!$A:$A, 0)) ) + VALUE( INDEX(Pack_Master!$D:$D, MATCH($D23, Pack_Master!$A:$A, 0)) ), "")} -> 109 | G23: {=IFERROR( ( INDEX(Pack_Master!E:E, MATCH($D23, Pack_Master!A:A, 0)) * INDEX(Pack_Master!F:F, MATCH($D23, Pack_Master!A:A, 0)) * INDEX(Pack_Master!G:G, MATCH($D23, Pack_Master!A:A, 0)) ) / INDEX(Config!C:C, MATCH($A23, Config!A:A, 0)), "")} -> 0.375 | H23: {=MAX( INDEX(Pack_Master!H:H, MATCH($D23, Pack_Master!A:A, 0)), IFERROR(G23, 0) )} -> 0.5 | I23: =IFERROR(__xludf.DUMMYFUNCTION("IFERROR( INDEX( FILTER(Shipping_Rate_Card!B:F, Shipping_Rate_Card!A:A=$A23), MATCH($H23, FILTER(Shipping_Rate_Card!B:B, Shipping_Rate_Card!A:A=$A23), 1), IF( INDEX(Config!B:B, MATCH($A23, Config!A:A, 0))=""Local"", 2, IF( INDEX(Config!B:B, "&"MATCH($A23, Config!A:A, 0))=""Regional"", 3, 4 ) ) ), """") "),67.0) -> 67 | J23: =IFERROR(__xludf.DUMMYFUNCTION("IFERROR( ( E23 * INDEX(FILTER(Pricing_Rules!E:E, Pricing_Rules!A:A=A23, Pricing_Rules!B:B=B23, Pricing_Rules!C:C<=E23, Pricing_Rules!D:D>=E23), 1) + INDEX(FILTER(Pricing_Rules!F:F, Pricing_Rules!A:A=A23, Pricing_Rules!B:B=B23, Pricing_Rules!C:C<=E23, "&"Pricing_Rules!D:D>=E23), 1) ) * (1 + IFERROR( INDEX(Config!D:D, MATCH(A23, Config!A:A, 0)), 0 )), """") "),5.8999999999999995) -> 5.9 | K23: =IFERROR(E23 - F23 - I23 - J23, "") -> 117.1 | L23: =IFERROR(K23 / E23, "") -> 0.3916388
A24: Amazon | B24: {=IF(D24="","", INDEX(Product_Master!A:A, MATCH( INDEX(Pack_Master!B:B, MATCH(D24, Pack_Master!A:A, 0)), Product_Master!B:B, 0 ) ))} -> Apparel_Caps_Beanies | C24: BEANIE-FOLD-KING-GREY | D24: BEANIE-FOLD-KING-GREY | E24: 299 | F24: {=IFERROR( VALUE( INDEX(Product_Master!$I:$I, MATCH( INDEX(Pack_Master!$B:$B, MATCH($D24, Pack_Master!$A:$A, 0)), Product_Master!$B:$B, 0) )) * VALUE( INDEX(Pack_Master!$C:$C, MATCH($D24, Pack_Master!$A:$A, 0)) ) + VALUE( INDEX(Pack_Master!$D:$D, MATCH($D24, Pack_Master!$A:$A, 0)) ), "")} -> 109 | G24: {=IFERROR( ( INDEX(Pack_Master!E:E, MATCH($D24, Pack_Master!A:A, 0)) * INDEX(Pack_Master!F:F, MATCH($D24, Pack_Master!A:A, 0)) * INDEX(Pack_Master!G:G, MATCH($D24, Pack_Master!A:A, 0)) ) / INDEX(Config!C:C, MATCH($A24, Config!A:A, 0)), "")} -> 0.375 | H24: {=MAX( INDEX(Pack_Master!H:H, MATCH($D24, Pack_Master!A:A, 0)), IFERROR(G24, 0) )} -> 0.5 | I24: =IFERROR(__xludf.DUMMYFUNCTION("IFERROR( INDEX( FILTER(Shipping_Rate_Card!B:F, Shipping_Rate_Card!A:A=$A24), MATCH($H24, FILTER(Shipping_Rate_Card!B:B, Shipping_Rate_Card!A:A=$A24), 1), IF( INDEX(Config!B:B, MATCH($A24, Config!A:A, 0))=""Local"", 2, IF( INDEX(Config!B:B, "&"MATCH($A24, Config!A:A, 0))=""Regional"", 3, 4 ) ) ), """") "),67.0) -> 67 | J24: =IFERROR(__xludf.DUMMYFUNCTION("IFERROR( ( E24 * INDEX(FILTER(Pricing_Rules!E:E, Pricing_Rules!A:A=A24, Pricing_Rules!B:B=B24, Pricing_Rules!C:C<=E24, Pricing_Rules!D:D>=E24), 1) + INDEX(FILTER(Pricing_Rules!F:F, Pricing_Rules!A:A=A24, Pricing_Rules!B:B=B24, Pricing_Rules!C:C<=E24, "&"Pricing_Rules!D:D>=E24), 1) ) * (1 + IFERROR( INDEX(Config!D:D, MATCH(A24, Config!A:A, 0)), 0 )), """") "),5.8999999999999995) -> 5.9 | K24: =IFERROR(E24 - F24 - I24 - J24, "") -> 117.1 | L24: =IFERROR(K24 / E24, "") -> 0.3916388
A25: Amazon | B25: {=IF(D25="","", INDEX(Product_Master!A:A, MATCH( INDEX(Pack_Master!B:B, MATCH(D25, Pack_Master!A:A, 0)), Product_Master!B:B, 0 ) ))} -> Apparel_Caps_Beanies | C25: BEANIE-FOLD-KING-LIGHT GREEN | D25: BEANIE-FOLD-KING-LIGHT GREEN | E25: 299 | F25: {=IFERROR( VALUE( INDEX(Product_Master!$I:$I, MATCH( INDEX(Pack_Master!$B:$B, MATCH($D25, Pack_Master!$A:$A, 0)), Product_Master!$B:$B, 0) )) * VALUE( INDEX(Pack_Master!$C:$C, MATCH($D25, Pack_Master!$A:$A, 0)) ) + VALUE( INDEX(Pack_Master!$D:$D, MATCH($D25, Pack_Master!$A:$A, 0)) ), "")} -> 109 | G25: {=IFERROR( ( INDEX(Pack_Master!E:E, MATCH($D25, Pack_Master!A:A, 0)) * INDEX(Pack_Master!F:F, MATCH($D25, Pack_Master!A:A, 0)) * INDEX(Pack_Master!G:G, MATCH($D25, Pack_Master!A:A, 0)) ) / INDEX(Config!C:C, MATCH($A25, Config!A:A, 0)), "")} -> 0.375 | H25: {=MAX( INDEX(Pack_Master!H:H, MATCH($D25, Pack_Master!A:A, 0)), IFERROR(G25, 0) )} -> 0.5 | I25: =IFERROR(__xludf.DUMMYFUNCTION("IFERROR( INDEX( FILTER(Shipping_Rate_Card!B:F, Shipping_Rate_Card!A:A=$A25), MATCH($H25, FILTER(Shipping_Rate_Card!B:B, Shipping_Rate_Card!A:A=$A25), 1), IF( INDEX(Config!B:B, MATCH($A25, Config!A:A, 0))=""Local"", 2, IF( INDEX(Config!B:B, "&"MATCH($A25, Config!A:A, 0))=""Regional"", 3, 4 ) ) ), """") "),67.0) -> 67 | J25: =IFERROR(__xludf.DUMMYFUNCTION("IFERROR( ( E25 * INDEX(FILTER(Pricing_Rules!E:E, Pricing_Rules!A:A=A25, Pricing_Rules!B:B=B25, Pricing_Rules!C:C<=E25, Pricing_Rules!D:D>=E25), 1) + INDEX(FILTER(Pricing_Rules!F:F, Pricing_Rules!A:A=A25, Pricing_Rules!B:B=B25, Pricing_Rules!C:C<=E25, "&"Pricing_Rules!D:D>=E25), 1) ) * (1 + IFERROR( INDEX(Config!D:D, MATCH(A25, Config!A:A, 0)), 0 )), """") "),5.8999999999999995) -> 5.9 | K25: =IFERROR(E25 - F25 - I25 - J25, "") -> 117.1 | L25: =IFERROR(K25 / E25, "") -> 0.3916388
A26: Amazon | B26: {=IF(D26="","", INDEX(Product_Master!A:A, MATCH( INDEX(Pack_Master!B:B, MATCH(D26, Pack_Master!A:A, 0)), Product_Master!B:B, 0 ) ))} -> Apparel_Caps_Beanies | C26: BEANIE-FOLD-KING-MAROON | D26: BEANIE-FOLD-KING-MAROON | E26: 299 | F26: {=IFERROR( VALUE( INDEX(Product_Master!$I:$I, MATCH( INDEX(Pack_Master!$B:$B, MATCH($D26, Pack_Master!$A:$A, 0)), Product_Master!$B:$B, 0) )) * VALUE( INDEX(Pack_Master!$C:$C, MATCH($D26, Pack_Master!$A:$A, 0)) ) + VALUE( INDEX(Pack_Master!$D:$D, MATCH($D26, Pack_Master!$A:$A, 0)) ), "")} -> 109 | G26: {=IFERROR( ( INDEX(Pack_Master!E:E, MATCH($D26, Pack_Master!A:A, 0)) * INDEX(Pack_Master!F:F, MATCH($D26, Pack_Master!A:A, 0)) * INDEX(Pack_Master!G:G, MATCH($D26, Pack_Master!A:A, 0)) ) / INDEX(Config!C:C, MATCH($A26, Config!A:A, 0)), "")} -> 0.375 | H26: {=MAX( INDEX(Pack_Master!H:H, MATCH($D26, Pack_Master!A:A, 0)), IFERROR(G26, 0) )} -> 0.5 | I26: =IFERROR(__xludf.DUMMYFUNCTION("IFERROR( INDEX( FILTER(Shipping_Rate_Card!B:F, Shipping_Rate_Card!A:A=$A26), MATCH($H26, FILTER(Shipping_Rate_Card!B:B, Shipping_Rate_Card!A:A=$A26), 1), IF( INDEX(Config!B:B, MATCH($A26, Config!A:A, 0))=""Local"", 2, IF( INDEX(Config!B:B, "&"MATCH($A26, Config!A:A, 0))=""Regional"", 3, 4 ) ) ), """") "),67.0) -> 67 | J26: =IFERROR(__xludf.DUMMYFUNCTION("IFERROR( ( E26 * INDEX(FILTER(Pricing_Rules!E:E, Pricing_Rules!A:A=A26, Pricing_Rules!B:B=B26, Pricing_Rules!C:C<=E26, Pricing_Rules!D:D>=E26), 1) + INDEX(FILTER(Pricing_Rules!F:F, Pricing_Rules!A:A=A26, Pricing_Rules!B:B=B26, Pricing_Rules!C:C<=E26, "&"Pricing_Rules!D:D>=E26), 1) ) * (1 + IFERROR( INDEX(Config!D:D, MATCH(A26, Config!A:A, 0)), 0 )), """") "),5.8999999999999995) -> 5.9 | K26: =IFERROR(E26 - F26 - I26 - J26, "") -> 117.1 | L26: =IFERROR(K26 / E26, "") -> 0.3916388
A27: Amazon | B27: {=IF(D27="","", INDEX(Product_Master!A:A, MATCH( INDEX(Pack_Master!B:B, MATCH(D27, Pack_Master!A:A, 0)), Product_Master!B:B, 0 ) ))} -> Apparel_Caps_Beanies | C27: BEANIE-FUR-SHORT-RED | D27: BEANIE-FUR-SHORT-RED | E27: 299 | F27: {=IFERROR( VALUE( INDEX(Product_Master!$I:$I, MATCH( INDEX(Pack_Master!$B:$B, MATCH($D27, Pack_Master!$A:$A, 0)), Product_Master!$B:$B, 0) )) * VALUE( INDEX(Pack_Master!$C:$C, MATCH($D27, Pack_Master!$A:$A, 0)) ) + VALUE( INDEX(Pack_Master!$D:$D, MATCH($D27, Pack_Master!$A:$A, 0)) ), "")} -> 109 | G27: {=IFERROR( ( INDEX(Pack_Master!E:E, MATCH($D27, Pack_Master!A:A, 0)) * INDEX(Pack_Master!F:F, MATCH($D27, Pack_Master!A:A, 0)) * INDEX(Pack_Master!G:G, MATCH($D27, Pack_Master!A:A, 0)) ) / INDEX(Config!C:C, MATCH($A27, Config!A:A, 0)), "")} -> 0.375 | H27: {=MAX( INDEX(Pack_Master!H:H, MATCH($D27, Pack_Master!A:A, 0)), IFERROR(G27, 0) )} -> 0.5 | I27: =IFERROR(__xludf.DUMMYFUNCTION("IFERROR( INDEX( FILTER(Shipping_Rate_Card!B:F, Shipping_Rate_Card!A:A=$A27), MATCH($H27, FILTER(Shipping_Rate_Card!B:B, Shipping_Rate_Card!A:A=$A27), 1), IF( INDEX(Config!B:B, MATCH($A27, Config!A:A, 0))=""Local"", 2, IF( INDEX(Config!B:B, "&"MATCH($A27, Config!A:A, 0))=""Regional"", 3, 4 ) ) ), """") "),67.0) -> 67 | J27: =IFERROR(__xludf.DUMMYFUNCTION("IFERROR( ( E27 * INDEX(FILTER(Pricing_Rules!E:E, Pricing_Rules!A:A=A27, Pricing_Rules!B:B=B27, Pricing_Rules!C:C<=E27, Pricing_Rules!D:D>=E27), 1) + INDEX(FILTER(Pricing_Rules!F:F, Pricing_Rules!A:A=A27, Pricing_Rules!B:B=B27, Pricing_Rules!C:C<=E27, "&"Pricing_Rules!D:D>=E27), 1) ) * (1 + IFERROR( INDEX(Config!D:D, MATCH(A27, Config!A:A, 0)), 0 )), """") "),5.8999999999999995) -> 5.9 | K27: =IFERROR(E27 - F27 - I27 - J27, "") -> 117.1 | L27: =IFERROR(K27 / E27, "") -> 0.3916388
A28: Amazon | B28: {=IF(D28="","", INDEX(Product_Master!A:A, MATCH( INDEX(Pack_Master!B:B, MATCH(D28, Pack_Master!A:A, 0)), Product_Master!B:B, 0 ) ))} -> Apparel_Caps_Beanies | C28: BEANIE-FUR-SHORT-YELLOW | D28: BEANIE-FUR-SHORT-YELLOW | E28: 299 | F28: {=IFERROR( VALUE( INDEX(Product_Master!$I:$I, MATCH( INDEX(Pack_Master!$B:$B, MATCH($D28, Pack_Master!$A:$A, 0)), Product_Master!$B:$B, 0) )) * VALUE( INDEX(Pack_Master!$C:$C, MATCH($D28, Pack_Master!$A:$A, 0)) ) + VALUE( INDEX(Pack_Master!$D:$D, MATCH($D28, Pack_Master!$A:$A, 0)) ), "")} -> 109 | G28: {=IFERROR( ( INDEX(Pack_Master!E:E, MATCH($D28, Pack_Master!A:A, 0)) * INDEX(Pack_Master!F:F, MATCH($D28, Pack_Master!A:A, 0)) * INDEX(Pack_Master!G:G, MATCH($D28, Pack_Master!A:A, 0)) ) / INDEX(Config!C:C, MATCH($A28, Config!A:A, 0)), "")} -> 0.375 | H28: {=MAX( INDEX(Pack_Master!H:H, MATCH($D28, Pack_Master!A:A, 0)), IFERROR(G28, 0) )} -> 0.5 | I28: =IFERROR(__xludf.DUMMYFUNCTION("IFERROR( INDEX( FILTER(Shipping_Rate_Card!B:F, Shipping_Rate_Card!A:A=$A28), MATCH($H28, FILTER(Shipping_Rate_Card!B:B, Shipping_Rate_Card!A:A=$A28), 1), IF( INDEX(Config!B:B, MATCH($A28, Config!A:A, 0))=""Local"", 2, IF( INDEX(Config!B:B, "&"MATCH($A28, Config!A:A, 0))=""Regional"", 3, 4 ) ) ), """") "),67.0) -> 67 | J28: =IFERROR(__xludf.DUMMYFUNCTION("IFERROR( ( E28 * INDEX(FILTER(Pricing_Rules!E:E, Pricing_Rules!A:A=A28, Pricing_Rules!B:B=B28, Pricing_Rules!C:C<=E28, Pricing_Rules!D:D>=E28), 1) + INDEX(FILTER(Pricing_Rules!F:F, Pricing_Rules!A:A=A28, Pricing_Rules!B:B=B28, Pricing_Rules!C:C<=E28, "&"Pricing_Rules!D:D>=E28), 1) ) * (1 + IFERROR( INDEX(Config!D:D, MATCH(A28, Config!A:A, 0)), 0 )), """") "),5.8999999999999995) -> 5.9 | K28: =IFERROR(E28 - F28 - I28 - J28, "") -> 117.1 | L28: =IFERROR(K28 / E28, "") -> 0.3916388
A29: Amazon | B29: {=IF(D29="","", INDEX(Product_Master!A:A, MATCH( INDEX(Pack_Master!B:B, MATCH(D29, Pack_Master!A:A, 0)), Product_Master!B:B, 0 ) ))} -> Apparel_Caps_Beanies | C29: BEANIE-LONGFUR-BEIGE | D29: BEANIE-LONGFUR-BEIGE | E29: 299 | F29: {=IFERROR( VALUE( INDEX(Product_Master!$I:$I, MATCH( INDEX(Pack_Master!$B:$B, MATCH($D29, Pack_Master!$A:$A, 0)), Product_Master!$B:$B, 0) )) * VALUE( INDEX(Pack_Master!$C:$C, MATCH($D29, Pack_Master!$A:$A, 0)) ) + VALUE( INDEX(Pack_Master!$D:$D, MATCH($D29, Pack_Master!$A:$A, 0)) ), "")} -> 109 | G29: {=IFERROR( ( INDEX(Pack_Master!E:E, MATCH($D29, Pack_Master!A:A, 0)) * INDEX(Pack_Master!F:F, MATCH($D29, Pack_Master!A:A, 0)) * INDEX(Pack_Master!G:G, MATCH($D29, Pack_Master!A:A, 0)) ) / INDEX(Config!C:C, MATCH($A29, Config!A:A, 0)), "")} -> 0.375 | H29: {=MAX( INDEX(Pack_Master!H:H, MATCH($D29, Pack_Master!A:A, 0)), IFERROR(G29, 0) )} -> 0.5 | I29: =IFERROR(__xludf.DUMMYFUNCTION("IFERROR( INDEX( FILTER(Shipping_Rate_Card!B:F, Shipping_Rate_Card!A:A=$A29), MATCH($H29, FILTER(Shipping_Rate_Card!B:B, Shipping_Rate_Card!A:A=$A29), 1), IF( INDEX(Config!B:B, MATCH($A29, Config!A:A, 0))=""Local"", 2, IF( INDEX(Config!B:B, "&"MATCH($A29, Config!A:A, 0))=""Regional"", 3, 4 ) ) ), """") "),67.0) -> 67 | J29: =IFERROR(__xludf.DUMMYFUNCTION("IFERROR( ( E29 * INDEX(FILTER(Pricing_Rules!E:E, Pricing_Rules!A:A=A29, Pricing_Rules!B:B=B29, Pricing_Rules!C:C<=E29, Pricing_Rules!D:D>=E29), 1) + INDEX(FILTER(Pricing_Rules!F:F, Pricing_Rules!A:A=A29, Pricing_Rules!B:B=B29, Pricing_Rules!C:C<=E29, "&"Pricing_Rules!D:D>=E29), 1) ) * (1 + IFERROR( INDEX(Config!D:D, MATCH(A29, Config!A:A, 0)), 0 )), """") "),5.8999999999999995) -> 5.9 | K29: =IFERROR(E29 - F29 - I29 - J29, "") -> 117.1 | L29: =IFERROR(K29 / E29, "") -> 0.3916388
A30: Amazon | B30: {=IF(D30="","", INDEX(Product_Master!A:A, MATCH( INDEX(Pack_Master!B:B, MATCH(D30, Pack_Master!A:A, 0)), Product_Master!B:B, 0 ) ))} -> Apparel_Caps_Beanies | C30: BEANIE-LONGFUR-BLACK | D30: BEANIE-LONGFUR-BLACK | E30: 299 | F30: {=IFERROR( VALUE( INDEX(Product_Master!$I:$I, MATCH( INDEX(Pack_Master!$B:$B, MATCH($D30, Pack_Master!$A:$A, 0)), Product_Master!$B:$B, 0) )) * VALUE( INDEX(Pack_Master!$C:$C, MATCH($D30, Pack_Master!$A:$A, 0)) ) + VALUE( INDEX(Pack_Master!$D:$D, MATCH($D30, Pack_Master!$A:$A, 0)) ), "")} -> 109 | G30: {=IFERROR( ( INDEX(Pack_Master!E:E, MATCH($D30, Pack_Master!A:A, 0)) * INDEX(Pack_Master!F:F, MATCH($D30, Pack_Master!A:A, 0)) * INDEX(Pack_Master!G:G, MATCH($D30, Pack_Master!A:A, 0)) ) / INDEX(Config!C:C, MATCH($A30, Config!A:A, 0)), "")} -> 0.375 | H30: {=MAX( INDEX(Pack_Master!H:H, MATCH($D30, Pack_Master!A:A, 0)), IFERROR(G30, 0) )} -> 0.5 | I30: =IFERROR(__xludf.DUMMYFUNCTION("IFERROR( INDEX( FILTER(Shipping_Rate_Card!B:F, Shipping_Rate_Card!A:A=$A30), MATCH($H30, FILTER(Shipping_Rate_Card!B:B, Shipping_Rate_Card!A:A=$A30), 1), IF( INDEX(Config!B:B, MATCH($A30, Config!A:A, 0))=""Local"", 2, IF( INDEX(Config!B:B, "&"MATCH($A30, Config!A:A, 0))=""Regional"", 3, 4 ) ) ), """") "),67.0) -> 67 | J30: =IFERROR(__xludf.DUMMYFUNCTION("IFERROR( ( E30 * INDEX(FILTER(Pricing_Rules!E:E, Pricing_Rules!A:A=A30, Pricing_Rules!B:B=B30, Pricing_Rules!C:C<=E30, Pricing_Rules!D:D>=E30), 1) + INDEX(FILTER(Pricing_Rules!F:F, Pricing_Rules!A:A=A30, Pricing_Rules!B:B=B30, Pricing_Rules!C:C<=E30, "&"Pricing_Rules!D:D>=E30), 1) ) * (1 + IFERROR( INDEX(Config!D:D, MATCH(A30, Config!A:A, 0)), 0 )), """") "),5.8999999999999995) -> 5.9 | K30: =IFERROR(E30 - F30 - I30 - J30, "") -> 117.1 | L30: =IFERROR(K30 / E30, "") -> 0.3916388
A31: Amazon | B31: {=IF(D31="","", INDEX(Product_Master!A:A, MATCH( INDEX(Pack_Master!B:B, MATCH(D31, Pack_Master!A:A, 0)), Product_Master!B:B, 0 ) ))} -> Apparel_Caps_Beanies | C31: BEANIE-SLOUCHY-LONG-BLACK | D31: BEANIE-LONGFUR-BLACK | E31: 299 | F31: {=IFERROR( VALUE( INDEX(Product_Master!$I:$I, MATCH( INDEX(Pack_Master!$B:$B, MATCH($D31, Pack_Master!$A:$A, 0)), Product_Master!$B:$B, 0) )) * VALUE( INDEX(Pack_Master!$C:$C, MATCH($D31, Pack_Master!$A:$A, 0)) ) + VALUE( INDEX(Pack_Master!$D:$D, MATCH($D31, Pack_Master!$A:$A, 0)) ), "")} -> 109 | G31: {=IFERROR( ( INDEX(Pack_Master!E:E, MATCH($D31, Pack_Master!A:A, 0)) * INDEX(Pack_Master!F:F, MATCH($D31, Pack_Master!A:A, 0)) * INDEX(Pack_Master!G:G, MATCH($D31, Pack_Master!A:A, 0)) ) / INDEX(Config!C:C, MATCH($A31, Config!A:A, 0)), "")} -> 0.375 | H31: {=MAX( INDEX(Pack_Master!H:H, MATCH($D31, Pack_Master!A:A, 0)), IFERROR(G31, 0) )} -> 0.5 | I31: =IFERROR(__xludf.DUMMYFUNCTION("IFERROR( INDEX( FILTER(Shipping_Rate_Card!B:F, Shipping_Rate_Card!A:A=$A31), MATCH($H31, FILTER(Shipping_Rate_Card!B:B, Shipping_Rate_Card!A:A=$A31), 1), IF( INDEX(Config!B:B, MATCH($A31, Config!A:A, 0))=""Local"", 2, IF( INDEX(Config!B:B, "&"MATCH($A31, Config!A:A, 0))=""Regional"", 3, 4 ) ) ), """") "),67.0) -> 67 | J31: =IFERROR(__xludf.DUMMYFUNCTION("IFERROR( ( E31 * INDEX(FILTER(Pricing_Rules!E:E, Pricing_Rules!A:A=A31, Pricing_Rules!B:B=B31, Pricing_Rules!C:C<=E31, Pricing_Rules!D:D>=E31), 1) + INDEX(FILTER(Pricing_Rules!F:F, Pricing_Rules!A:A=A31, Pricing_Rules!B:B=B31, Pricing_Rules!C:C<=E31, "&"Pricing_Rules!D:D>=E31), 1) ) * (1 + IFERROR( INDEX(Config!D:D, MATCH(A31, Config!A:A, 0)), 0 )), """") "),5.8999999999999995) -> 5.9 | K31: =IFERROR(E31 - F31 - I31 - J31, "") -> 117.1 | L31: =IFERROR(K31 / E31, "") -> 0.3916388
A32: Amazon | B32: {=IF(D32="","", INDEX(Product_Master!A:A, MATCH( INDEX(Pack_Master!B:B, MATCH(D32, Pack_Master!A:A, 0)), Product_Master!B:B, 0 ) ))} -> Apparel_Caps_Beanies | C32: BEANIE-LONGFUR-BROWN1 | D32: BEANIE-LONGFUR-BROWN | E32: 299 | F32: {=IFERROR( VALUE( INDEX(Product_Master!$I:$I, MATCH( INDEX(Pack_Master!$B:$B, MATCH($D32, Pack_Master!$A:$A, 0)), Product_Master!$B:$B, 0) )) * VALUE( INDEX(Pack_Master!$C:$C, MATCH($D32, Pack_Master!$A:$A, 0)) ) + VALUE( INDEX(Pack_Master!$D:$D, MATCH($D32, Pack_Master!$A:$A, 0)) ), "")} -> 109 | G32: {=IFERROR( ( INDEX(Pack_Master!E:E, MATCH($D32, Pack_Master!A:A, 0)) * INDEX(Pack_Master!F:F, MATCH($D32, Pack_Master!A:A, 0)) * INDEX(Pack_Master!G:G, MATCH($D32, Pack_Master!A:A, 0)) ) / INDEX(Config!C:C, MATCH($A32, Config!A:A, 0)), "")} -> 0.375 | H32: {=MAX( INDEX(Pack_Master!H:H, MATCH($D32, Pack_Master!A:A, 0)), IFERROR(G32, 0) )} -> 0.5 | I32: =IFERROR(__xludf.DUMMYFUNCTION("IFERROR( INDEX( FILTER(Shipping_Rate_Card!B:F, Shipping_Rate_Card!A:A=$A32), MATCH($H32, FILTER(Shipping_Rate_Card!B:B, Shipping_Rate_Card!A:A=$A32), 1), IF( INDEX(Config!B:B, MATCH($A32, Config!A:A, 0))=""Local"", 2, IF( INDEX(Config!B:B, "&"MATCH($A32, Config!A:A, 0))=""Regional"", 3, 4 ) ) ), """") "),67.0) -> 67 | J32: =IFERROR(__xludf.DUMMYFUNCTION("IFERROR( ( E32 * INDEX(FILTER(Pricing_Rules!E:E, Pricing_Rules!A:A=A32, Pricing_Rules!B:B=B32, Pricing_Rules!C:C<=E32, Pricing_Rules!D:D>=E32), 1) + INDEX(FILTER(Pricing_Rules!F:F, Pricing_Rules!A:A=A32, Pricing_Rules!B:B=B32, Pricing_Rules!C:C<=E32, "&"Pricing_Rules!D:D>=E32), 1) ) * (1 + IFERROR( INDEX(Config!D:D, MATCH(A32, Config!A:A, 0)), 0 )), """") "),5.8999999999999995) -> 5.9 | K32: =IFERROR(E32 - F32 - I32 - J32, "") -> 117.1 | L32: =IFERROR(K32 / E32, "") -> 0.3916388
A33: Amazon | B33: {=IF(D33="","", INDEX(Product_Master!A:A, MATCH( INDEX(Pack_Master!B:B, MATCH(D33, Pack_Master!A:A, 0)), Product_Master!B:B, 0 ) ))} -> Apparel_Caps_Beanies | C33: BEANIE-LONGFUR-CHARCOAL | D33: BEANIE-LONGFUR-CHARCOAL | E33: 299 | F33: {=IFERROR( VALUE( INDEX(Product_Master!$I:$I, MATCH( INDEX(Pack_Master!$B:$B, MATCH($D33, Pack_Master!$A:$A, 0)), Product_Master!$B:$B, 0) )) * VALUE( INDEX(Pack_Master!$C:$C, MATCH($D33, Pack_Master!$A:$A, 0)) ) + VALUE( INDEX(Pack_Master!$D:$D, MATCH($D33, Pack_Master!$A:$A, 0)) ), "")} -> 109 | G33: {=IFERROR( ( INDEX(Pack_Master!E:E, MATCH($D33, Pack_Master!A:A, 0)) * INDEX(Pack_Master!F:F, MATCH($D33, Pack_Master!A:A, 0)) * INDEX(Pack_Master!G:G, MATCH($D33, Pack_Master!A:A, 0)) ) / INDEX(Config!C:C, MATCH($A33, Config!A:A, 0)), "")} -> 0.375 | H33: {=MAX( INDEX(Pack_Master!H:H, MATCH($D33, Pack_Master!A:A, 0)), IFERROR(G33, 0) )} -> 0.5 | I33: =IFERROR(__xludf.DUMMYFUNCTION("IFERROR( INDEX( FILTER(Shipping_Rate_Card!B:F, Shipping_Rate_Card!A:A=$A33), MATCH($H33, FILTER(Shipping_Rate_Card!B:B, Shipping_Rate_Card!A:A=$A33), 1), IF( INDEX(Config!B:B, MATCH($A33, Config!A:A, 0))=""Local"", 2, IF( INDEX(Config!B:B, "&"MATCH($A33, Config!A:A, 0))=""Regional"", 3, 4 ) ) ), """") "),67.0) -> 67 | J33: =IFERROR(__xludf.DUMMYFUNCTION("IFERROR( ( E33 * INDEX(FILTER(Pricing_Rules!E:E, Pricing_Rules!A:A=A33, Pricing_Rules!B:B=B33, Pricing_Rules!C:C<=E33, Pricing_Rules!D:D>=E33), 1) + INDEX(FILTER(Pricing_Rules!F:F, Pricing_Rules!A:A=A33, Pricing_Rules!B:B=B33, Pricing_Rules!C:C<=E33, "&"Pricing_Rules!D:D>=E33), 1) ) * (1 + IFERROR( INDEX(Config!D:D, MATCH(A33, Config!A:A, 0)), 0 )), """") "),5.8999999999999995) -> 5.9 | K33: =IFERROR(E33 - F33 - I33 - J33, "") -> 117.1 | L33: =IFERROR(K33 / E33, "") -> 0.3916388
A34: Amazon | B34: {=IF(D34="","", INDEX(Product_Master!A:A, MATCH( INDEX(Pack_Master!B:B, MATCH(D34, Pack_Master!A:A, 0)), Product_Master!B:B, 0 ) ))} -> Apparel_Caps_Beanies | C34: BEANIE-LONGFUR-MAROON | D34: BEANIE-LONGFUR-MAROON | E34: 299 | F34: {=IFERROR( VALUE( INDEX(Product_Master!$I:$I, MATCH( INDEX(Pack_Master!$B:$B, MATCH($D34, Pack_Master!$A:$A, 0)), Product_Master!$B:$B, 0) )) * VALUE( INDEX(Pack_Master!$C:$C, MATCH($D34, Pack_Master!$A:$A, 0)) ) + VALUE( INDEX(Pack_Master!$D:$D, MATCH($D34, Pack_Master!$A:$A, 0)) ), "")} -> 109 | G34: {=IFERROR( ( INDEX(Pack_Master!E:E, MATCH($D34, Pack_Master!A:A, 0)) * INDEX(Pack_Master!F:F, MATCH($D34, Pack_Master!A:A, 0)) * INDEX(Pack_Master!G:G, MATCH($D34, Pack_Master!A:A, 0)) ) / INDEX(Config!C:C, MATCH($A34, Config!A:A, 0)), "")} -> 0.375 | H34: {=MAX( INDEX(Pack_Master!H:H, MATCH($D34, Pack_Master!A:A, 0)), IFERROR(G34, 0) )} -> 0.5 | I34: =IFERROR(__xludf.DUMMYFUNCTION("IFERROR( INDEX( FILTER(Shipping_Rate_Card!B:F, Shipping_Rate_Card!A:A=$A34), MATCH($H34, FILTER(Shipping_Rate_Card!B:B, Shipping_Rate_Card!A:A=$A34), 1), IF( INDEX(Config!B:B, MATCH($A34, Config!A:A, 0))=""Local"", 2, IF( INDEX(Config!B:B, "&"MATCH($A34, Config!A:A, 0))=""Regional"", 3, 4 ) ) ), """") "),67.0) -> 67 | J34: =IFERROR(__xludf.DUMMYFUNCTION("IFERROR( ( E34 * INDEX(FILTER(Pricing_Rules!E:E, Pricing_Rules!A:A=A34, Pricing_Rules!B:B=B34, Pricing_Rules!C:C<=E34, Pricing_Rules!D:D>=E34), 1) + INDEX(FILTER(Pricing_Rules!F:F, Pricing_Rules!A:A=A34, Pricing_Rules!B:B=B34, Pricing_Rules!C:C<=E34, "&"Pricing_Rules!D:D>=E34), 1) ) * (1 + IFERROR( INDEX(Config!D:D, MATCH(A34, Config!A:A, 0)), 0 )), """") "),5.8999999999999995) -> 5.9 | K34: =IFERROR(E34 - F34 - I34 - J34, "") -> 117.1 | L34: =IFERROR(K34 / E34, "") -> 0.3916388
A35: Amazon | B35: {=IF(D35="","", INDEX(Product_Master!A:A, MATCH( INDEX(Pack_Master!B:B, MATCH(D35, Pack_Master!A:A, 0)), Product_Master!B:B, 0 ) ))} -> Apparel_Caps_Beanies | C35: BEANIE-LONGFUR-NAVYBLUE | D35: BEANIE-LONGFUR-NAVYBLUE | E35: 299 | F35: {=IFERROR( VALUE( INDEX(Product_Master!$I:$I, MATCH( INDEX(Pack_Master!$B:$B, MATCH($D35, Pack_Master!$A:$A, 0)), Product_Master!$B:$B, 0) )) * VALUE( INDEX(Pack_Master!$C:$C, MATCH($D35, Pack_Master!$A:$A, 0)) ) + VALUE( INDEX(Pack_Master!$D:$D, MATCH($D35, Pack_Master!$A:$A, 0)) ), "")} -> 109 | G35: {=IFERROR( ( INDEX(Pack_Master!E:E, MATCH($D35, Pack_Master!A:A, 0)) * INDEX(Pack_Master!F:F, MATCH($D35, Pack_Master!A:A, 0)) * INDEX(Pack_Master!G:G, MATCH($D35, Pack_Master!A:A, 0)) ) / INDEX(Config!C:C, MATCH($A35, Config!A:A, 0)), "")} -> 0.375 | H35: {=MAX( INDEX(Pack_Master!H:H, MATCH($D35, Pack_Master!A:A, 0)), IFERROR(G35, 0) )} -> 0.5 | I35: =IFERROR(__xludf.DUMMYFUNCTION("IFERROR( INDEX( FILTER(Shipping_Rate_Card!B:F, Shipping_Rate_Card!A:A=$A35), MATCH($H35, FILTER(Shipping_Rate_Card!B:B, Shipping_Rate_Card!A:A=$A35), 1), IF( INDEX(Config!B:B, MATCH($A35, Config!A:A, 0))=""Local"", 2, IF( INDEX(Config!B:B, "&"MATCH($A35, Config!A:A, 0))=""Regional"", 3, 4 ) ) ), """") "),67.0) -> 67 | J35: =IFERROR(__xludf.DUMMYFUNCTION("IFERROR( ( E35 * INDEX(FILTER(Pricing_Rules!E:E, Pricing_Rules!A:A=A35, Pricing_Rules!B:B=B35, Pricing_Rules!C:C<=E35, Pricing_Rules!D:D>=E35), 1) + INDEX(FILTER(Pricing_Rules!F:F, Pricing_Rules!A:A=A35, Pricing_Rules!B:B=B35, Pricing_Rules!C:C<=E35, "&"Pricing_Rules!D:D>=E35), 1) ) * (1 + IFERROR( INDEX(Config!D:D, MATCH(A35, Config!A:A, 0)), 0 )), """") "),5.8999999999999995) -> 5.9 | K35: =IFERROR(E35 - F35 - I35 - J35, "") -> 117.1 | L35: =IFERROR(K35 / E35, "") -> 0.3916388
A36: Amazon | B36: {=IF(D36="","", INDEX(Product_Master!A:A, MATCH( INDEX(Pack_Master!B:B, MATCH(D36, Pack_Master!A:A, 0)), Product_Master!B:B, 0 ) ))} -> Apparel_Caps_Beanies | C36: BEANIE-FUR-SHORT-BEIGE | D36: BEANIE-SHORTFUR-BEIGE | E36: 299 | F36: {=IFERROR( VALUE( INDEX(Product_Master!$I:$I, MATCH( INDEX(Pack_Master!$B:$B, MATCH($D36, Pack_Master!$A:$A, 0)), Product_Master!$B:$B, 0) )) * VALUE( INDEX(Pack_Master!$C:$C, MATCH($D36, Pack_Master!$A:$A, 0)) ) + VALUE( INDEX(Pack_Master!$D:$D, MATCH($D36, Pack_Master!$A:$A, 0)) ), "")} -> 109 | G36: {=IFERROR( ( INDEX(Pack_Master!E:E, MATCH($D36, Pack_Master!A:A, 0)) * INDEX(Pack_Master!F:F, MATCH($D36, Pack_Master!A:A, 0)) * INDEX(Pack_Master!G:G, MATCH($D36, Pack_Master!A:A, 0)) ) / INDEX(Config!C:C, MATCH($A36, Config!A:A, 0)), "")} -> 0.375 | H36: {=MAX( INDEX(Pack_Master!H:H, MATCH($D36, Pack_Master!A:A, 0)), IFERROR(G36, 0) )} -> 0.5 | I36: =IFERROR(__xludf.DUMMYFUNCTION("IFERROR( INDEX( FILTER(Shipping_Rate_Card!B:F, Shipping_Rate_Card!A:A=$A36), MATCH($H36, FILTER(Shipping_Rate_Card!B:B, Shipping_Rate_Card!A:A=$A36), 1), IF( INDEX(Config!B:B, MATCH($A36, Config!A:A, 0))=""Local"", 2, IF( INDEX(Config!B:B, "&"MATCH($A36, Config!A:A, 0))=""Regional"", 3, 4 ) ) ), """") "),67.0) -> 67 | J36: =IFERROR(__xludf.DUMMYFUNCTION("IFERROR( ( E36 * INDEX(FILTER(Pricing_Rules!E:E, Pricing_Rules!A:A=A36, Pricing_Rules!B:B=B36, Pricing_Rules!C:C<=E36, Pricing_Rules!D:D>=E36), 1) + INDEX(FILTER(Pricing_Rules!F:F, Pricing_Rules!A:A=A36, Pricing_Rules!B:B=B36, Pricing_Rules!C:C<=E36, "&"Pricing_Rules!D:D>=E36), 1) ) * (1 + IFERROR( INDEX(Config!D:D, MATCH(A36, Config!A:A, 0)), 0 )), """") "),5.8999999999999995) -> 5.9 | K36: =IFERROR(E36 - F36 - I36 - J36, "") -> 117.1 | L36: =IFERROR(K36 / E36, "") -> 0.3916388
A37: Amazon | B37: {=IF(D37="","", INDEX(Product_Master!A:A, MATCH( INDEX(Pack_Master!B:B, MATCH(D37, Pack_Master!A:A, 0)), Product_Master!B:B, 0 ) ))} -> Apparel_Caps_Beanies | C37: BEANIE-FUR-SHORT-BLACK | D37: BEANIE-SHORTFUR-BLACK | E37: 299 | F37: {=IFERROR( VALUE( INDEX(Product_Master!$I:$I, MATCH( INDEX(Pack_Master!$B:$B, MATCH($D37, Pack_Master!$A:$A, 0)), Product_Master!$B:$B, 0) )) * VALUE( INDEX(Pack_Master!$C:$C, MATCH($D37, Pack_Master!$A:$A, 0)) ) + VALUE( INDEX(Pack_Master!$D:$D, MATCH($D37, Pack_Master!$A:$A, 0)) ), "")} -> 109 | G37: {=IFERROR( ( INDEX(Pack_Master!E:E, MATCH($D37, Pack_Master!A:A, 0)) * INDEX(Pack_Master!F:F, MATCH($D37, Pack_Master!A:A, 0)) * INDEX(Pack_Master!G:G, MATCH($D37, Pack_Master!A:A, 0)) ) / INDEX(Config!C:C, MATCH($A37, Config!A:A, 0)), "")} -> 0.375 | H37: {=MAX( INDEX(Pack_Master!H:H, MATCH($D37, Pack_Master!A:A, 0)), IFERROR(G37, 0) )} -> 0.5 | I37: =IFERROR(__xludf.DUMMYFUNCTION("IFERROR( INDEX( FILTER(Shipping_Rate_Card!B:F, Shipping_Rate_Card!A:A=$A37), MATCH($H37, FILTER(Shipping_Rate_Card!B:B, Shipping_Rate_Card!A:A=$A37), 1), IF( INDEX(Config!B:B, MATCH($A37, Config!A:A, 0))=""Local"", 2, IF( INDEX(Config!B:B, "&"MATCH($A37, Config!A:A, 0))=""Regional"", 3, 4 ) ) ), """") "),67.0) -> 67 | J37: =IFERROR(__xludf.DUMMYFUNCTION("IFERROR( ( E37 * INDEX(FILTER(Pricing_Rules!E:E, Pricing_Rules!A:A=A37, Pricing_Rules!B:B=B37, Pricing_Rules!C:C<=E37, Pricing_Rules!D:D>=E37), 1) + INDEX(FILTER(Pricing_Rules!F:F, Pricing_Rules!A:A=A37, Pricing_Rules!B:B=B37, Pricing_Rules!C:C<=E37, "&"Pricing_Rules!D:D>=E37), 1) ) * (1 + IFERROR( INDEX(Config!D:D, MATCH(A37, Config!A:A, 0)), 0 )), """") "),5.8999999999999995) -> 5.9 | K37: =IFERROR(E37 - F37 - I37 - J37, "") -> 117.1 | L37: =IFERROR(K37 / E37, "") -> 0.3916388
A38: Amazon | B38: {=IF(D38="","", INDEX(Product_Master!A:A, MATCH( INDEX(Pack_Master!B:B, MATCH(D38, Pack_Master!A:A, 0)), Product_Master!B:B, 0 ) ))} -> Apparel_Caps_Beanies | C38: BEANIE-SHORTFUR-BROWN | D38: BEANIE-SHORTFUR-BROWN | E38: 299 | F38: {=IFERROR( VALUE( INDEX(Product_Master!$I:$I, MATCH( INDEX(Pack_Master!$B:$B, MATCH($D38, Pack_Master!$A:$A, 0)), Product_Master!$B:$B, 0) )) * VALUE( INDEX(Pack_Master!$C:$C, MATCH($D38, Pack_Master!$A:$A, 0)) ) + VALUE( INDEX(Pack_Master!$D:$D, MATCH($D38, Pack_Master!$A:$A, 0)) ), "")} -> 109 | G38: {=IFERROR( ( INDEX(Pack_Master!E:E, MATCH($D38, Pack_Master!A:A, 0)) * INDEX(Pack_Master!F:F, MATCH($D38, Pack_Master!A:A, 0)) * INDEX(Pack_Master!G:G, MATCH($D38, Pack_Master!A:A, 0)) ) / INDEX(Config!C:C, MATCH($A38, Config!A:A, 0)), "")} -> 0.375 | H38: {=MAX( INDEX(Pack_Master!H:H, MATCH($D38, Pack_Master!A:A, 0)), IFERROR(G38, 0) )} -> 0.5 | I38: =IFERROR(__xludf.DUMMYFUNCTION("IFERROR( INDEX( FILTER(Shipping_Rate_Card!B:F, Shipping_Rate_Card!A:A=$A38), MATCH($H38, FILTER(Shipping_Rate_Card!B:B, Shipping_Rate_Card!A:A=$A38), 1), IF( INDEX(Config!B:B, MATCH($A38, Config!A:A, 0))=""Local"", 2, IF( INDEX(Config!B:B, "&"MATCH($A38, Config!A:A, 0))=""Regional"", 3, 4 ) ) ), """") "),67.0) -> 67 | J38: =IFERROR(__xludf.DUMMYFUNCTION("IFERROR( ( E38 * INDEX(FILTER(Pricing_Rules!E:E, Pricing_Rules!A:A=A38, Pricing_Rules!B:B=B38, Pricing_Rules!C:C<=E38, Pricing_Rules!D:D>=E38), 1) + INDEX(FILTER(Pricing_Rules!F:F, Pricing_Rules!A:A=A38, Pricing_Rules!B:B=B38, Pricing_Rules!C:C<=E38, "&"Pricing_Rules!D:D>=E38), 1) ) * (1 + IFERROR( INDEX(Config!D:D, MATCH(A38, Config!A:A, 0)), 0 )), """") "),5.8999999999999995) -> 5.9 | K38: =IFERROR(E38 - F38 - I38 - J38, "") -> 117.1 | L38: =IFERROR(K38 / E38, "") -> 0.3916388
A39: Flipkart | B39: {=IF(D39="","", INDEX(Product_Master!A:A, MATCH( INDEX(Pack_Master!B:B, MATCH(D39, Pack_Master!A:A, 0)), Product_Master!B:B, 0 ) ))} -> Apparel_Caps_Beanies | C39: BEANIE-FUR-SHORT-GREEN | D39: BEANIE-SHORTFUR-GREEN | E39: 299 | F39: {=IFERROR( VALUE( INDEX(Product_Master!$I:$I, MATCH( INDEX(Pack_Master!$B:$B, MATCH($D39, Pack_Master!$A:$A, 0)), Product_Master!$B:$B, 0) )) * VALUE( INDEX(Pack_Master!$C:$C, MATCH($D39, Pack_Master!$A:$A, 0)) ) + VALUE( INDEX(Pack_Master!$D:$D, MATCH($D39, Pack_Master!$A:$A, 0)) ), "")} -> 109 | G39: {=IFERROR( ( INDEX(Pack_Master!E:E, MATCH($D39, Pack_Master!A:A, 0)) * INDEX(Pack_Master!F:F, MATCH($D39, Pack_Master!A:A, 0)) * INDEX(Pack_Master!G:G, MATCH($D39, Pack_Master!A:A, 0)) ) / INDEX(Config!C:C, MATCH($A39, Config!A:A, 0)), "")} -> 0.375 | H39: {=MAX( INDEX(Pack_Master!H:H, MATCH($D39, Pack_Master!A:A, 0)), IFERROR(G39, 0) )} -> 0.5 | I39: =IFERROR(__xludf.DUMMYFUNCTION("IFERROR( INDEX( FILTER(Shipping_Rate_Card!B:F, Shipping_Rate_Card!A:A=$A39), MATCH($H39, FILTER(Shipping_Rate_Card!B:B, Shipping_Rate_Card!A:A=$A39), 1), IF( INDEX(Config!B:B, MATCH($A39, Config!A:A, 0))=""Local"", 2, IF( INDEX(Config!B:B, "&"MATCH($A39, Config!A:A, 0))=""Regional"", 3, 4 ) ) ), """") "),75.0) -> 75 | J39: =IFERROR(__xludf.DUMMYFUNCTION("IFERROR( ( E39 * INDEX(FILTER(Pricing_Rules!E:E, Pricing_Rules!A:A=A39, Pricing_Rules!B:B=B39, Pricing_Rules!C:C<=E39, Pricing_Rules!D:D>=E39), 1) + INDEX(FILTER(Pricing_Rules!F:F, Pricing_Rules!A:A=A39, Pricing_Rules!B:B=B39, Pricing_Rules!C:C<=E39, "&"Pricing_Rules!D:D>=E39), 1) ) * (1 + IFERROR( INDEX(Config!D:D, MATCH(A39, Config!A:A, 0)), 0 )), """") "),15.34) -> 15.34 | K39: =IFERROR(E39 - F39 - I39 - J39, "") -> 99.66 | L39: =IFERROR(K39 / E39, "") -> 0.33331104
A40: Flipkart | B40: {=IF(D40="","", INDEX(Product_Master!A:A, MATCH( INDEX(Pack_Master!B:B, MATCH(D40, Pack_Master!A:A, 0)), Product_Master!B:B, 0 ) ))} -> Apparel_Caps_Beanies | C40: BEANIE-SHORTFUR-GREY | D40: BEANIE-SHORTFUR-GREY | E40: 299 | F40: {=IFERROR( VALUE( INDEX(Product_Master!$I:$I, MATCH( INDEX(Pack_Master!$B:$B, MATCH($D40, Pack_Master!$A:$A, 0)), Product_Master!$B:$B, 0) )) * VALUE( INDEX(Pack_Master!$C:$C, MATCH($D40, Pack_Master!$A:$A, 0)) ) + VALUE( INDEX(Pack_Master!$D:$D, MATCH($D40, Pack_Master!$A:$A, 0)) ), "")} -> 109 | G40: {=IFERROR( ( INDEX(Pack_Master!E:E, MATCH($D40, Pack_Master!A:A, 0)) * INDEX(Pack_Master!F:F, MATCH($D40, Pack_Master!A:A, 0)) * INDEX(Pack_Master!G:G, MATCH($D40, Pack_Master!A:A, 0)) ) / INDEX(Config!C:C, MATCH($A40, Config!A:A, 0)), "")} -> 0.375 | H40: {=MAX( INDEX(Pack_Master!H:H, MATCH($D40, Pack_Master!A:A, 0)), IFERROR(G40, 0) )} -> 0.5 | I40: =IFERROR(__xludf.DUMMYFUNCTION("IFERROR( INDEX( FILTER(Shipping_Rate_Card!B:F, Shipping_Rate_Card!A:A=$A40), MATCH($H40, FILTER(Shipping_Rate_Card!B:B, Shipping_Rate_Card!A:A=$A40), 1), IF( INDEX(Config!B:B, MATCH($A40, Config!A:A, 0))=""Local"", 2, IF( INDEX(Config!B:B, "&"MATCH($A40, Config!A:A, 0))=""Regional"", 3, 4 ) ) ), """") "),75.0) -> 75 | J40: =IFERROR(__xludf.DUMMYFUNCTION("IFERROR( ( E40 * INDEX(FILTER(Pricing_Rules!E:E, Pricing_Rules!A:A=A40, Pricing_Rules!B:B=B40, Pricing_Rules!C:C<=E40, Pricing_Rules!D:D>=E40), 1) + INDEX(FILTER(Pricing_Rules!F:F, Pricing_Rules!A:A=A40, Pricing_Rules!B:B=B40, Pricing_Rules!C:C<=E40, "&"Pricing_Rules!D:D>=E40), 1) ) * (1 + IFERROR( INDEX(Config!D:D, MATCH(A40, Config!A:A, 0)), 0 )), """") "),15.34) -> 15.34 | K40: =IFERROR(E40 - F40 - I40 - J40, "") -> 99.66 | L40: =IFERROR(K40 / E40, "") -> 0.33331104
A41: Flipkart | B41: {=IF(D41="","", INDEX(Product_Master!A:A, MATCH( INDEX(Pack_Master!B:B, MATCH(D41, Pack_Master!A:A, 0)), Product_Master!B:B, 0 ) ))} -> Apparel_Caps_Beanies | C41: BEANIE-SHORTFUR-MESH-BEIGE | D41: BEANIE-SHORTFUR-MESH-BEIGE | E41: 299 | F41: {=IFERROR( VALUE( INDEX(Product_Master!$I:$I, MATCH( INDEX(Pack_Master!$B:$B, MATCH($D41, Pack_Master!$A:$A, 0)), Product_Master!$B:$B, 0) )) * VALUE( INDEX(Pack_Master!$C:$C, MATCH($D41, Pack_Master!$A:$A, 0)) ) + VALUE( INDEX(Pack_Master!$D:$D, MATCH($D41, Pack_Master!$A:$A, 0)) ), "")} -> 109 | G41: {=IFERROR( ( INDEX(Pack_Master!E:E, MATCH($D41, Pack_Master!A:A, 0)) * INDEX(Pack_Master!F:F, MATCH($D41, Pack_Master!A:A, 0)) * INDEX(Pack_Master!G:G, MATCH($D41, Pack_Master!A:A, 0)) ) / INDEX(Config!C:C, MATCH($A41, Config!A:A, 0)), "")} -> 0.375 | H41: {=MAX( INDEX(Pack_Master!H:H, MATCH($D41, Pack_Master!A:A, 0)), IFERROR(G41, 0) )} -> 0.5 | I41: =IFERROR(__xludf.DUMMYFUNCTION("IFERROR( INDEX( FILTER(Shipping_Rate_Card!B:F, Shipping_Rate_Card!A:A=$A41), MATCH($H41, FILTER(Shipping_Rate_Card!B:B, Shipping_Rate_Card!A:A=$A41), 1), IF( INDEX(Config!B:B, MATCH($A41, Config!A:A, 0))=""Local"", 2, IF( INDEX(Config!B:B, "&"MATCH($A41, Config!A:A, 0))=""Regional"", 3, 4 ) ) ), """") "),75.0) -> 75 | J41: =IFERROR(__xludf.DUMMYFUNCTION("IFERROR( ( E41 * INDEX(FILTER(Pricing_Rules!E:E, Pricing_Rules!A:A=A41, Pricing_Rules!B:B=B41, Pricing_Rules!C:C<=E41, Pricing_Rules!D:D>=E41), 1) + INDEX(FILTER(Pricing_Rules!F:F, Pricing_Rules!A:A=A41, Pricing_Rules!B:B=B41, Pricing_Rules!C:C<=E41, "&"Pricing_Rules!D:D>=E41), 1) ) * (1 + IFERROR( INDEX(Config!D:D, MATCH(A41, Config!A:A, 0)), 0 )), """") "),15.34) -> 15.34 | K41: =IFERROR(E41 - F41 - I41 - J41, "") -> 99.66 | L41: =IFERROR(K41 / E41, "") -> 0.33331104
A42: Flipkart | B42: {=IF(D42="","", INDEX(Product_Master!A:A, MATCH( INDEX(Pack_Master!B:B, MATCH(D42, Pack_Master!A:A, 0)), Product_Master!B:B, 0 ) ))} -> Apparel_Caps_Beanies | C42: BEANIE-SHORTFUR-MESH-MAROON | D42: BEANIE-SHORTFUR-MESH-MAROON | E42: 299 | F42: {=IFERROR( VALUE( INDEX(Product_Master!$I:$I, MATCH( INDEX(Pack_Master!$B:$B, MATCH($D42, Pack_Master!$A:$A, 0)), Product_Master!$B:$B, 0) )) * VALUE( INDEX(Pack_Master!$C:$C, MATCH($D42, Pack_Master!$A:$A, 0)) ) + VALUE( INDEX(Pack_Master!$D:$D, MATCH($D42, Pack_Master!$A:$A, 0)) ), "")} -> 109 | G42: {=IFERROR( ( INDEX(Pack_Master!E:E, MATCH($D42, Pack_Master!A:A, 0)) * INDEX(Pack_Master!F:F, MATCH($D42, Pack_Master!A:A, 0)) * INDEX(Pack_Master!G:G, MATCH($D42, Pack_Master!A:A, 0)) ) / INDEX(Config!C:C, MATCH($A42, Config!A:A, 0)), "")} -> 0.375 | H42: {=MAX( INDEX(Pack_Master!H:H, MATCH($D42, Pack_Master!A:A, 0)), IFERROR(G42, 0) )} -> 0.5 | I42: =IFERROR(__xludf.DUMMYFUNCTION("IFERROR( INDEX( FILTER(Shipping_Rate_Card!B:F, Shipping_Rate_Card!A:A=$A42), MATCH($H42, FILTER(Shipping_Rate_Card!B:B, Shipping_Rate_Card!A:A=$A42), 1), IF( INDEX(Config!B:B, MATCH($A42, Config!A:A, 0))=""Local"", 2, IF( INDEX(Config!B:B, "&"MATCH($A42, Config!A:A, 0))=""Regional"", 3, 4 ) ) ), """") "),75.0) -> 75 | J42: =IFERROR(__xludf.DUMMYFUNCTION("IFERROR( ( E42 * INDEX(FILTER(Pricing_Rules!E:E, Pricing_Rules!A:A=A42, Pricing_Rules!B:B=B42, Pricing_Rules!C:C<=E42, Pricing_Rules!D:D>=E42), 1) + INDEX(FILTER(Pricing_Rules!F:F, Pricing_Rules!A:A=A42, Pricing_Rules!B:B=B42, Pricing_Rules!C:C<=E42, "&"Pricing_Rules!D:D>=E42), 1) ) * (1 + IFERROR( INDEX(Config!D:D, MATCH(A42, Config!A:A, 0)), 0 )), """") "),15.34) -> 15.34 | K42: =IFERROR(E42 - F42 - I42 - J42, "") -> 99.66 | L42: =IFERROR(K42 / E42, "") -> 0.33331104
A43: Flipkart | B43: {=IF(D43="","", INDEX(Product_Master!A:A, MATCH( INDEX(Pack_Master!B:B, MATCH(D43, Pack_Master!A:A, 0)), Product_Master!B:B, 0 ) ))} -> Apparel_Caps_Beanies | C43: BEANIE-SHORTFUR-MESH-NAVYBLUE | D43: BEANIE-SHORTFUR-MESH-NAVYBLUE | E43: 299 | F43: {=IFERROR( VALUE( INDEX(Product_Master!$I:$I, MATCH( INDEX(Pack_Master!$B:$B, MATCH($D43, Pack_Master!$A:$A, 0)), Product_Master!$B:$B, 0) )) * VALUE( INDEX(Pack_Master!$C:$C, MATCH($D43, Pack_Master!$A:$A, 0)) ) + VALUE( INDEX(Pack_Master!$D:$D, MATCH($D43, Pack_Master!$A:$A, 0)) ), "")} -> 109 | G43: {=IFERROR( ( INDEX(Pack_Master!E:E, MATCH($D43, Pack_Master!A:A, 0)) * INDEX(Pack_Master!F:F, MATCH($D43, Pack_Master!A:A, 0)) * INDEX(Pack_Master!G:G, MATCH($D43, Pack_Master!A:A, 0)) ) / INDEX(Config!C:C, MATCH($A43, Config!A:A, 0)), "")} -> 0.375 | H43: {=MAX( INDEX(Pack_Master!H:H, MATCH($D43, Pack_Master!A:A, 0)), IFERROR(G43, 0) )} -> 0.5 | I43: =IFERROR(__xludf.DUMMYFUNCTION("IFERROR( INDEX( FILTER(Shipping_Rate_Card!B:F, Shipping_Rate_Card!A:A=$A43), MATCH($H43, FILTER(Shipping_Rate_Card!B:B, Shipping_Rate_Card!A:A=$A43), 1), IF( INDEX(Config!B:B, MATCH($A43, Config!A:A, 0))=""Local"", 2, IF( INDEX(Config!B:B, "&"MATCH($A43, Config!A:A, 0))=""Regional"", 3, 4 ) ) ), """") "),75.0) -> 75 | J43: =IFERROR(__xludf.DUMMYFUNCTION("IFERROR( ( E43 * INDEX(FILTER(Pricing_Rules!E:E, Pricing_Rules!A:A=A43, Pricing_Rules!B:B=B43, Pricing_Rules!C:C<=E43, Pricing_Rules!D:D>=E43), 1) + INDEX(FILTER(Pricing_Rules!F:F, Pricing_Rules!A:A=A43, Pricing_Rules!B:B=B43, Pricing_Rules!C:C<=E43, "&"Pricing_Rules!D:D>=E43), 1) ) * (1 + IFERROR( INDEX(Config!D:D, MATCH(A43, Config!A:A, 0)), 0 )), """") "),15.34) -> 15.34 | K43: =IFERROR(E43 - F43 - I43 - J43, "") -> 99.66 | L43: =IFERROR(K43 / E43, "") -> 0.33331104
A44: Flipkart | B44: {=IF(D44="","", INDEX(Product_Master!A:A, MATCH( INDEX(Pack_Master!B:B, MATCH(D44, Pack_Master!A:A, 0)), Product_Master!B:B, 0 ) ))} -> Apparel_Caps_Beanies | C44: BEANIE-SHORTFUR-OLIVE | D44: BEANIE-SHORTFUR-OLIVE | E44: 299 | F44: {=IFERROR( VALUE( INDEX(Product_Master!$I:$I, MATCH( INDEX(Pack_Master!$B:$B, MATCH($D44, Pack_Master!$A:$A, 0)), Product_Master!$B:$B, 0) )) * VALUE( INDEX(Pack_Master!$C:$C, MATCH($D44, Pack_Master!$A:$A, 0)) ) + VALUE( INDEX(Pack_Master!$D:$D, MATCH($D44, Pack_Master!$A:$A, 0)) ), "")} -> 109 | G44: {=IFERROR( ( INDEX(Pack_Master!E:E, MATCH($D44, Pack_Master!A:A, 0)) * INDEX(Pack_Master!F:F, MATCH($D44, Pack_Master!A:A, 0)) * INDEX(Pack_Master!G:G, MATCH($D44, Pack_Master!A:A, 0)) ) / INDEX(Config!C:C, MATCH($A44, Config!A:A, 0)), "")} -> 0.375 | H44: {=MAX( INDEX(Pack_Master!H:H, MATCH($D44, Pack_Master!A:A, 0)), IFERROR(G44, 0) )} -> 0.5 | I44: =IFERROR(__xludf.DUMMYFUNCTION("IFERROR( INDEX( FILTER(Shipping_Rate_Card!B:F, Shipping_Rate_Card!A:A=$A44), MATCH($H44, FILTER(Shipping_Rate_Card!B:B, Shipping_Rate_Card!A:A=$A44), 1), IF( INDEX(Config!B:B, MATCH($A44, Config!A:A, 0))=""Local"", 2, IF( INDEX(Config!B:B, "&"MATCH($A44, Config!A:A, 0))=""Regional"", 3, 4 ) ) ), """") "),75.0) -> 75 | J44: =IFERROR(__xludf.DUMMYFUNCTION("IFERROR( ( E44 * INDEX(FILTER(Pricing_Rules!E:E, Pricing_Rules!A:A=A44, Pricing_Rules!B:B=B44, Pricing_Rules!C:C<=E44, Pricing_Rules!D:D>=E44), 1) + INDEX(FILTER(Pricing_Rules!F:F, Pricing_Rules!A:A=A44, Pricing_Rules!B:B=B44, Pricing_Rules!C:C<=E44, "&"Pricing_Rules!D:D>=E44), 1) ) * (1 + IFERROR( INDEX(Config!D:D, MATCH(A44, Config!A:A, 0)), 0 )), """") "),15.34) -> 15.34 | K44: =IFERROR(E44 - F44 - I44 - J44, "") -> 99.66 | L44: =IFERROR(K44 / E44, "") -> 0.33331104
A45: Flipkart | B45: {=IF(D45="","", INDEX(Product_Master!A:A, MATCH( INDEX(Pack_Master!B:B, MATCH(D45, Pack_Master!A:A, 0)), Product_Master!B:B, 0 ) ))} -> Apparel_Caps_Beanies | C45: BEANIE-SHORTFUR-RED | D45: BEANIE-SHORTFUR-RED | E45: 299 | F45: {=IFERROR( VALUE( INDEX(Product_Master!$I:$I, MATCH( INDEX(Pack_Master!$B:$B, MATCH($D45, Pack_Master!$A:$A, 0)), Product_Master!$B:$B, 0) )) * VALUE( INDEX(Pack_Master!$C:$C, MATCH($D45, Pack_Master!$A:$A, 0)) ) + VALUE( INDEX(Pack_Master!$D:$D, MATCH($D45, Pack_Master!$A:$A, 0)) ), "")} -> 109 | G45: {=IFERROR( ( INDEX(Pack_Master!E:E, MATCH($D45, Pack_Master!A:A, 0)) * INDEX(Pack_Master!F:F, MATCH($D45, Pack_Master!A:A, 0)) * INDEX(Pack_Master!G:G, MATCH($D45, Pack_Master!A:A, 0)) ) / INDEX(Config!C:C, MATCH($A45, Config!A:A, 0)), "")} -> 0.375 | H45: {=MAX( INDEX(Pack_Master!H:H, MATCH($D45, Pack_Master!A:A, 0)), IFERROR(G45, 0) )} -> 0.5 | I45: =IFERROR(__xludf.DUMMYFUNCTION("IFERROR( INDEX( FILTER(Shipping_Rate_Card!B:F, Shipping_Rate_Card!A:A=$A45), MATCH($H45, FILTER(Shipping_Rate_Card!B:B, Shipping_Rate_Card!A:A=$A45), 1), IF( INDEX(Config!B:B, MATCH($A45, Config!A:A, 0))=""Local"", 2, IF( INDEX(Config!B:B, "&"MATCH($A45, Config!A:A, 0))=""Regional"", 3, 4 ) ) ), """") "),75.0) -> 75 | J45: =IFERROR(__xludf.DUMMYFUNCTION("IFERROR( ( E45 * INDEX(FILTER(Pricing_Rules!E:E, Pricing_Rules!A:A=A45, Pricing_Rules!B:B=B45, Pricing_Rules!C:C<=E45, Pricing_Rules!D:D>=E45), 1) + INDEX(FILTER(Pricing_Rules!F:F, Pricing_Rules!A:A=A45, Pricing_Rules!B:B=B45, Pricing_Rules!C:C<=E45, "&"Pricing_Rules!D:D>=E45), 1) ) * (1 + IFERROR( INDEX(Config!D:D, MATCH(A45, Config!A:A, 0)), 0 )), """") "),15.34) -> 15.34 | K45: =IFERROR(E45 - F45 - I45 - J45, "") -> 99.66 | L45: =IFERROR(K45 / E45, "") -> 0.33331104
A46: Flipkart | B46: {=IF(D46="","", INDEX(Product_Master!A:A, MATCH( INDEX(Pack_Master!B:B, MATCH(D46, Pack_Master!A:A, 0)), Product_Master!B:B, 0 ) ))} -> Apparel_Caps_Beanies | C46: BEANIE-SHORTFUR-YELLOW | D46: BEANIE-SHORTFUR-YELLOW | E46: 299 | F46: {=IFERROR( VALUE( INDEX(Product_Master!$I:$I, MATCH( INDEX(Pack_Master!$B:$B, MATCH($D46, Pack_Master!$A:$A, 0)), Product_Master!$B:$B, 0) )) * VALUE( INDEX(Pack_Master!$C:$C, MATCH($D46, Pack_Master!$A:$A, 0)) ) + VALUE( INDEX(Pack_Master!$D:$D, MATCH($D46, Pack_Master!$A:$A, 0)) ), "")} -> 109 | G46: {=IFERROR( ( INDEX(Pack_Master!E:E, MATCH($D46, Pack_Master!A:A, 0)) * INDEX(Pack_Master!F:F, MATCH($D46, Pack_Master!A:A, 0)) * INDEX(Pack_Master!G:G, MATCH($D46, Pack_Master!A:A, 0)) ) / INDEX(Config!C:C, MATCH($A46, Config!A:A, 0)), "")} -> 0.375 | H46: {=MAX( INDEX(Pack_Master!H:H, MATCH($D46, Pack_Master!A:A, 0)), IFERROR(G46, 0) )} -> 0.5 | I46: =IFERROR(__xludf.DUMMYFUNCTION("IFERROR( INDEX( FILTER(Shipping_Rate_Card!B:F, Shipping_Rate_Card!A:A=$A46), MATCH($H46, FILTER(Shipping_Rate_Card!B:B, Shipping_Rate_Card!A:A=$A46), 1), IF( INDEX(Config!B:B, MATCH($A46, Config!A:A, 0))=""Local"", 2, IF( INDEX(Config!B:B, "&"MATCH($A46, Config!A:A, 0))=""Regional"", 3, 4 ) ) ), """") "),75.0) -> 75 | J46: =IFERROR(__xludf.DUMMYFUNCTION("IFERROR( ( E46 * INDEX(FILTER(Pricing_Rules!E:E, Pricing_Rules!A:A=A46, Pricing_Rules!B:B=B46, Pricing_Rules!C:C<=E46, Pricing_Rules!D:D>=E46), 1) + INDEX(FILTER(Pricing_Rules!F:F, Pricing_Rules!A:A=A46, Pricing_Rules!B:B=B46, Pricing_Rules!C:C<=E46, "&"Pricing_Rules!D:D>=E46), 1) ) * (1 + IFERROR( INDEX(Config!D:D, MATCH(A46, Config!A:A, 0)), 0 )), """") "),15.34) -> 15.34 | K46: =IFERROR(E46 - F46 - I46 - J46, "") -> 99.66 | L46: =IFERROR(K46 / E46, "") -> 0.33331104
A47: Flipkart | B47: {=IF(D47="","", INDEX(Product_Master!A:A, MATCH( INDEX(Pack_Master!B:B, MATCH(D47, Pack_Master!A:A, 0)), Product_Master!B:B, 0 ) ))} -> Apparel_Caps_Beanies | C47: BEANIE-WOOL-OFFWHITE | D47: BEANIE-WOOL-OFFWHITE | E47: 299 | F47: {=IFERROR( VALUE( INDEX(Product_Master!$I:$I, MATCH( INDEX(Pack_Master!$B:$B, MATCH($D47, Pack_Master!$A:$A, 0)), Product_Master!$B:$B, 0) )) * VALUE( INDEX(Pack_Master!$C:$C, MATCH($D47, Pack_Master!$A:$A, 0)) ) + VALUE( INDEX(Pack_Master!$D:$D, MATCH($D47, Pack_Master!$A:$A, 0)) ), "")} -> 109 | G47: {=IFERROR( ( INDEX(Pack_Master!E:E, MATCH($D47, Pack_Master!A:A, 0)) * INDEX(Pack_Master!F:F, MATCH($D47, Pack_Master!A:A, 0)) * INDEX(Pack_Master!G:G, MATCH($D47, Pack_Master!A:A, 0)) ) / INDEX(Config!C:C, MATCH($A47, Config!A:A, 0)), "")} -> 0.375 | H47: {=MAX( INDEX(Pack_Master!H:H, MATCH($D47, Pack_Master!A:A, 0)), IFERROR(G47, 0) )} -> 0.5 | I47: =IFERROR(__xludf.DUMMYFUNCTION("IFERROR( INDEX( FILTER(Shipping_Rate_Card!B:F, Shipping_Rate_Card!A:A=$A47), MATCH($H47, FILTER(Shipping_Rate_Card!B:B, Shipping_Rate_Card!A:A=$A47), 1), IF( INDEX(Config!B:B, MATCH($A47, Config!A:A, 0))=""Local"", 2, IF( INDEX(Config!B:B, "&"MATCH($A47, Config!A:A, 0))=""Regional"", 3, 4 ) ) ), """") "),75.0) -> 75 | J47: =IFERROR(__xludf.DUMMYFUNCTION("IFERROR( ( E47 * INDEX(FILTER(Pricing_Rules!E:E, Pricing_Rules!A:A=A47, Pricing_Rules!B:B=B47, Pricing_Rules!C:C<=E47, Pricing_Rules!D:D>=E47), 1) + INDEX(FILTER(Pricing_Rules!F:F, Pricing_Rules!A:A=A47, Pricing_Rules!B:B=B47, Pricing_Rules!C:C<=E47, "&"Pricing_Rules!D:D>=E47), 1) ) * (1 + IFERROR( INDEX(Config!D:D, MATCH(A47, Config!A:A, 0)), 0 )), """") "),15.34) -> 15.34 | K47: =IFERROR(E47 - F47 - I47 - J47, "") -> 99.66 | L47: =IFERROR(K47 / E47, "") -> 0.33331104
A48: Flipkart | B48: {=IF(D48="","", INDEX(Product_Master!A:A, MATCH( INDEX(Pack_Master!B:B, MATCH(D48, Pack_Master!A:A, 0)), Product_Master!B:B, 0 ) ))} -> Apparel_Caps_Beanies | C48: CAP-BASEBALL-NY-CHARCOALWHITE | D48: CAP-BASEBALL-NY-CHARCOALWHITE-PK1 | E48: 349 | F48: {=IFERROR( VALUE( INDEX(Product_Master!$I:$I, MATCH( INDEX(Pack_Master!$B:$B, MATCH($D48, Pack_Master!$A:$A, 0)), Product_Master!$B:$B, 0) )) * VALUE( INDEX(Pack_Master!$C:$C, MATCH($D48, Pack_Master!$A:$A, 0)) ) + VALUE( INDEX(Pack_Master!$D:$D, MATCH($D48, Pack_Master!$A:$A, 0)) ), "")} -> 106 | G48: {=IFERROR( ( INDEX(Pack_Master!E:E, MATCH($D48, Pack_Master!A:A, 0)) * INDEX(Pack_Master!F:F, MATCH($D48, Pack_Master!A:A, 0)) * INDEX(Pack_Master!G:G, MATCH($D48, Pack_Master!A:A, 0)) ) / INDEX(Config!C:C, MATCH($A48, Config!A:A, 0)), "")} -> 0.375 | H48: {=MAX( INDEX(Pack_Master!H:H, MATCH($D48, Pack_Master!A:A, 0)), IFERROR(G48, 0) )} -> 0.5 | I48: =IFERROR(__xludf.DUMMYFUNCTION("IFERROR( INDEX( FILTER(Shipping_Rate_Card!B:F, Shipping_Rate_Card!A:A=$A48), MATCH($H48, FILTER(Shipping_Rate_Card!B:B, Shipping_Rate_Card!A:A=$A48), 1), IF( INDEX(Config!B:B, MATCH($A48, Config!A:A, 0))=""Local"", 2, IF( INDEX(Config!B:B, "&"MATCH($A48, Config!A:A, 0))=""Regional"", 3, 4 ) ) ), """") "),75.0) -> 75 | J48: =IFERROR(__xludf.DUMMYFUNCTION("IFERROR( ( E48 * INDEX(FILTER(Pricing_Rules!E:E, Pricing_Rules!A:A=A48, Pricing_Rules!B:B=B48, Pricing_Rules!C:C<=E48, Pricing_Rules!D:D>=E48), 1) + INDEX(FILTER(Pricing_Rules!F:F, Pricing_Rules!A:A=A48, Pricing_Rules!B:B=B48, Pricing_Rules!C:C<=E48, "&"Pricing_Rules!D:D>=E48), 1) ) * (1 + IFERROR( INDEX(Config!D:D, MATCH(A48, Config!A:A, 0)), 0 )), """") "),72.4166) -> 72.4166 | K48: =IFERROR(E48 - F48 - I48 - J48, "") -> 95.5834 | L48: =IFERROR(K48 / E48, "") -> 0.27387794
A49: Flipkart | B49: {=IF(D49="","", INDEX(Product_Master!A:A, MATCH( INDEX(Pack_Master!B:B, MATCH(D49, Pack_Master!A:A, 0)), Product_Master!B:B, 0 ) ))} -> Kitchen_Containers | C49: CONTAINER-DELUXE333-PO12 | D49: CONTAINER-DELUXE333-PK12 | E49: 999 | F49: {=IFERROR( VALUE( INDEX(Product_Master!$I:$I, MATCH( INDEX(Pack_Master!$B:$B, MATCH($D49, Pack_Master!$A:$A, 0)), Product_Master!$B:$B, 0) )) * VALUE( INDEX(Pack_Master!$C:$C, MATCH($D49, Pack_Master!$A:$A, 0)) ) + VALUE( INDEX(Pack_Master!$D:$D, MATCH($D49, Pack_Master!$A:$A, 0)) ), "")} -> 361 | G49: {=IFERROR( ( INDEX(Pack_Master!E:E, MATCH($D49, Pack_Master!A:A, 0)) * INDEX(Pack_Master!F:F, MATCH($D49, Pack_Master!A:A, 0)) * INDEX(Pack_Master!G:G, MATCH($D49, Pack_Master!A:A, 0)) ) / INDEX(Config!C:C, MATCH($A49, Config!A:A, 0)), "")} -> 1.6 | H49: {=MAX( INDEX(Pack_Master!H:H, MATCH($D49, Pack_Master!A:A, 0)), IFERROR(G49, 0) )} -> 1.6 | I49: =IFERROR(__xludf.DUMMYFUNCTION("IFERROR( INDEX( FILTER(Shipping_Rate_Card!B:F, Shipping_Rate_Card!A:A=$A49), MATCH($H49, FILTER(Shipping_Rate_Card!B:B, Shipping_Rate_Card!A:A=$A49), 1), IF( INDEX(Config!B:B, MATCH($A49, Config!A:A, 0))=""Local"", 2, IF( INDEX(Config!B:B, "&"MATCH($A49, Config!A:A, 0))=""Regional"", 3, 4 ) ) ), """") "),138.0) -> 138 | J49: =IFERROR(__xludf.DUMMYFUNCTION("IFERROR( ( E49 * INDEX(FILTER(Pricing_Rules!E:E, Pricing_Rules!A:A=A49, Pricing_Rules!B:B=B49, Pricing_Rules!C:C<=E49, Pricing_Rules!D:D>=E49), 1) + INDEX(FILTER(Pricing_Rules!F:F, Pricing_Rules!A:A=A49, Pricing_Rules!B:B=B49, Pricing_Rules!C:C<=E49, "&"Pricing_Rules!D:D>=E49), 1) ) * (1 + IFERROR( INDEX(Config!D:D, MATCH(A49, Config!A:A, 0)), 0 )), """") "),179.21839999999997) -> 179.2184 | K49: =IFERROR(E49 - F49 - I49 - J49, "") -> 320.7816 | L49: =IFERROR(K49 / E49, "") -> 0.3211027
A50: Flipkart | B50: {=IF(D50="","", INDEX(Product_Master!A:A, MATCH( INDEX(Pack_Master!B:B, MATCH(D50, Pack_Master!A:A, 0)), Product_Master!B:B, 0 ) ))} -> Kitchen_Containers | C50: CONTAINER-DELUXE333-PO12 | D50: CONTAINER-DELUXE333-PK12 | E50: 999 | F50: {=IFERROR( VALUE( INDEX(Product_Master!$I:$I, MATCH( INDEX(Pack_Master!$B:$B, MATCH($D50, Pack_Master!$A:$A, 0)), Product_Master!$B:$B, 0) )) * VALUE( INDEX(Pack_Master!$C:$C, MATCH($D50, Pack_Master!$A:$A, 0)) ) + VALUE( INDEX(Pack_Master!$D:$D, MATCH($D50, Pack_Master!$A:$A, 0)) ), "")} -> 361 | G50: {=IFERROR( ( INDEX(Pack_Master!E:E, MATCH($D50, Pack_Master!A:A, 0)) * INDEX(Pack_Master!F:F, MATCH($D50, Pack_Master!A:A, 0)) * INDEX(Pack_Master!G:G, MATCH($D50, Pack_Master!A:A, 0)) ) / INDEX(Config!C:C, MATCH($A50, Config!A:A, 0)), "")} -> 1.6 | H50: {=MAX( INDEX(Pack_Master!H:H, MATCH($D50, Pack_Master!A:A, 0)), IFERROR(G50, 0) )} -> 1.6 | I50: =IFERROR(__xludf.DUMMYFUNCTION("IFERROR( INDEX( FILTER(Shipping_Rate_Card!B:F, Shipping_Rate_Card!A:A=$A50), MATCH($H50, FILTER(Shipping_Rate_Card!B:B, Shipping_Rate_Card!A:A=$A50), 1), IF( INDEX(Config!B:B, MATCH($A50, Config!A:A, 0))=""Local"", 2, IF( INDEX(Config!B:B, "&"MATCH($A50, Config!A:A, 0))=""Regional"", 3, 4 ) ) ), """") "),138.0) -> 138 | J50: =IFERROR(__xludf.DUMMYFUNCTION("IFERROR( ( E50 * INDEX(FILTER(Pricing_Rules!E:E, Pricing_Rules!A:A=A50, Pricing_Rules!B:B=B50, Pricing_Rules!C:C<=E50, Pricing_Rules!D:D>=E50), 1) + INDEX(FILTER(Pricing_Rules!F:F, Pricing_Rules!A:A=A50, Pricing_Rules!B:B=B50, Pricing_Rules!C:C<=E50, "&"Pricing_Rules!D:D>=E50), 1) ) * (1 + IFERROR( INDEX(Config!D:D, MATCH(A50, Config!A:A, 0)), 0 )), """") "),179.21839999999997) -> 179.2184 | K50: =IFERROR(E50 - F50 - I50 - J50, "") -> 320.7816 | L50: =IFERROR(K50 / E50, "") -> 0.3211027
A51: Flipkart | B51: {=IF(D51="","", INDEX(Product_Master!A:A, MATCH( INDEX(Pack_Master!B:B, MATCH(D51, Pack_Master!A:A, 0)), Product_Master!B:B, 0 ) ))} -> Kitchen_Containers | C51: CONTAINER-DELUXE333-PO2 | D51: CONTAINER-DELUXE333-PK2 | E51: 999 | F51: {=IFERROR( VALUE( INDEX(Product_Master!$I:$I, MATCH( INDEX(Pack_Master!$B:$B, MATCH($D51, Pack_Master!$A:$A, 0)), Product_Master!$B:$B, 0) )) * VALUE( INDEX(Pack_Master!$C:$C, MATCH($D51, Pack_Master!$A:$A, 0)) ) + VALUE( INDEX(Pack_Master!$D:$D, MATCH($D51, Pack_Master!$A:$A, 0)) ), "")} -> 81 | G51: {=IFERROR( ( INDEX(Pack_Master!E:E, MATCH($D51, Pack_Master!A:A, 0)) * INDEX(Pack_Master!F:F, MATCH($D51, Pack_Master!A:A, 0)) * INDEX(Pack_Master!G:G, MATCH($D51, Pack_Master!A:A, 0)) ) / INDEX(Config!C:C, MATCH($A51, Config!A:A, 0)), "")} -> 1.6 | H51: {=MAX( INDEX(Pack_Master!H:H, MATCH($D51, Pack_Master!A:A, 0)), IFERROR(G51, 0) )} -> 1.6 | I51: =IFERROR(__xludf.DUMMYFUNCTION("IFERROR( INDEX( FILTER(Shipping_Rate_Card!B:F, Shipping_Rate_Card!A:A=$A51), MATCH($H51, FILTER(Shipping_Rate_Card!B:B, Shipping_Rate_Card!A:A=$A51), 1), IF( INDEX(Config!B:B, MATCH($A51, Config!A:A, 0))=""Local"", 2, IF( INDEX(Config!B:B, "&"MATCH($A51, Config!A:A, 0))=""Regional"", 3, 4 ) ) ), """") "),138.0) -> 138 | J51: =IFERROR(__xludf.DUMMYFUNCTION("IFERROR( ( E51 * INDEX(FILTER(Pricing_Rules!E:E, Pricing_Rules!A:A=A51, Pricing_Rules!B:B=B51, Pricing_Rules!C:C<=E51, Pricing_Rules!D:D>=E51), 1) + INDEX(FILTER(Pricing_Rules!F:F, Pricing_Rules!A:A=A51, Pricing_Rules!B:B=B51, Pricing_Rules!C:C<=E51, "&"Pricing_Rules!D:D>=E51), 1) ) * (1 + IFERROR( INDEX(Config!D:D, MATCH(A51, Config!A:A, 0)), 0 )), """") "),179.21839999999997) -> 179.2184 | K51: =IFERROR(E51 - F51 - I51 - J51, "") -> 600.7816 | L51: =IFERROR(K51 / E51, "") -> 0.60138298
A52: Flipkart | B52: {=IF(D52="","", INDEX(Product_Master!A:A, MATCH( INDEX(Pack_Master!B:B, MATCH(D52, Pack_Master!A:A, 0)), Product_Master!B:B, 0 ) ))} -> Kitchen_Containers | C52: CONTAINER-DELUXE333-PO2 | D52: CONTAINER-DELUXE333-PK2 | E52: 999 | F52: {=IFERROR( VALUE( INDEX(Product_Master!$I:$I, MATCH( INDEX(Pack_Master!$B:$B, MATCH($D52, Pack_Master!$A:$A, 0)), Product_Master!$B:$B, 0) )) * VALUE( INDEX(Pack_Master!$C:$C, MATCH($D52, Pack_Master!$A:$A, 0)) ) + VALUE( INDEX(Pack_Master!$D:$D, MATCH($D52, Pack_Master!$A:$A, 0)) ), "")} -> 81 | G52: {=IFERROR( ( INDEX(Pack_Master!E:E, MATCH($D52, Pack_Master!A:A, 0)) * INDEX(Pack_Master!F:F, MATCH($D52, Pack_Master!A:A, 0)) * INDEX(Pack_Master!G:G, MATCH($D52, Pack_Master!A:A, 0)) ) / INDEX(Config!C:C, MATCH($A52, Config!A:A, 0)), "")} -> 1.6 | H52: {=MAX( INDEX(Pack_Master!H:H, MATCH($D52, Pack_Master!A:A, 0)), IFERROR(G52, 0) )} -> 1.6 | I52: =IFERROR(__xludf.DUMMYFUNCTION("IFERROR( INDEX( FILTER(Shipping_Rate_Card!B:F, Shipping_Rate_Card!A:A=$A52), MATCH($H52, FILTER(Shipping_Rate_Card!B:B, Shipping_Rate_Card!A:A=$A52), 1), IF( INDEX(Config!B:B, MATCH($A52, Config!A:A, 0))=""Local"", 2, IF( INDEX(Config!B:B, "&"MATCH($A52, Config!A:A, 0))=""Regional"", 3, 4 ) ) ), """") "),138.0) -> 138 | J52: =IFERROR(__xludf.DUMMYFUNCTION("IFERROR( ( E52 * INDEX(FILTER(Pricing_Rules!E:E, Pricing_Rules!A:A=A52, Pricing_Rules!B:B=B52, Pricing_Rules!C:C<=E52, Pricing_Rules!D:D>=E52), 1) + INDEX(FILTER(Pricing_Rules!F:F, Pricing_Rules!A:A=A52, Pricing_Rules!B:B=B52, Pricing_Rules!C:C<=E52, "&"Pricing_Rules!D:D>=E52), 1) ) * (1 + IFERROR( INDEX(Config!D:D, MATCH(A52, Config!A:A, 0)), 0 )), """") "),179.21839999999997) -> 179.2184 | K52: =IFERROR(E52 - F52 - I52 - J52, "") -> 600.7816 | L52: =IFERROR(K52 / E52, "") -> 0.60138298
A53: Flipkart | B53: {=IF(D53="","", INDEX(Product_Master!A:A, MATCH( INDEX(Pack_Master!B:B, MATCH(D53, Pack_Master!A:A, 0)), Product_Master!B:B, 0 ) ))} -> Kitchen_Containers | C53: CONTAINER-DELUXE333-PO6 | D53: CONTAINER-DELUXE333-PK6 | E53: 999 | F53: {=IFERROR( VALUE( INDEX(Product_Master!$I:$I, MATCH( INDEX(Pack_Master!$B:$B, MATCH($D53, Pack_Master!$A:$A, 0)), Product_Master!$B:$B, 0) )) * VALUE( INDEX(Pack_Master!$C:$C, MATCH($D53, Pack_Master!$A:$A, 0)) ) + VALUE( INDEX(Pack_Master!$D:$D, MATCH($D53, Pack_Master!$A:$A, 0)) ), "")} -> 193 | G53: {=IFERROR( ( INDEX(Pack_Master!E:E, MATCH($D53, Pack_Master!A:A, 0)) * INDEX(Pack_Master!F:F, MATCH($D53, Pack_Master!A:A, 0)) * INDEX(Pack_Master!G:G, MATCH($D53, Pack_Master!A:A, 0)) ) / INDEX(Config!C:C, MATCH($A53, Config!A:A, 0)), "")} -> 1.6 | H53: {=MAX( INDEX(Pack_Master!H:H, MATCH($D53, Pack_Master!A:A, 0)), IFERROR(G53, 0) )} -> 1.6 | I53: =IFERROR(__xludf.DUMMYFUNCTION("IFERROR( INDEX( FILTER(Shipping_Rate_Card!B:F, Shipping_Rate_Card!A:A=$A53), MATCH($H53, FILTER(Shipping_Rate_Card!B:B, Shipping_Rate_Card!A:A=$A53), 1), IF( INDEX(Config!B:B, MATCH($A53, Config!A:A, 0))=""Local"", 2, IF( INDEX(Config!B:B, "&"MATCH($A53, Config!A:A, 0))=""Regional"", 3, 4 ) ) ), """") "),138.0) -> 138 | J53: =IFERROR(__xludf.DUMMYFUNCTION("IFERROR( ( E53 * INDEX(FILTER(Pricing_Rules!E:E, Pricing_Rules!A:A=A53, Pricing_Rules!B:B=B53, Pricing_Rules!C:C<=E53, Pricing_Rules!D:D>=E53), 1) + INDEX(FILTER(Pricing_Rules!F:F, Pricing_Rules!A:A=A53, Pricing_Rules!B:B=B53, Pricing_Rules!C:C<=E53, "&"Pricing_Rules!D:D>=E53), 1) ) * (1 + IFERROR( INDEX(Config!D:D, MATCH(A53, Config!A:A, 0)), 0 )), """") "),179.21839999999997) -> 179.2184 | K53: =IFERROR(E53 - F53 - I53 - J53, "") -> 488.7816 | L53: =IFERROR(K53 / E53, "") -> 0.48927087
A54: Flipkart | B54: {=IF(D54="","", INDEX(Product_Master!A:A, MATCH( INDEX(Pack_Master!B:B, MATCH(D54, Pack_Master!A:A, 0)), Product_Master!B:B, 0 ) ))} -> Kitchen_Containers | C54: CONTAINER-DELUXE333-PO6 | D54: CONTAINER-DELUXE333-PK6 | E54: 999 | F54: {=IFERROR( VALUE( INDEX(Product_Master!$I:$I, MATCH( INDEX(Pack_Master!$B:$B, MATCH($D54, Pack_Master!$A:$A, 0)), Product_Master!$B:$B, 0) )) * VALUE( INDEX(Pack_Master!$C:$C, MATCH($D54, Pack_Master!$A:$A, 0)) ) + VALUE( INDEX(Pack_Master!$D:$D, MATCH($D54, Pack_Master!$A:$A, 0)) ), "")} -> 193 | G54: {=IFERROR( ( INDEX(Pack_Master!E:E, MATCH($D54, Pack_Master!A:A, 0)) * INDEX(Pack_Master!F:F, MATCH($D54, Pack_Master!A:A, 0)) * INDEX(Pack_Master!G:G, MATCH($D54, Pack_Master!A:A, 0)) ) / INDEX(Config!C:C, MATCH($A54, Config!A:A, 0)), "")} -> 1.6 | H54: {=MAX( INDEX(Pack_Master!H:H, MATCH($D54, Pack_Master!A:A, 0)), IFERROR(G54, 0) )} -> 1.6 | I54: =IFERROR(__xludf.DUMMYFUNCTION("IFERROR( INDEX( FILTER(Shipping_Rate_Card!B:F, Shipping_Rate_Card!A:A=$A54), MATCH($H54, FILTER(Shipping_Rate_Card!B:B, Shipping_Rate_Card!A:A=$A54), 1), IF( INDEX(Config!B:B, MATCH($A54, Config!A:A, 0))=""Local"", 2, IF( INDEX(Config!B:B, "&"MATCH($A54, Config!A:A, 0))=""Regional"", 3, 4 ) ) ), """") "),138.0) -> 138 | J54: =IFERROR(__xludf.DUMMYFUNCTION("IFERROR( ( E54 * INDEX(FILTER(Pricing_Rules!E:E, Pricing_Rules!A:A=A54, Pricing_Rules!B:B=B54, Pricing_Rules!C:C<=E54, Pricing_Rules!D:D>=E54), 1) + INDEX(FILTER(Pricing_Rules!F:F, Pricing_Rules!A:A=A54, Pricing_Rules!B:B=B54, Pricing_Rules!C:C<=E54, "&"Pricing_Rules!D:D>=E54), 1) ) * (1 + IFERROR( INDEX(Config!D:D, MATCH(A54, Config!A:A, 0)), 0 )), """") "),179.21839999999997) -> 179.2184 | K54: =IFERROR(E54 - F54 - I54 - J54, "") -> 488.7816 | L54: =IFERROR(K54 / E54, "") -> 0.48927087
A55: Flipkart | B55: {=IF(D55="","", INDEX(Product_Master!A:A, MATCH( INDEX(Pack_Master!B:B, MATCH(D55, Pack_Master!A:A, 0)), Product_Master!B:B, 0 ) ))} -> Kitchen_Containers | C55: CONTAINER-DELUXE444-PO12 | D55: CONTAINER-DELUXE444-PK12 | E55: 999 | F55: {=IFERROR( VALUE( INDEX(Product_Master!$I:$I, MATCH( INDEX(Pack_Master!$B:$B, MATCH($D55, Pack_Master!$A:$A, 0)), Product_Master!$B:$B, 0) )) * VALUE( INDEX(Pack_Master!$C:$C, MATCH($D55, Pack_Master!$A:$A, 0)) ) + VALUE( INDEX(Pack_Master!$D:$D, MATCH($D55, Pack_Master!$A:$A, 0)) ), "")} -> 409 | G55: {=IFERROR( ( INDEX(Pack_Master!E:E, MATCH($D55, Pack_Master!A:A, 0)) * INDEX(Pack_Master!F:F, MATCH($D55, Pack_Master!A:A, 0)) * INDEX(Pack_Master!G:G, MATCH($D55, Pack_Master!A:A, 0)) ) / INDEX(Config!C:C, MATCH($A55, Config!A:A, 0)), "")} -> 1.6 | H55: {=MAX( INDEX(Pack_Master!H:H, MATCH($D55, Pack_Master!A:A, 0)), IFERROR(G55, 0) )} -> 1.6 | I55: =IFERROR(__xludf.DUMMYFUNCTION("IFERROR( INDEX( FILTER(Shipping_Rate_Card!B:F, Shipping_Rate_Card!A:A=$A55), MATCH($H55, FILTER(Shipping_Rate_Card!B:B, Shipping_Rate_Card!A:A=$A55), 1), IF( INDEX(Config!B:B, MATCH($A55, Config!A:A, 0))=""Local"", 2, IF( INDEX(Config!B:B, "&"MATCH($A55, Config!A:A, 0))=""Regional"", 3, 4 ) ) ), """") "),138.0) -> 138 | J55: =IFERROR(__xludf.DUMMYFUNCTION("IFERROR( ( E55 * INDEX(FILTER(Pricing_Rules!E:E, Pricing_Rules!A:A=A55, Pricing_Rules!B:B=B55, Pricing_Rules!C:C<=E55, Pricing_Rules!D:D>=E55), 1) + INDEX(FILTER(Pricing_Rules!F:F, Pricing_Rules!A:A=A55, Pricing_Rules!B:B=B55, Pricing_Rules!C:C<=E55, "&"Pricing_Rules!D:D>=E55), 1) ) * (1 + IFERROR( INDEX(Config!D:D, MATCH(A55, Config!A:A, 0)), 0 )), """") "),179.21839999999997) -> 179.2184 | K55: =IFERROR(E55 - F55 - I55 - J55, "") -> 272.7816 | L55: =IFERROR(K55 / E55, "") -> 0.27305465
A56: Flipkart | B56: {=IF(D56="","", INDEX(Product_Master!A:A, MATCH( INDEX(Pack_Master!B:B, MATCH(D56, Pack_Master!A:A, 0)), Product_Master!B:B, 0 ) ))} -> Kitchen_Containers | C56: CONTAINER-DELUXE444-PO12 | D56: CONTAINER-DELUXE444-PK12 | E56: 999 | F56: {=IFERROR( VALUE( INDEX(Product_Master!$I:$I, MATCH( INDEX(Pack_Master!$B:$B, MATCH($D56, Pack_Master!$A:$A, 0)), Product_Master!$B:$B, 0) )) * VALUE( INDEX(Pack_Master!$C:$C, MATCH($D56, Pack_Master!$A:$A, 0)) ) + VALUE( INDEX(Pack_Master!$D:$D, MATCH($D56, Pack_Master!$A:$A, 0)) ), "")} -> 409 | G56: {=IFERROR( ( INDEX(Pack_Master!E:E, MATCH($D56, Pack_Master!A:A, 0)) * INDEX(Pack_Master!F:F, MATCH($D56, Pack_Master!A:A, 0)) * INDEX(Pack_Master!G:G, MATCH($D56, Pack_Master!A:A, 0)) ) / INDEX(Config!C:C, MATCH($A56, Config!A:A, 0)), "")} -> 1.6 | H56: {=MAX( INDEX(Pack_Master!H:H, MATCH($D56, Pack_Master!A:A, 0)), IFERROR(G56, 0) )} -> 1.6 | I56: =IFERROR(__xludf.DUMMYFUNCTION("IFERROR( INDEX( FILTER(Shipping_Rate_Card!B:F, Shipping_Rate_Card!A:A=$A56), MATCH($H56, FILTER(Shipping_Rate_Card!B:B, Shipping_Rate_Card!A:A=$A56), 1), IF( INDEX(Config!B:B, MATCH($A56, Config!A:A, 0))=""Local"", 2, IF( INDEX(Config!B:B, "&"MATCH($A56, Config!A:A, 0))=""Regional"", 3, 4 ) ) ), """") "),138.0) -> 138 | J56: =IFERROR(__xludf.DUMMYFUNCTION("IFERROR( ( E56 * INDEX(FILTER(Pricing_Rules!E:E, Pricing_Rules!A:A=A56, Pricing_Rules!B:B=B56, Pricing_Rules!C:C<=E56, Pricing_Rules!D:D>=E56), 1) + INDEX(FILTER(Pricing_Rules!F:F, Pricing_Rules!A:A=A56, Pricing_Rules!B:B=B56, Pricing_Rules!C:C<=E56, "&"Pricing_Rules!D:D>=E56), 1) ) * (1 + IFERROR( INDEX(Config!D:D, MATCH(A56, Config!A:A, 0)), 0 )), """") "),179.21839999999997) -> 179.2184 | K56: =IFERROR(E56 - F56 - I56 - J56, "") -> 272.7816 | L56: =IFERROR(K56 / E56, "") -> 0.27305465
A57: Flipkart | B57: {=IF(D57="","", INDEX(Product_Master!A:A, MATCH( INDEX(Pack_Master!B:B, MATCH(D57, Pack_Master!A:A, 0)), Product_Master!B:B, 0 ) ))} -> Kitchen_Containers | C57: CONTAINER-DELUXE444-PO2 | D57: CONTAINER-DELUXE444-PK2 | E57: 999 | F57: {=IFERROR( VALUE( INDEX(Product_Master!$I:$I, MATCH( INDEX(Pack_Master!$B:$B, MATCH($D57, Pack_Master!$A:$A, 0)), Product_Master!$B:$B, 0) )) * VALUE( INDEX(Pack_Master!$C:$C, MATCH($D57, Pack_Master!$A:$A, 0)) ) + VALUE( INDEX(Pack_Master!$D:$D, MATCH($D57, Pack_Master!$A:$A, 0)) ), "")} -> 89 | G57: {=IFERROR( ( INDEX(Pack_Master!E:E, MATCH($D57, Pack_Master!A:A, 0)) * INDEX(Pack_Master!F:F, MATCH($D57, Pack_Master!A:A, 0)) * INDEX(Pack_Master!G:G, MATCH($D57, Pack_Master!A:A, 0)) ) / INDEX(Config!C:C, MATCH($A57, Config!A:A, 0)), "")} -> 1.6 | H57: {=MAX( INDEX(Pack_Master!H:H, MATCH($D57, Pack_Master!A:A, 0)), IFERROR(G57, 0) )} -> 1.6 | I57: =IFERROR(__xludf.DUMMYFUNCTION("IFERROR( INDEX( FILTER(Shipping_Rate_Card!B:F, Shipping_Rate_Card!A:A=$A57), MATCH($H57, FILTER(Shipping_Rate_Card!B:B, Shipping_Rate_Card!A:A=$A57), 1), IF( INDEX(Config!B:B, MATCH($A57, Config!A:A, 0))=""Local"", 2, IF( INDEX(Config!B:B, "&"MATCH($A57, Config!A:A, 0))=""Regional"", 3, 4 ) ) ), """") "),138.0) -> 138 | J57: =IFERROR(__xludf.DUMMYFUNCTION("IFERROR( ( E57 * INDEX(FILTER(Pricing_Rules!E:E, Pricing_Rules!A:A=A57, Pricing_Rules!B:B=B57, Pricing_Rules!C:C<=E57, Pricing_Rules!D:D>=E57), 1) + INDEX(FILTER(Pricing_Rules!F:F, Pricing_Rules!A:A=A57, Pricing_Rules!B:B=B57, Pricing_Rules!C:C<=E57, "&"Pricing_Rules!D:D>=E57), 1) ) * (1 + IFERROR( INDEX(Config!D:D, MATCH(A57, Config!A:A, 0)), 0 )), """") "),179.21839999999997) -> 179.2184 | K57: =IFERROR(E57 - F57 - I57 - J57, "") -> 592.7816 | L57: =IFERROR(K57 / E57, "") -> 0.59337498
A58: Flipkart | B58: {=IF(D58="","", INDEX(Product_Master!A:A, MATCH( INDEX(Pack_Master!B:B, MATCH(D58, Pack_Master!A:A, 0)), Product_Master!B:B, 0 ) ))} -> Kitchen_Containers | C58: CONTAINER-DELUXE444-PO2 | D58: CONTAINER-DELUXE444-PK2 | E58: 999 | F58: {=IFERROR( VALUE( INDEX(Product_Master!$I:$I, MATCH( INDEX(Pack_Master!$B:$B, MATCH($D58, Pack_Master!$A:$A, 0)), Product_Master!$B:$B, 0) )) * VALUE( INDEX(Pack_Master!$C:$C, MATCH($D58, Pack_Master!$A:$A, 0)) ) + VALUE( INDEX(Pack_Master!$D:$D, MATCH($D58, Pack_Master!$A:$A, 0)) ), "")} -> 89 | G58: {=IFERROR( ( INDEX(Pack_Master!E:E, MATCH($D58, Pack_Master!A:A, 0)) * INDEX(Pack_Master!F:F, MATCH($D58, Pack_Master!A:A, 0)) * INDEX(Pack_Master!G:G, MATCH($D58, Pack_Master!A:A, 0)) ) / INDEX(Config!C:C, MATCH($A58, Config!A:A, 0)), "")} -> 1.6 | H58: {=MAX( INDEX(Pack_Master!H:H, MATCH($D58, Pack_Master!A:A, 0)), IFERROR(G58, 0) )} -> 1.6 | I58: =IFERROR(__xludf.DUMMYFUNCTION("IFERROR( INDEX( FILTER(Shipping_Rate_Card!B:F, Shipping_Rate_Card!A:A=$A58), MATCH($H58, FILTER(Shipping_Rate_Card!B:B, Shipping_Rate_Card!A:A=$A58), 1), IF( INDEX(Config!B:B, MATCH($A58, Config!A:A, 0))=""Local"", 2, IF( INDEX(Config!B:B, "&"MATCH($A58, Config!A:A, 0))=""Regional"", 3, 4 ) ) ), """") "),138.0) -> 138 | J58: =IFERROR(__xludf.DUMMYFUNCTION("IFERROR( ( E58 * INDEX(FILTER(Pricing_Rules!E:E, Pricing_Rules!A:A=A58, Pricing_Rules!B:B=B58, Pricing_Rules!C:C<=E58, Pricing_Rules!D:D>=E58), 1) + INDEX(FILTER(Pricing_Rules!F:F, Pricing_Rules!A:A=A58, Pricing_Rules!B:B=B58, Pricing_Rules!C:C<=E58, "&"Pricing_Rules!D:D>=E58), 1) ) * (1 + IFERROR( INDEX(Config!D:D, MATCH(A58, Config!A:A, 0)), 0 )), """") "),179.21839999999997) -> 179.2184 | K58: =IFERROR(E58 - F58 - I58 - J58, "") -> 592.7816 | L58: =IFERROR(K58 / E58, "") -> 0.59337498
A59: Flipkart | B59: {=IF(D59="","", INDEX(Product_Master!A:A, MATCH( INDEX(Pack_Master!B:B, MATCH(D59, Pack_Master!A:A, 0)), Product_Master!B:B, 0 ) ))} -> Kitchen_Containers | C59: CONTAINER-DELUXE444-PO6 | D59: CONTAINER-DELUXE444-PK6 | E59: 999 | F59: {=IFERROR( VALUE( INDEX(Product_Master!$I:$I, MATCH( INDEX(Pack_Master!$B:$B, MATCH($D59, Pack_Master!$A:$A, 0)), Product_Master!$B:$B, 0) )) * VALUE( INDEX(Pack_Master!$C:$C, MATCH($D59, Pack_Master!$A:$A, 0)) ) + VALUE( INDEX(Pack_Master!$D:$D, MATCH($D59, Pack_Master!$A:$A, 0)) ), "")} -> 217 | G59: {=IFERROR( ( INDEX(Pack_Master!E:E, MATCH($D59, Pack_Master!A:A, 0)) * INDEX(Pack_Master!F:F, MATCH($D59, Pack_Master!A:A, 0)) * INDEX(Pack_Master!G:G, MATCH($D59, Pack_Master!A:A, 0)) ) / INDEX(Config!C:C, MATCH($A59, Config!A:A, 0)), "")} -> 1.6 | H59: {=MAX( INDEX(Pack_Master!H:H, MATCH($D59, Pack_Master!A:A, 0)), IFERROR(G59, 0) )} -> 1.6 | I59: =IFERROR(__xludf.DUMMYFUNCTION("IFERROR( INDEX( FILTER(Shipping_Rate_Card!B:F, Shipping_Rate_Card!A:A=$A59), MATCH($H59, FILTER(Shipping_Rate_Card!B:B, Shipping_Rate_Card!A:A=$A59), 1), IF( INDEX(Config!B:B, MATCH($A59, Config!A:A, 0))=""Local"", 2, IF( INDEX(Config!B:B, "&"MATCH($A59, Config!A:A, 0))=""Regional"", 3, 4 ) ) ), """") "),138.0) -> 138 | J59: =IFERROR(__xludf.DUMMYFUNCTION("IFERROR( ( E59 * INDEX(FILTER(Pricing_Rules!E:E, Pricing_Rules!A:A=A59, Pricing_Rules!B:B=B59, Pricing_Rules!C:C<=E59, Pricing_Rules!D:D>=E59), 1) + INDEX(FILTER(Pricing_Rules!F:F, Pricing_Rules!A:A=A59, Pricing_Rules!B:B=B59, Pricing_Rules!C:C<=E59, "&"Pricing_Rules!D:D>=E59), 1) ) * (1 + IFERROR( INDEX(Config!D:D, MATCH(A59, Config!A:A, 0)), 0 )), """") "),179.21839999999997) -> 179.2184 | K59: =IFERROR(E59 - F59 - I59 - J59, "") -> 464.7816 | L59: =IFERROR(K59 / E59, "") -> 0.46524685
A60: Flipkart | B60: {=IF(D60="","", INDEX(Product_Master!A:A, MATCH( INDEX(Pack_Master!B:B, MATCH(D60, Pack_Master!A:A, 0)), Product_Master!B:B, 0 ) ))} -> Kitchen_Containers | C60: CONTAINER-DELUXE444-PO6 | D60: CONTAINER-DELUXE444-PK6 | E60: 999 | F60: {=IFERROR( VALUE( INDEX(Product_Master!$I:$I, MATCH( INDEX(Pack_Master!$B:$B, MATCH($D60, Pack_Master!$A:$A, 0)), Product_Master!$B:$B, 0) )) * VALUE( INDEX(Pack_Master!$C:$C, MATCH($D60, Pack_Master!$A:$A, 0)) ) + VALUE( INDEX(Pack_Master!$D:$D, MATCH($D60, Pack_Master!$A:$A, 0)) ), "")} -> 217 | G60: {=IFERROR( ( INDEX(Pack_Master!E:E, MATCH($D60, Pack_Master!A:A, 0)) * INDEX(Pack_Master!F:F, MATCH($D60, Pack_Master!A:A, 0)) * INDEX(Pack_Master!G:G, MATCH($D60, Pack_Master!A:A, 0)) ) / INDEX(Config!C:C, MATCH($A60, Config!A:A, 0)), "")} -> 1.6 | H60: {=MAX( INDEX(Pack_Master!H:H, MATCH($D60, Pack_Master!A:A, 0)), IFERROR(G60, 0) )} -> 1.6 | I60: =IFERROR(__xludf.DUMMYFUNCTION("IFERROR( INDEX( FILTER(Shipping_Rate_Card!B:F, Shipping_Rate_Card!A:A=$A60), MATCH($H60, FILTER(Shipping_Rate_Card!B:B, Shipping_Rate_Card!A:A=$A60), 1), IF( INDEX(Config!B:B, MATCH($A60, Config!A:A, 0))=""Local"", 2, IF( INDEX(Config!B:B, "&"MATCH($A60, Config!A:A, 0))=""Regional"", 3, 4 ) ) ), """") "),138.0) -> 138 | J60: =IFERROR(__xludf.DUMMYFUNCTION("IFERROR( ( E60 * INDEX(FILTER(Pricing_Rules!E:E, Pricing_Rules!A:A=A60, Pricing_Rules!B:B=B60, Pricing_Rules!C:C<=E60, Pricing_Rules!D:D>=E60), 1) + INDEX(FILTER(Pricing_Rules!F:F, Pricing_Rules!A:A=A60, Pricing_Rules!B:B=B60, Pricing_Rules!C:C<=E60, "&"Pricing_Rules!D:D>=E60), 1) ) * (1 + IFERROR( INDEX(Config!D:D, MATCH(A60, Config!A:A, 0)), 0 )), """") "),179.21839999999997) -> 179.2184 | K60: =IFERROR(E60 - F60 - I60 - J60, "") -> 464.7816 | L60: =IFERROR(K60 / E60, "") -> 0.46524685
A61: Flipkart | B61: {=IF(D61="","", INDEX(Product_Master!A:A, MATCH( INDEX(Pack_Master!B:B, MATCH(D61, Pack_Master!A:A, 0)), Product_Master!B:B, 0 ) ))} -> Kitchen_Containers | C61: CONTAINER-DELUXE555-PO12 | D61: CONTAINER-DELUXE555-PK12 | E61: 999 | F61: {=IFERROR( VALUE( INDEX(Product_Master!$I:$I, MATCH( INDEX(Pack_Master!$B:$B, MATCH($D61, Pack_Master!$A:$A, 0)), Product_Master!$B:$B, 0) )) * VALUE( INDEX(Pack_Master!$C:$C, MATCH($D61, Pack_Master!$A:$A, 0)) ) + VALUE( INDEX(Pack_Master!$D:$D, MATCH($D61, Pack_Master!$A:$A, 0)) ), "")} -> 529 | G61: {=IFERROR( ( INDEX(Pack_Master!E:E, MATCH($D61, Pack_Master!A:A, 0)) * INDEX(Pack_Master!F:F, MATCH($D61, Pack_Master!A:A, 0)) * INDEX(Pack_Master!G:G, MATCH($D61, Pack_Master!A:A, 0)) ) / INDEX(Config!C:C, MATCH($A61, Config!A:A, 0)), "")} -> 1.6 | H61: {=MAX( INDEX(Pack_Master!H:H, MATCH($D61, Pack_Master!A:A, 0)), IFERROR(G61, 0) )} -> 1.6 | I61: =IFERROR(__xludf.DUMMYFUNCTION("IFERROR( INDEX( FILTER(Shipping_Rate_Card!B:F, Shipping_Rate_Card!A:A=$A61), MATCH($H61, FILTER(Shipping_Rate_Card!B:B, Shipping_Rate_Card!A:A=$A61), 1), IF( INDEX(Config!B:B, MATCH($A61, Config!A:A, 0))=""Local"", 2, IF( INDEX(Config!B:B, "&"MATCH($A61, Config!A:A, 0))=""Regional"", 3, 4 ) ) ), """") "),138.0) -> 138 | J61: =IFERROR(__xludf.DUMMYFUNCTION("IFERROR( ( E61 * INDEX(FILTER(Pricing_Rules!E:E, Pricing_Rules!A:A=A61, Pricing_Rules!B:B=B61, Pricing_Rules!C:C<=E61, Pricing_Rules!D:D>=E61), 1) + INDEX(FILTER(Pricing_Rules!F:F, Pricing_Rules!A:A=A61, Pricing_Rules!B:B=B61, Pricing_Rules!C:C<=E61, "&"Pricing_Rules!D:D>=E61), 1) ) * (1 + IFERROR( INDEX(Config!D:D, MATCH(A61, Config!A:A, 0)), 0 )), """") "),179.21839999999997) -> 179.2184 | K61: =IFERROR(E61 - F61 - I61 - J61, "") -> 152.7816 | L61: =IFERROR(K61 / E61, "") -> 0.15293453
A62: Flipkart | B62: {=IF(D62="","", INDEX(Product_Master!A:A, MATCH( INDEX(Pack_Master!B:B, MATCH(D62, Pack_Master!A:A, 0)), Product_Master!B:B, 0 ) ))} -> Kitchen_Containers | C62: CONTAINER-DELUXE555-PO12 | D62: CONTAINER-DELUXE555-PK12 | E62: 999 | F62: {=IFERROR( VALUE( INDEX(Product_Master!$I:$I, MATCH( INDEX(Pack_Master!$B:$B, MATCH($D62, Pack_Master!$A:$A, 0)), Product_Master!$B:$B, 0) )) * VALUE( INDEX(Pack_Master!$C:$C, MATCH($D62, Pack_Master!$A:$A, 0)) ) + VALUE( INDEX(Pack_Master!$D:$D, MATCH($D62, Pack_Master!$A:$A, 0)) ), "")} -> 529 | G62: {=IFERROR( ( INDEX(Pack_Master!E:E, MATCH($D62, Pack_Master!A:A, 0)) * INDEX(Pack_Master!F:F, MATCH($D62, Pack_Master!A:A, 0)) * INDEX(Pack_Master!G:G, MATCH($D62, Pack_Master!A:A, 0)) ) / INDEX(Config!C:C, MATCH($A62, Config!A:A, 0)), "")} -> 1.6 | H62: {=MAX( INDEX(Pack_Master!H:H, MATCH($D62, Pack_Master!A:A, 0)), IFERROR(G62, 0) )} -> 1.6 | I62: =IFERROR(__xludf.DUMMYFUNCTION("IFERROR( INDEX( FILTER(Shipping_Rate_Card!B:F, Shipping_Rate_Card!A:A=$A62), MATCH($H62, FILTER(Shipping_Rate_Card!B:B, Shipping_Rate_Card!A:A=$A62), 1), IF( INDEX(Config!B:B, MATCH($A62, Config!A:A, 0))=""Local"", 2, IF( INDEX(Config!B:B, "&"MATCH($A62, Config!A:A, 0))=""Regional"", 3, 4 ) ) ), """") "),138.0) -> 138 | J62: =IFERROR(__xludf.DUMMYFUNCTION("IFERROR( ( E62 * INDEX(FILTER(Pricing_Rules!E:E, Pricing_Rules!A:A=A62, Pricing_Rules!B:B=B62, Pricing_Rules!C:C<=E62, Pricing_Rules!D:D>=E62), 1) + INDEX(FILTER(Pricing_Rules!F:F, Pricing_Rules!A:A=A62, Pricing_Rules!B:B=B62, Pricing_Rules!C:C<=E62, "&"Pricing_Rules!D:D>=E62), 1) ) * (1 + IFERROR( INDEX(Config!D:D, MATCH(A62, Config!A:A, 0)), 0 )), """") "),179.21839999999997) -> 179.2184 | K62: =IFERROR(E62 - F62 - I62 - J62, "") -> 152.7816 | L62: =IFERROR(K62 / E62, "") -> 0.15293453
A63: Flipkart | B63: {=IF(D63="","", INDEX(Product_Master!A:A, MATCH( INDEX(Pack_Master!B:B, MATCH(D63, Pack_Master!A:A, 0)), Product_Master!B:B, 0 ) ))} -> Kitchen_Containers | C63: CONTAINER-DELUXE555-PO2 | D63: CONTAINER-DELUXE555-PK2 | E63: 999 | F63: {=IFERROR( VALUE( INDEX(Product_Master!$I:$I, MATCH( INDEX(Pack_Master!$B:$B, MATCH($D63, Pack_Master!$A:$A, 0)), Product_Master!$B:$B, 0) )) * VALUE( INDEX(Pack_Master!$C:$C, MATCH($D63, Pack_Master!$A:$A, 0)) ) + VALUE( INDEX(Pack_Master!$D:$D, MATCH($D63, Pack_Master!$A:$A, 0)) ), "")} -> 109 | G63: {=IFERROR( ( INDEX(Pack_Master!E:E, MATCH($D63, Pack_Master!A:A, 0)) * INDEX(Pack_Master!F:F, MATCH($D63, Pack_Master!A:A, 0)) * INDEX(Pack_Master!G:G, MATCH($D63, Pack_Master!A:A, 0)) ) / INDEX(Config!C:C, MATCH($A63, Config!A:A, 0)), "")} -> 1.6 | H63: {=MAX( INDEX(Pack_Master!H:H, MATCH($D63, Pack_Master!A:A, 0)), IFERROR(G63, 0) )} -> 1.6 | I63: =IFERROR(__xludf.DUMMYFUNCTION("IFERROR( INDEX( FILTER(Shipping_Rate_Card!B:F, Shipping_Rate_Card!A:A=$A63), MATCH($H63, FILTER(Shipping_Rate_Card!B:B, Shipping_Rate_Card!A:A=$A63), 1), IF( INDEX(Config!B:B, MATCH($A63, Config!A:A, 0))=""Local"", 2, IF( INDEX(Config!B:B, "&"MATCH($A63, Config!A:A, 0))=""Regional"", 3, 4 ) ) ), """") "),138.0) -> 138 | J63: =IFERROR(__xludf.DUMMYFUNCTION("IFERROR( ( E63 * INDEX(FILTER(Pricing_Rules!E:E, Pricing_Rules!A:A=A63, Pricing_Rules!B:B=B63, Pricing_Rules!C:C<=E63, Pricing_Rules!D:D>=E63), 1) + INDEX(FILTER(Pricing_Rules!F:F, Pricing_Rules!A:A=A63, Pricing_Rules!B:B=B63, Pricing_Rules!C:C<=E63, "&"Pricing_Rules!D:D>=E63), 1) ) * (1 + IFERROR( INDEX(Config!D:D, MATCH(A63, Config!A:A, 0)), 0 )), """") "),179.21839999999997) -> 179.2184 | K63: =IFERROR(E63 - F63 - I63 - J63, "") -> 572.7816 | L63: =IFERROR(K63 / E63, "") -> 0.57335495
A64: Flipkart | B64: {=IF(D64="","", INDEX(Product_Master!A:A, MATCH( INDEX(Pack_Master!B:B, MATCH(D64, Pack_Master!A:A, 0)), Product_Master!B:B, 0 ) ))} -> Kitchen_Containers | C64: CONTAINER-DELUXE555-PO2 | D64: CONTAINER-DELUXE555-PK2 | E64: 999 | F64: {=IFERROR( VALUE( INDEX(Product_Master!$I:$I, MATCH( INDEX(Pack_Master!$B:$B, MATCH($D64, Pack_Master!$A:$A, 0)), Product_Master!$B:$B, 0) )) * VALUE( INDEX(Pack_Master!$C:$C, MATCH($D64, Pack_Master!$A:$A, 0)) ) + VALUE( INDEX(Pack_Master!$D:$D, MATCH($D64, Pack_Master!$A:$A, 0)) ), "")} -> 109 | G64: {=IFERROR( ( INDEX(Pack_Master!E:E, MATCH($D64, Pack_Master!A:A, 0)) * INDEX(Pack_Master!F:F, MATCH($D64, Pack_Master!A:A, 0)) * INDEX(Pack_Master!G:G, MATCH($D64, Pack_Master!A:A, 0)) ) / INDEX(Config!C:C, MATCH($A64, Config!A:A, 0)), "")} -> 1.6 | H64: {=MAX( INDEX(Pack_Master!H:H, MATCH($D64, Pack_Master!A:A, 0)), IFERROR(G64, 0) )} -> 1.6 | I64: =IFERROR(__xludf.DUMMYFUNCTION("IFERROR( INDEX( FILTER(Shipping_Rate_Card!B:F, Shipping_Rate_Card!A:A=$A64), MATCH($H64, FILTER(Shipping_Rate_Card!B:B, Shipping_Rate_Card!A:A=$A64), 1), IF( INDEX(Config!B:B, MATCH($A64, Config!A:A, 0))=""Local"", 2, IF( INDEX(Config!B:B, "&"MATCH($A64, Config!A:A, 0))=""Regional"", 3, 4 ) ) ), """") "),138.0) -> 138 | J64: =IFERROR(__xludf.DUMMYFUNCTION("IFERROR( ( E64 * INDEX(FILTER(Pricing_Rules!E:E, Pricing_Rules!A:A=A64, Pricing_Rules!B:B=B64, Pricing_Rules!C:C<=E64, Pricing_Rules!D:D>=E64), 1) + INDEX(FILTER(Pricing_Rules!F:F, Pricing_Rules!A:A=A64, Pricing_Rules!B:B=B64, Pricing_Rules!C:C<=E64, "&"Pricing_Rules!D:D>=E64), 1) ) * (1 + IFERROR( INDEX(Config!D:D, MATCH(A64, Config!A:A, 0)), 0 )), """") "),179.21839999999997) -> 179.2184 | K64: =IFERROR(E64 - F64 - I64 - J64, "") -> 572.7816 | L64: =IFERROR(K64 / E64, "") -> 0.57335495
A65: Flipkart | B65: {=IF(D65="","", INDEX(Product_Master!A:A, MATCH( INDEX(Pack_Master!B:B, MATCH(D65, Pack_Master!A:A, 0)), Product_Master!B:B, 0 ) ))} -> Kitchen_Containers | C65: CONTAINER-DELUXE555-PO6 | D65: CONTAINER-DELUXE555-PK6 | E65: 999 | F65: {=IFERROR( VALUE( INDEX(Product_Master!$I:$I, MATCH( INDEX(Pack_Master!$B:$B, MATCH($D65, Pack_Master!$A:$A, 0)), Product_Master!$B:$B, 0) )) * VALUE( INDEX(Pack_Master!$C:$C, MATCH($D65, Pack_Master!$A:$A, 0)) ) + VALUE( INDEX(Pack_Master!$D:$D, MATCH($D65, Pack_Master!$A:$A, 0)) ), "")} -> 277 | G65: {=IFERROR( ( INDEX(Pack_Master!E:E, MATCH($D65, Pack_Master!A:A, 0)) * INDEX(Pack_Master!F:F, MATCH($D65, Pack_Master!A:A, 0)) * INDEX(Pack_Master!G:G, MATCH($D65, Pack_Master!A:A, 0)) ) / INDEX(Config!C:C, MATCH($A65, Config!A:A, 0)), "")} -> 1.6 | H65: {=MAX( INDEX(Pack_Master!H:H, MATCH($D65, Pack_Master!A:A, 0)), IFERROR(G65, 0) )} -> 1.6 | I65: =IFERROR(__xludf.DUMMYFUNCTION("IFERROR( INDEX( FILTER(Shipping_Rate_Card!B:F, Shipping_Rate_Card!A:A=$A65), MATCH($H65, FILTER(Shipping_Rate_Card!B:B, Shipping_Rate_Card!A:A=$A65), 1), IF( INDEX(Config!B:B, MATCH($A65, Config!A:A, 0))=""Local"", 2, IF( INDEX(Config!B:B, "&"MATCH($A65, Config!A:A, 0))=""Regional"", 3, 4 ) ) ), """") "),138.0) -> 138 | J65: =IFERROR(__xludf.DUMMYFUNCTION("IFERROR( ( E65 * INDEX(FILTER(Pricing_Rules!E:E, Pricing_Rules!A:A=A65, Pricing_Rules!B:B=B65, Pricing_Rules!C:C<=E65, Pricing_Rules!D:D>=E65), 1) + INDEX(FILTER(Pricing_Rules!F:F, Pricing_Rules!A:A=A65, Pricing_Rules!B:B=B65, Pricing_Rules!C:C<=E65, "&"Pricing_Rules!D:D>=E65), 1) ) * (1 + IFERROR( INDEX(Config!D:D, MATCH(A65, Config!A:A, 0)), 0 )), """") "),179.21839999999997) -> 179.2184 | K65: =IFERROR(E65 - F65 - I65 - J65, "") -> 404.7816 | L65: =IFERROR(K65 / E65, "") -> 0.40518679
A66: Flipkart | B66: {=IF(D66="","", INDEX(Product_Master!A:A, MATCH( INDEX(Pack_Master!B:B, MATCH(D66, Pack_Master!A:A, 0)), Product_Master!B:B, 0 ) ))} -> Kitchen_Containers | C66: CONTAINER-DELUXE555-PO6 | D66: CONTAINER-DELUXE555-PK6 | E66: 999 | F66: {=IFERROR( VALUE( INDEX(Product_Master!$I:$I, MATCH( INDEX(Pack_Master!$B:$B, MATCH($D66, Pack_Master!$A:$A, 0)), Product_Master!$B:$B, 0) )) * VALUE( INDEX(Pack_Master!$C:$C, MATCH($D66, Pack_Master!$A:$A, 0)) ) + VALUE( INDEX(Pack_Master!$D:$D, MATCH($D66, Pack_Master!$A:$A, 0)) ), "")} -> 277 | G66: {=IFERROR( ( INDEX(Pack_Master!E:E, MATCH($D66, Pack_Master!A:A, 0)) * INDEX(Pack_Master!F:F, MATCH($D66, Pack_Master!A:A, 0)) * INDEX(Pack_Master!G:G, MATCH($D66, Pack_Master!A:A, 0)) ) / INDEX(Config!C:C, MATCH($A66, Config!A:A, 0)), "")} -> 1.6 | H66: {=MAX( INDEX(Pack_Master!H:H, MATCH($D66, Pack_Master!A:A, 0)), IFERROR(G66, 0) )} -> 1.6 | I66: =IFERROR(__xludf.DUMMYFUNCTION("IFERROR( INDEX( FILTER(Shipping_Rate_Card!B:F, Shipping_Rate_Card!A:A=$A66), MATCH($H66, FILTER(Shipping_Rate_Card!B:B, Shipping_Rate_Card!A:A=$A66), 1), IF( INDEX(Config!B:B, MATCH($A66, Config!A:A, 0))=""Local"", 2, IF( INDEX(Config!B:B, "&"MATCH($A66, Config!A:A, 0))=""Regional"", 3, 4 ) ) ), """") "),138.0) -> 138 | J66: =IFERROR(__xludf.DUMMYFUNCTION("IFERROR( ( E66 * INDEX(FILTER(Pricing_Rules!E:E, Pricing_Rules!A:A=A66, Pricing_Rules!B:B=B66, Pricing_Rules!C:C<=E66, Pricing_Rules!D:D>=E66), 1) + INDEX(FILTER(Pricing_Rules!F:F, Pricing_Rules!A:A=A66, Pricing_Rules!B:B=B66, Pricing_Rules!C:C<=E66, "&"Pricing_Rules!D:D>=E66), 1) ) * (1 + IFERROR( INDEX(Config!D:D, MATCH(A66, Config!A:A, 0)), 0 )), """") "),179.21839999999997) -> 179.2184 | K66: =IFERROR(E66 - F66 - I66 - J66, "") -> 404.7816 | L66: =IFERROR(K66 / E66, "") -> 0.40518679
A67: Flipkart | B67: {=IF(D67="","", INDEX(Product_Master!A:A, MATCH( INDEX(Pack_Master!B:B, MATCH(D67, Pack_Master!A:A, 0)), Product_Master!B:B, 0 ) ))} -> Kitchen_Containers | C67: CONTAINER-DELUXE666-PO12 | D67: CONTAINER-DELUXE666-PK12 | E67: 999 | F67: {=IFERROR( VALUE( INDEX(Product_Master!$I:$I, MATCH( INDEX(Pack_Master!$B:$B, MATCH($D67, Pack_Master!$A:$A, 0)), Product_Master!$B:$B, 0) )) * VALUE( INDEX(Pack_Master!$C:$C, MATCH($D67, Pack_Master!$A:$A, 0)) ) + VALUE( INDEX(Pack_Master!$D:$D, MATCH($D67, Pack_Master!$A:$A, 0)) ), "")} -> 697 | G67: {=IFERROR( ( INDEX(Pack_Master!E:E, MATCH($D67, Pack_Master!A:A, 0)) * INDEX(Pack_Master!F:F, MATCH($D67, Pack_Master!A:A, 0)) * INDEX(Pack_Master!G:G, MATCH($D67, Pack_Master!A:A, 0)) ) / INDEX(Config!C:C, MATCH($A67, Config!A:A, 0)), "")} -> 1.6 | H67: {=MAX( INDEX(Pack_Master!H:H, MATCH($D67, Pack_Master!A:A, 0)), IFERROR(G67, 0) )} -> 1.6 | I67: =IFERROR(__xludf.DUMMYFUNCTION("IFERROR( INDEX( FILTER(Shipping_Rate_Card!B:F, Shipping_Rate_Card!A:A=$A67), MATCH($H67, FILTER(Shipping_Rate_Card!B:B, Shipping_Rate_Card!A:A=$A67), 1), IF( INDEX(Config!B:B, MATCH($A67, Config!A:A, 0))=""Local"", 2, IF( INDEX(Config!B:B, "&"MATCH($A67, Config!A:A, 0))=""Regional"", 3, 4 ) ) ), """") "),138.0) -> 138 | J67: =IFERROR(__xludf.DUMMYFUNCTION("IFERROR( ( E67 * INDEX(FILTER(Pricing_Rules!E:E, Pricing_Rules!A:A=A67, Pricing_Rules!B:B=B67, Pricing_Rules!C:C<=E67, Pricing_Rules!D:D>=E67), 1) + INDEX(FILTER(Pricing_Rules!F:F, Pricing_Rules!A:A=A67, Pricing_Rules!B:B=B67, Pricing_Rules!C:C<=E67, "&"Pricing_Rules!D:D>=E67), 1) ) * (1 + IFERROR( INDEX(Config!D:D, MATCH(A67, Config!A:A, 0)), 0 )), """") "),179.21839999999997) -> 179.2184 | K67: =IFERROR(E67 - F67 - I67 - J67, "") -> -15.2184 | L67: =IFERROR(K67 / E67, "") -> -0.015233634
A68: Flipkart | B68: {=IF(D68="","", INDEX(Product_Master!A:A, MATCH( INDEX(Pack_Master!B:B, MATCH(D68, Pack_Master!A:A, 0)), Product_Master!B:B, 0 ) ))} -> Kitchen_Containers | C68: CONTAINER-DELUXE666-PO12 | D68: CONTAINER-DELUXE666-PK12 | E68: 999 | F68: {=IFERROR( VALUE( INDEX(Product_Master!$I:$I, MATCH( INDEX(Pack_Master!$B:$B, MATCH($D68, Pack_Master!$A:$A, 0)), Product_Master!$B:$B, 0) )) * VALUE( INDEX(Pack_Master!$C:$C, MATCH($D68, Pack_Master!$A:$A, 0)) ) + VALUE( INDEX(Pack_Master!$D:$D, MATCH($D68, Pack_Master!$A:$A, 0)) ), "")} -> 697 | G68: {=IFERROR( ( INDEX(Pack_Master!E:E, MATCH($D68, Pack_Master!A:A, 0)) * INDEX(Pack_Master!F:F, MATCH($D68, Pack_Master!A:A, 0)) * INDEX(Pack_Master!G:G, MATCH($D68, Pack_Master!A:A, 0)) ) / INDEX(Config!C:C, MATCH($A68, Config!A:A, 0)), "")} -> 1.6 | H68: {=MAX( INDEX(Pack_Master!H:H, MATCH($D68, Pack_Master!A:A, 0)), IFERROR(G68, 0) )} -> 1.6 | I68: =IFERROR(__xludf.DUMMYFUNCTION("IFERROR( INDEX( FILTER(Shipping_Rate_Card!B:F, Shipping_Rate_Card!A:A=$A68), MATCH($H68, FILTER(Shipping_Rate_Card!B:B, Shipping_Rate_Card!A:A=$A68), 1), IF( INDEX(Config!B:B, MATCH($A68, Config!A:A, 0))=""Local"", 2, IF( INDEX(Config!B:B, "&"MATCH($A68, Config!A:A, 0))=""Regional"", 3, 4 ) ) ), """") "),138.0) -> 138 | J68: =IFERROR(__xludf.DUMMYFUNCTION("IFERROR( ( E68 * INDEX(FILTER(Pricing_Rules!E:E, Pricing_Rules!A:A=A68, Pricing_Rules!B:B=B68, Pricing_Rules!C:C<=E68, Pricing_Rules!D:D>=E68), 1) + INDEX(FILTER(Pricing_Rules!F:F, Pricing_Rules!A:A=A68, Pricing_Rules!B:B=B68, Pricing_Rules!C:C<=E68, "&"Pricing_Rules!D:D>=E68), 1) ) * (1 + IFERROR( INDEX(Config!D:D, MATCH(A68, Config!A:A, 0)), 0 )), """") "),179.21839999999997) -> 179.2184 | K68: =IFERROR(E68 - F68 - I68 - J68, "") -> -15.2184 | L68: =IFERROR(K68 / E68, "") -> -0.015233634
A69: Flipkart | B69: {=IF(D69="","", INDEX(Product_Master!A:A, MATCH( INDEX(Pack_Master!B:B, MATCH(D69, Pack_Master!A:A, 0)), Product_Master!B:B, 0 ) ))} -> Kitchen_Containers | C69: CONTAINER-DELUXE666-PO2 | D69: CONTAINER-DELUXE666-PK2 | E69: 999 | F69: {=IFERROR( VALUE( INDEX(Product_Master!$I:$I, MATCH( INDEX(Pack_Master!$B:$B, MATCH($D69, Pack_Master!$A:$A, 0)), Product_Master!$B:$B, 0) )) * VALUE( INDEX(Pack_Master!$C:$C, MATCH($D69, Pack_Master!$A:$A, 0)) ) + VALUE( INDEX(Pack_Master!$D:$D, MATCH($D69, Pack_Master!$A:$A, 0)) ), "")} -> 137 | G69: {=IFERROR( ( INDEX(Pack_Master!E:E, MATCH($D69, Pack_Master!A:A, 0)) * INDEX(Pack_Master!F:F, MATCH($D69, Pack_Master!A:A, 0)) * INDEX(Pack_Master!G:G, MATCH($D69, Pack_Master!A:A, 0)) ) / INDEX(Config!C:C, MATCH($A69, Config!A:A, 0)), "")} -> 1.6 | H69: {=MAX( INDEX(Pack_Master!H:H, MATCH($D69, Pack_Master!A:A, 0)), IFERROR(G69, 0) )} -> 1.6 | I69: =IFERROR(__xludf.DUMMYFUNCTION("IFERROR( INDEX( FILTER(Shipping_Rate_Card!B:F, Shipping_Rate_Card!A:A=$A69), MATCH($H69, FILTER(Shipping_Rate_Card!B:B, Shipping_Rate_Card!A:A=$A69), 1), IF( INDEX(Config!B:B, MATCH($A69, Config!A:A, 0))=""Local"", 2, IF( INDEX(Config!B:B, "&"MATCH($A69, Config!A:A, 0))=""Regional"", 3, 4 ) ) ), """") "),138.0) -> 138 | J69: =IFERROR(__xludf.DUMMYFUNCTION("IFERROR( ( E69 * INDEX(FILTER(Pricing_Rules!E:E, Pricing_Rules!A:A=A69, Pricing_Rules!B:B=B69, Pricing_Rules!C:C<=E69, Pricing_Rules!D:D>=E69), 1) + INDEX(FILTER(Pricing_Rules!F:F, Pricing_Rules!A:A=A69, Pricing_Rules!B:B=B69, Pricing_Rules!C:C<=E69, "&"Pricing_Rules!D:D>=E69), 1) ) * (1 + IFERROR( INDEX(Config!D:D, MATCH(A69, Config!A:A, 0)), 0 )), """") "),179.21839999999997) -> 179.2184 | K69: =IFERROR(E69 - F69 - I69 - J69, "") -> 544.7816 | L69: =IFERROR(K69 / E69, "") -> 0.54532693
A70: Flipkart | B70: {=IF(D70="","", INDEX(Product_Master!A:A, MATCH( INDEX(Pack_Master!B:B, MATCH(D70, Pack_Master!A:A, 0)), Product_Master!B:B, 0 ) ))} -> Kitchen_Containers | C70: CONTAINER-DELUXE666-PO2 | D70: CONTAINER-DELUXE666-PK2 | E70: 999 | F70: {=IFERROR( VALUE( INDEX(Product_Master!$I:$I, MATCH( INDEX(Pack_Master!$B:$B, MATCH($D70, Pack_Master!$A:$A, 0)), Product_Master!$B:$B, 0) )) * VALUE( INDEX(Pack_Master!$C:$C, MATCH($D70, Pack_Master!$A:$A, 0)) ) + VALUE( INDEX(Pack_Master!$D:$D, MATCH($D70, Pack_Master!$A:$A, 0)) ), "")} -> 137 | G70: {=IFERROR( ( INDEX(Pack_Master!E:E, MATCH($D70, Pack_Master!A:A, 0)) * INDEX(Pack_Master!F:F, MATCH($D70, Pack_Master!A:A, 0)) * INDEX(Pack_Master!G:G, MATCH($D70, Pack_Master!A:A, 0)) ) / INDEX(Config!C:C, MATCH($A70, Config!A:A, 0)), "")} -> 1.6 | H70: {=MAX( INDEX(Pack_Master!H:H, MATCH($D70, Pack_Master!A:A, 0)), IFERROR(G70, 0) )} -> 1.6 | I70: =IFERROR(__xludf.DUMMYFUNCTION("IFERROR( INDEX( FILTER(Shipping_Rate_Card!B:F, Shipping_Rate_Card!A:A=$A70), MATCH($H70, FILTER(Shipping_Rate_Card!B:B, Shipping_Rate_Card!A:A=$A70), 1), IF( INDEX(Config!B:B, MATCH($A70, Config!A:A, 0))=""Local"", 2, IF( INDEX(Config!B:B, "&"MATCH($A70, Config!A:A, 0))=""Regional"", 3, 4 ) ) ), """") "),138.0) -> 138 | J70: =IFERROR(__xludf.DUMMYFUNCTION("IFERROR( ( E70 * INDEX(FILTER(Pricing_Rules!E:E, Pricing_Rules!A:A=A70, Pricing_Rules!B:B=B70, Pricing_Rules!C:C<=E70, Pricing_Rules!D:D>=E70), 1) + INDEX(FILTER(Pricing_Rules!F:F, Pricing_Rules!A:A=A70, Pricing_Rules!B:B=B70, Pricing_Rules!C:C<=E70, "&"Pricing_Rules!D:D>=E70), 1) ) * (1 + IFERROR( INDEX(Config!D:D, MATCH(A70, Config!A:A, 0)), 0 )), """") "),179.21839999999997) -> 179.2184 | K70: =IFERROR(E70 - F70 - I70 - J70, "") -> 544.7816 | L70: =IFERROR(K70 / E70, "") -> 0.54532693
A71: Flipkart | B71: {=IF(D71="","", INDEX(Product_Master!A:A, MATCH( INDEX(Pack_Master!B:B, MATCH(D71, Pack_Master!A:A, 0)), Product_Master!B:B, 0 ) ))} -> Kitchen_Containers | C71: CONTAINER-DELUXE666-PO6 | D71: CONTAINER-DELUXE666-PK6 | E71: 999 | F71: {=IFERROR( VALUE( INDEX(Product_Master!$I:$I, MATCH( INDEX(Pack_Master!$B:$B, MATCH($D71, Pack_Master!$A:$A, 0)), Product_Master!$B:$B, 0) )) * VALUE( INDEX(Pack_Master!$C:$C, MATCH($D71, Pack_Master!$A:$A, 0)) ) + VALUE( INDEX(Pack_Master!$D:$D, MATCH($D71, Pack_Master!$A:$A, 0)) ), "")} -> 361 | G71: {=IFERROR( ( INDEX(Pack_Master!E:E, MATCH($D71, Pack_Master!A:A, 0)) * INDEX(Pack_Master!F:F, MATCH($D71, Pack_Master!A:A, 0)) * INDEX(Pack_Master!G:G, MATCH($D71, Pack_Master!A:A, 0)) ) / INDEX(Config!C:C, MATCH($A71, Config!A:A, 0)), "")} -> 1.6 | H71: {=MAX( INDEX(Pack_Master!H:H, MATCH($D71, Pack_Master!A:A, 0)), IFERROR(G71, 0) )} -> 1.6 | I71: =IFERROR(__xludf.DUMMYFUNCTION("IFERROR( INDEX( FILTER(Shipping_Rate_Card!B:F, Shipping_Rate_Card!A:A=$A71), MATCH($H71, FILTER(Shipping_Rate_Card!B:B, Shipping_Rate_Card!A:A=$A71), 1), IF( INDEX(Config!B:B, MATCH($A71, Config!A:A, 0))=""Local"", 2, IF( INDEX(Config!B:B, "&"MATCH($A71, Config!A:A, 0))=""Regional"", 3, 4 ) ) ), """") "),138.0) -> 138 | J71: =IFERROR(__xludf.DUMMYFUNCTION("IFERROR( ( E71 * INDEX(FILTER(Pricing_Rules!E:E, Pricing_Rules!A:A=A71, Pricing_Rules!B:B=B71, Pricing_Rules!C:C<=E71, Pricing_Rules!D:D>=E71), 1) + INDEX(FILTER(Pricing_Rules!F:F, Pricing_Rules!A:A=A71, Pricing_Rules!B:B=B71, Pricing_Rules!C:C<=E71, "&"Pricing_Rules!D:D>=E71), 1) ) * (1 + IFERROR( INDEX(Config!D:D, MATCH(A71, Config!A:A, 0)), 0 )), """") "),179.21839999999997) -> 179.2184 | K71: =IFERROR(E71 - F71 - I71 - J71, "") -> 320.7816 | L71: =IFERROR(K71 / E71, "") -> 0.3211027
A72: Flipkart | B72: {=IF(D72="","", INDEX(Product_Master!A:A, MATCH( INDEX(Pack_Master!B:B, MATCH(D72, Pack_Master!A:A, 0)), Product_Master!B:B, 0 ) ))} -> Kitchen_Containers | C72: CONTAINER-DELUXE666-PO6 | D72: CONTAINER-DELUXE666-PK6 | E72: 999 | F72: {=IFERROR( VALUE( INDEX(Product_Master!$I:$I, MATCH( INDEX(Pack_Master!$B:$B, MATCH($D72, Pack_Master!$A:$A, 0)), Product_Master!$B:$B, 0) )) * VALUE( INDEX(Pack_Master!$C:$C, MATCH($D72, Pack_Master!$A:$A, 0)) ) + VALUE( INDEX(Pack_Master!$D:$D, MATCH($D72, Pack_Master!$A:$A, 0)) ), "")} -> 361 | G72: {=IFERROR( ( INDEX(Pack_Master!E:E, MATCH($D72, Pack_Master!A:A, 0)) * INDEX(Pack_Master!F:F, MATCH($D72, Pack_Master!A:A, 0)) * INDEX(Pack_Master!G:G, MATCH($D72, Pack_Master!A:A, 0)) ) / INDEX(Config!C:C, MATCH($A72, Config!A:A, 0)), "")} -> 1.6 | H72: {=MAX( INDEX(Pack_Master!H:H, MATCH($D72, Pack_Master!A:A, 0)), IFERROR(G72, 0) )} -> 1.6 | I72: =IFERROR(__xludf.DUMMYFUNCTION("IFERROR( INDEX( FILTER(Shipping_Rate_Card!B:F, Shipping_Rate_Card!A:A=$A72), MATCH($H72, FILTER(Shipping_Rate_Card!B:B, Shipping_Rate_Card!A:A=$A72), 1), IF( INDEX(Config!B:B, MATCH($A72, Config!A:A, 0))=""Local"", 2, IF( INDEX(Config!B:B, "&"MATCH($A72, Config!A:A, 0))=""Regional"", 3, 4 ) ) ), """") "),138.0) -> 138 | J72: =IFERROR(__xludf.DUMMYFUNCTION("IFERROR( ( E72 * INDEX(FILTER(Pricing_Rules!E:E, Pricing_Rules!A:A=A72, Pricing_Rules!B:B=B72, Pricing_Rules!C:C<=E72, Pricing_Rules!D:D>=E72), 1) + INDEX(FILTER(Pricing_Rules!F:F, Pricing_Rules!A:A=A72, Pricing_Rules!B:B=B72, Pricing_Rules!C:C<=E72, "&"Pricing_Rules!D:D>=E72), 1) ) * (1 + IFERROR( INDEX(Config!D:D, MATCH(A72, Config!A:A, 0)), 0 )), """") "),179.21839999999997) -> 179.2184 | K72: =IFERROR(E72 - F72 - I72 - J72, "") -> 320.7816 | L72: =IFERROR(K72 / E72, "") -> 0.3211027
A73: Flipkart | B73: {=IF(D73="","", INDEX(Product_Master!A:A, MATCH( INDEX(Pack_Master!B:B, MATCH(D73, Pack_Master!A:A, 0)), Product_Master!B:B, 0 ) ))} -> Kitchen_Containers | C73: CONTAINER-DELUXE777-PO12 | D73: CONTAINER-DELUXE777-PK12 | E73: 999 | F73: {=IFERROR( VALUE( INDEX(Product_Master!$I:$I, MATCH( INDEX(Pack_Master!$B:$B, MATCH($D73, Pack_Master!$A:$A, 0)), Product_Master!$B:$B, 0) )) * VALUE( INDEX(Pack_Master!$C:$C, MATCH($D73, Pack_Master!$A:$A, 0)) ) + VALUE( INDEX(Pack_Master!$D:$D, MATCH($D73, Pack_Master!$A:$A, 0)) ), "")} -> 949 | G73: {=IFERROR( ( INDEX(Pack_Master!E:E, MATCH($D73, Pack_Master!A:A, 0)) * INDEX(Pack_Master!F:F, MATCH($D73, Pack_Master!A:A, 0)) * INDEX(Pack_Master!G:G, MATCH($D73, Pack_Master!A:A, 0)) ) / INDEX(Config!C:C, MATCH($A73, Config!A:A, 0)), "")} -> 1.6 | H73: {=MAX( INDEX(Pack_Master!H:H, MATCH($D73, Pack_Master!A:A, 0)), IFERROR(G73, 0) )} -> 1.6 | I73: =IFERROR(__xludf.DUMMYFUNCTION("IFERROR( INDEX( FILTER(Shipping_Rate_Card!B:F, Shipping_Rate_Card!A:A=$A73), MATCH($H73, FILTER(Shipping_Rate_Card!B:B, Shipping_Rate_Card!A:A=$A73), 1), IF( INDEX(Config!B:B, MATCH($A73, Config!A:A, 0))=""Local"", 2, IF( INDEX(Config!B:B, "&"MATCH($A73, Config!A:A, 0))=""Regional"", 3, 4 ) ) ), """") "),138.0) -> 138 | J73: =IFERROR(__xludf.DUMMYFUNCTION("IFERROR( ( E73 * INDEX(FILTER(Pricing_Rules!E:E, Pricing_Rules!A:A=A73, Pricing_Rules!B:B=B73, Pricing_Rules!C:C<=E73, Pricing_Rules!D:D>=E73), 1) + INDEX(FILTER(Pricing_Rules!F:F, Pricing_Rules!A:A=A73, Pricing_Rules!B:B=B73, Pricing_Rules!C:C<=E73, "&"Pricing_Rules!D:D>=E73), 1) ) * (1 + IFERROR( INDEX(Config!D:D, MATCH(A73, Config!A:A, 0)), 0 )), """") "),179.21839999999997) -> 179.2184 | K73: =IFERROR(E73 - F73 - I73 - J73, "") -> -267.2184 | L73: =IFERROR(K73 / E73, "") -> -0.26748589
A74: Flipkart | B74: {=IF(D74="","", INDEX(Product_Master!A:A, MATCH( INDEX(Pack_Master!B:B, MATCH(D74, Pack_Master!A:A, 0)), Product_Master!B:B, 0 ) ))} -> Kitchen_Containers | C74: CONTAINER-DELUXE777-PO12 | D74: CONTAINER-DELUXE777-PK12 | E74: 999 | F74: {=IFERROR( VALUE( INDEX(Product_Master!$I:$I, MATCH( INDEX(Pack_Master!$B:$B, MATCH($D74, Pack_Master!$A:$A, 0)), Product_Master!$B:$B, 0) )) * VALUE( INDEX(Pack_Master!$C:$C, MATCH($D74, Pack_Master!$A:$A, 0)) ) + VALUE( INDEX(Pack_Master!$D:$D, MATCH($D74, Pack_Master!$A:$A, 0)) ), "")} -> 949 | G74: {=IFERROR( ( INDEX(Pack_Master!E:E, MATCH($D74, Pack_Master!A:A, 0)) * INDEX(Pack_Master!F:F, MATCH($D74, Pack_Master!A:A, 0)) * INDEX(Pack_Master!G:G, MATCH($D74, Pack_Master!A:A, 0)) ) / INDEX(Config!C:C, MATCH($A74, Config!A:A, 0)), "")} -> 1.6 | H74: {=MAX( INDEX(Pack_Master!H:H, MATCH($D74, Pack_Master!A:A, 0)), IFERROR(G74, 0) )} -> 1.6 | I74: =IFERROR(__xludf.DUMMYFUNCTION("IFERROR( INDEX( FILTER(Shipping_Rate_Card!B:F, Shipping_Rate_Card!A:A=$A74), MATCH($H74, FILTER(Shipping_Rate_Card!B:B, Shipping_Rate_Card!A:A=$A74), 1), IF( INDEX(Config!B:B, MATCH($A74, Config!A:A, 0))=""Local"", 2, IF( INDEX(Config!B:B, "&"MATCH($A74, Config!A:A, 0))=""Regional"", 3, 4 ) ) ), """") "),138.0) -> 138 | J74: =IFERROR(__xludf.DUMMYFUNCTION("IFERROR( ( E74 * INDEX(FILTER(Pricing_Rules!E:E, Pricing_Rules!A:A=A74, Pricing_Rules!B:B=B74, Pricing_Rules!C:C<=E74, Pricing_Rules!D:D>=E74), 1) + INDEX(FILTER(Pricing_Rules!F:F, Pricing_Rules!A:A=A74, Pricing_Rules!B:B=B74, Pricing_Rules!C:C<=E74, "&"Pricing_Rules!D:D>=E74), 1) ) * (1 + IFERROR( INDEX(Config!D:D, MATCH(A74, Config!A:A, 0)), 0 )), """") "),179.21839999999997) -> 179.2184 | K74: =IFERROR(E74 - F74 - I74 - J74, "") -> -267.2184 | L74: =IFERROR(K74 / E74, "") -> -0.26748589
A75: Flipkart | B75: {=IF(D75="","", INDEX(Product_Master!A:A, MATCH( INDEX(Pack_Master!B:B, MATCH(D75, Pack_Master!A:A, 0)), Product_Master!B:B, 0 ) ))} -> Kitchen_Containers | C75: CONTAINER-DELUXE777-PO2 | D75: CONTAINER-DELUXE777-PK2 | E75: 999 | F75: {=IFERROR( VALUE( INDEX(Product_Master!$I:$I, MATCH( INDEX(Pack_Master!$B:$B, MATCH($D75, Pack_Master!$A:$A, 0)), Product_Master!$B:$B, 0) )) * VALUE( INDEX(Pack_Master!$C:$C, MATCH($D75, Pack_Master!$A:$A, 0)) ) + VALUE( INDEX(Pack_Master!$D:$D, MATCH($D75, Pack_Master!$A:$A, 0)) ), "")} -> 179 | G75: {=IFERROR( ( INDEX(Pack_Master!E:E, MATCH($D75, Pack_Master!A:A, 0)) * INDEX(Pack_Master!F:F, MATCH($D75, Pack_Master!A:A, 0)) * INDEX(Pack_Master!G:G, MATCH($D75, Pack_Master!A:A, 0)) ) / INDEX(Config!C:C, MATCH($A75, Config!A:A, 0)), "")} -> 1.6 | H75: {=MAX( INDEX(Pack_Master!H:H, MATCH($D75, Pack_Master!A:A, 0)), IFERROR(G75, 0) )} -> 1.6 | I75: =IFERROR(__xludf.DUMMYFUNCTION("IFERROR( INDEX( FILTER(Shipping_Rate_Card!B:F, Shipping_Rate_Card!A:A=$A75), MATCH($H75, FILTER(Shipping_Rate_Card!B:B, Shipping_Rate_Card!A:A=$A75), 1), IF( INDEX(Config!B:B, MATCH($A75, Config!A:A, 0))=""Local"", 2, IF( INDEX(Config!B:B, "&"MATCH($A75, Config!A:A, 0))=""Regional"", 3, 4 ) ) ), """") "),138.0) -> 138 | J75: =IFERROR(__xludf.DUMMYFUNCTION("IFERROR( ( E75 * INDEX(FILTER(Pricing_Rules!E:E, Pricing_Rules!A:A=A75, Pricing_Rules!B:B=B75, Pricing_Rules!C:C<=E75, Pricing_Rules!D:D>=E75), 1) + INDEX(FILTER(Pricing_Rules!F:F, Pricing_Rules!A:A=A75, Pricing_Rules!B:B=B75, Pricing_Rules!C:C<=E75, "&"Pricing_Rules!D:D>=E75), 1) ) * (1 + IFERROR( INDEX(Config!D:D, MATCH(A75, Config!A:A, 0)), 0 )), """") "),179.21839999999997) -> 179.2184 | K75: =IFERROR(E75 - F75 - I75 - J75, "") -> 502.7816 | L75: =IFERROR(K75 / E75, "") -> 0.50328488
A76: Flipkart | B76: {=IF(D76="","", INDEX(Product_Master!A:A, MATCH( INDEX(Pack_Master!B:B, MATCH(D76, Pack_Master!A:A, 0)), Product_Master!B:B, 0 ) ))} -> Kitchen_Containers | C76: CONTAINER-DELUXE777-PO2 | D76: CONTAINER-DELUXE777-PK2 | E76: 999 | F76: {=IFERROR( VALUE( INDEX(Product_Master!$I:$I, MATCH( INDEX(Pack_Master!$B:$B, MATCH($D76, Pack_Master!$A:$A, 0)), Product_Master!$B:$B, 0) )) * VALUE( INDEX(Pack_Master!$C:$C, MATCH($D76, Pack_Master!$A:$A, 0)) ) + VALUE( INDEX(Pack_Master!$D:$D, MATCH($D76, Pack_Master!$A:$A, 0)) ), "")} -> 179 | G76: {=IFERROR( ( INDEX(Pack_Master!E:E, MATCH($D76, Pack_Master!A:A, 0)) * INDEX(Pack_Master!F:F, MATCH($D76, Pack_Master!A:A, 0)) * INDEX(Pack_Master!G:G, MATCH($D76, Pack_Master!A:A, 0)) ) / INDEX(Config!C:C, MATCH($A76, Config!A:A, 0)), "")} -> 1.6 | H76: {=MAX( INDEX(Pack_Master!H:H, MATCH($D76, Pack_Master!A:A, 0)), IFERROR(G76, 0) )} -> 1.6 | I76: =IFERROR(__xludf.DUMMYFUNCTION("IFERROR( INDEX( FILTER(Shipping_Rate_Card!B:F, Shipping_Rate_Card!A:A=$A76), MATCH($H76, FILTER(Shipping_Rate_Card!B:B, Shipping_Rate_Card!A:A=$A76), 1), IF( INDEX(Config!B:B, MATCH($A76, Config!A:A, 0))=""Local"", 2, IF( INDEX(Config!B:B, "&"MATCH($A76, Config!A:A, 0))=""Regional"", 3, 4 ) ) ), """") "),138.0) -> 138 | J76: =IFERROR(__xludf.DUMMYFUNCTION("IFERROR( ( E76 * INDEX(FILTER(Pricing_Rules!E:E, Pricing_Rules!A:A=A76, Pricing_Rules!B:B=B76, Pricing_Rules!C:C<=E76, Pricing_Rules!D:D>=E76), 1) + INDEX(FILTER(Pricing_Rules!F:F, Pricing_Rules!A:A=A76, Pricing_Rules!B:B=B76, Pricing_Rules!C:C<=E76, "&"Pricing_Rules!D:D>=E76), 1) ) * (1 + IFERROR( INDEX(Config!D:D, MATCH(A76, Config!A:A, 0)), 0 )), """") "),179.21839999999997) -> 179.2184 | K76: =IFERROR(E76 - F76 - I76 - J76, "") -> 502.7816 | L76: =IFERROR(K76 / E76, "") -> 0.50328488
A77: Flipkart | B77: {=IF(D77="","", INDEX(Product_Master!A:A, MATCH( INDEX(Pack_Master!B:B, MATCH(D77, Pack_Master!A:A, 0)), Product_Master!B:B, 0 ) ))} -> Kitchen_Containers | C77: CONTAINER-DELUXE777-PO6 | D77: CONTAINER-DELUXE777-PK6 | E77: 999 | F77: {=IFERROR( VALUE( INDEX(Product_Master!$I:$I, MATCH( INDEX(Pack_Master!$B:$B, MATCH($D77, Pack_Master!$A:$A, 0)), Product_Master!$B:$B, 0) )) * VALUE( INDEX(Pack_Master!$C:$C, MATCH($D77, Pack_Master!$A:$A, 0)) ) + VALUE( INDEX(Pack_Master!$D:$D, MATCH($D77, Pack_Master!$A:$A, 0)) ), "")} -> 487 | G77: {=IFERROR( ( INDEX(Pack_Master!E:E, MATCH($D77, Pack_Master!A:A, 0)) * INDEX(Pack_Master!F:F, MATCH($D77, Pack_Master!A:A, 0)) * INDEX(Pack_Master!G:G, MATCH($D77, Pack_Master!A:A, 0)) ) / INDEX(Config!C:C, MATCH($A77, Config!A:A, 0)), "")} -> 1.6 | H77: {=MAX( INDEX(Pack_Master!H:H, MATCH($D77, Pack_Master!A:A, 0)), IFERROR(G77, 0) )} -> 1.6 | I77: =IFERROR(__xludf.DUMMYFUNCTION("IFERROR( INDEX( FILTER(Shipping_Rate_Card!B:F, Shipping_Rate_Card!A:A=$A77), MATCH($H77, FILTER(Shipping_Rate_Card!B:B, Shipping_Rate_Card!A:A=$A77), 1), IF( INDEX(Config!B:B, MATCH($A77, Config!A:A, 0))=""Local"", 2, IF( INDEX(Config!B:B, "&"MATCH($A77, Config!A:A, 0))=""Regional"", 3, 4 ) ) ), """") "),138.0) -> 138 | J77: =IFERROR(__xludf.DUMMYFUNCTION("IFERROR( ( E77 * INDEX(FILTER(Pricing_Rules!E:E, Pricing_Rules!A:A=A77, Pricing_Rules!B:B=B77, Pricing_Rules!C:C<=E77, Pricing_Rules!D:D>=E77), 1) + INDEX(FILTER(Pricing_Rules!F:F, Pricing_Rules!A:A=A77, Pricing_Rules!B:B=B77, Pricing_Rules!C:C<=E77, "&"Pricing_Rules!D:D>=E77), 1) ) * (1 + IFERROR( INDEX(Config!D:D, MATCH(A77, Config!A:A, 0)), 0 )), """") "),179.21839999999997) -> 179.2184 | K77: =IFERROR(E77 - F77 - I77 - J77, "") -> 194.7816 | L77: =IFERROR(K77 / E77, "") -> 0.19497658
A78: Flipkart | B78: {=IF(D78="","", INDEX(Product_Master!A:A, MATCH( INDEX(Pack_Master!B:B, MATCH(D78, Pack_Master!A:A, 0)), Product_Master!B:B, 0 ) ))} -> Kitchen_Containers | C78: CONTAINER-DELUXE777-PO6 | D78: CONTAINER-DELUXE777-PK6 | E78: 999 | F78: {=IFERROR( VALUE( INDEX(Product_Master!$I:$I, MATCH( INDEX(Pack_Master!$B:$B, MATCH($D78, Pack_Master!$A:$A, 0)), Product_Master!$B:$B, 0) )) * VALUE( INDEX(Pack_Master!$C:$C, MATCH($D78, Pack_Master!$A:$A, 0)) ) + VALUE( INDEX(Pack_Master!$D:$D, MATCH($D78, Pack_Master!$A:$A, 0)) ), "")} -> 487 | G78: {=IFERROR( ( INDEX(Pack_Master!E:E, MATCH($D78, Pack_Master!A:A, 0)) * INDEX(Pack_Master!F:F, MATCH($D78, Pack_Master!A:A, 0)) * INDEX(Pack_Master!G:G, MATCH($D78, Pack_Master!A:A, 0)) ) / INDEX(Config!C:C, MATCH($A78, Config!A:A, 0)), "")} -> 1.6 | H78: {=MAX( INDEX(Pack_Master!H:H, MATCH($D78, Pack_Master!A:A, 0)), IFERROR(G78, 0) )} -> 1.6 | I78: =IFERROR(__xludf.DUMMYFUNCTION("IFERROR( INDEX( FILTER(Shipping_Rate_Card!B:F, Shipping_Rate_Card!A:A=$A78), MATCH($H78, FILTER(Shipping_Rate_Card!B:B, Shipping_Rate_Card!A:A=$A78), 1), IF( INDEX(Config!B:B, MATCH($A78, Config!A:A, 0))=""Local"", 2, IF( INDEX(Config!B:B, "&"MATCH($A78, Config!A:A, 0))=""Regional"", 3, 4 ) ) ), """") "),138.0) -> 138 | J78: =IFERROR(__xludf.DUMMYFUNCTION("IFERROR( ( E78 * INDEX(FILTER(Pricing_Rules!E:E, Pricing_Rules!A:A=A78, Pricing_Rules!B:B=B78, Pricing_Rules!C:C<=E78, Pricing_Rules!D:D>=E78), 1) + INDEX(FILTER(Pricing_Rules!F:F, Pricing_Rules!A:A=A78, Pricing_Rules!B:B=B78, Pricing_Rules!C:C<=E78, "&"Pricing_Rules!D:D>=E78), 1) ) * (1 + IFERROR( INDEX(Config!D:D, MATCH(A78, Config!A:A, 0)), 0 )), """") "),179.21839999999997) -> 179.2184 | K78: =IFERROR(E78 - F78 - I78 - J78, "") -> 194.7816 | L78: =IFERROR(K78 / E78, "") -> 0.19497658
A79: Flipkart | B79: {=IF(D79="","", INDEX(Product_Master!A:A, MATCH( INDEX(Pack_Master!B:B, MATCH(D79, Pack_Master!A:A, 0)), Product_Master!B:B, 0 ) ))} -> Kitchen_Containers | C79: CONTAINER-DELUXE888-PO12 | D79: CONTAINER-DELUXE888-PK12 | E79: 999 | F79: {=IFERROR( VALUE( INDEX(Product_Master!$I:$I, MATCH( INDEX(Pack_Master!$B:$B, MATCH($D79, Pack_Master!$A:$A, 0)), Product_Master!$B:$B, 0) )) * VALUE( INDEX(Pack_Master!$C:$C, MATCH($D79, Pack_Master!$A:$A, 0)) ) + VALUE( INDEX(Pack_Master!$D:$D, MATCH($D79, Pack_Master!$A:$A, 0)) ), "")} -> 1393 | G79: {=IFERROR( ( INDEX(Pack_Master!E:E, MATCH($D79, Pack_Master!A:A, 0)) * INDEX(Pack_Master!F:F, MATCH($D79, Pack_Master!A:A, 0)) * INDEX(Pack_Master!G:G, MATCH($D79, Pack_Master!A:A, 0)) ) / INDEX(Config!C:C, MATCH($A79, Config!A:A, 0)), "")} -> 1.6 | H79: {=MAX( INDEX(Pack_Master!H:H, MATCH($D79, Pack_Master!A:A, 0)), IFERROR(G79, 0) )} -> 1.6 | I79: =IFERROR(__xludf.DUMMYFUNCTION("IFERROR( INDEX( FILTER(Shipping_Rate_Card!B:F, Shipping_Rate_Card!A:A=$A79), MATCH($H79, FILTER(Shipping_Rate_Card!B:B, Shipping_Rate_Card!A:A=$A79), 1), IF( INDEX(Config!B:B, MATCH($A79, Config!A:A, 0))=""Local"", 2, IF( INDEX(Config!B:B, "&"MATCH($A79, Config!A:A, 0))=""Regional"", 3, 4 ) ) ), """") "),138.0) -> 138 | J79: =IFERROR(__xludf.DUMMYFUNCTION("IFERROR( ( E79 * INDEX(FILTER(Pricing_Rules!E:E, Pricing_Rules!A:A=A79, Pricing_Rules!B:B=B79, Pricing_Rules!C:C<=E79, Pricing_Rules!D:D>=E79), 1) + INDEX(FILTER(Pricing_Rules!F:F, Pricing_Rules!A:A=A79, Pricing_Rules!B:B=B79, Pricing_Rules!C:C<=E79, "&"Pricing_Rules!D:D>=E79), 1) ) * (1 + IFERROR( INDEX(Config!D:D, MATCH(A79, Config!A:A, 0)), 0 )), """") "),179.21839999999997) -> 179.2184 | K79: =IFERROR(E79 - F79 - I79 - J79, "") -> -711.2184 | L79: =IFERROR(K79 / E79, "") -> -0.71193033
A80: Flipkart | B80: {=IF(D80="","", INDEX(Product_Master!A:A, MATCH( INDEX(Pack_Master!B:B, MATCH(D80, Pack_Master!A:A, 0)), Product_Master!B:B, 0 ) ))} -> Kitchen_Containers | C80: CONTAINER-DELUXE888-PO12 | D80: CONTAINER-DELUXE888-PK12 | E80: 999 | F80: {=IFERROR( VALUE( INDEX(Product_Master!$I:$I, MATCH( INDEX(Pack_Master!$B:$B, MATCH($D80, Pack_Master!$A:$A, 0)), Product_Master!$B:$B, 0) )) * VALUE( INDEX(Pack_Master!$C:$C, MATCH($D80, Pack_Master!$A:$A, 0)) ) + VALUE( INDEX(Pack_Master!$D:$D, MATCH($D80, Pack_Master!$A:$A, 0)) ), "")} -> 1393 | G80: {=IFERROR( ( INDEX(Pack_Master!E:E, MATCH($D80, Pack_Master!A:A, 0)) * INDEX(Pack_Master!F:F, MATCH($D80, Pack_Master!A:A, 0)) * INDEX(Pack_Master!G:G, MATCH($D80, Pack_Master!A:A, 0)) ) / INDEX(Config!C:C, MATCH($A80, Config!A:A, 0)), "")} -> 1.6 | H80: {=MAX( INDEX(Pack_Master!H:H, MATCH($D80, Pack_Master!A:A, 0)), IFERROR(G80, 0) )} -> 1.6 | I80: =IFERROR(__xludf.DUMMYFUNCTION("IFERROR( INDEX( FILTER(Shipping_Rate_Card!B:F, Shipping_Rate_Card!A:A=$A80), MATCH($H80, FILTER(Shipping_Rate_Card!B:B, Shipping_Rate_Card!A:A=$A80), 1), IF( INDEX(Config!B:B, MATCH($A80, Config!A:A, 0))=""Local"", 2, IF( INDEX(Config!B:B, "&"MATCH($A80, Config!A:A, 0))=""Regional"", 3, 4 ) ) ), """") "),138.0) -> 138 | J80: =IFERROR(__xludf.DUMMYFUNCTION("IFERROR( ( E80 * INDEX(FILTER(Pricing_Rules!E:E, Pricing_Rules!A:A=A80, Pricing_Rules!B:B=B80, Pricing_Rules!C:C<=E80, Pricing_Rules!D:D>=E80), 1) + INDEX(FILTER(Pricing_Rules!F:F, Pricing_Rules!A:A=A80, Pricing_Rules!B:B=B80, Pricing_Rules!C:C<=E80, "&"Pricing_Rules!D:D>=E80), 1) ) * (1 + IFERROR( INDEX(Config!D:D, MATCH(A80, Config!A:A, 0)), 0 )), """") "),179.21839999999997) -> 179.2184 | K80: =IFERROR(E80 - F80 - I80 - J80, "") -> -711.2184 | L80: =IFERROR(K80 / E80, "") -> -0.71193033
A81: Flipkart | B81: {=IF(D81="","", INDEX(Product_Master!A:A, MATCH( INDEX(Pack_Master!B:B, MATCH(D81, Pack_Master!A:A, 0)), Product_Master!B:B, 0 ) ))} -> Kitchen_Containers | C81: CONTAINER-DELUXE888-PO2 | D81: CONTAINER-DELUXE888-PK2 | E81: 999 | F81: {=IFERROR( VALUE( INDEX(Product_Master!$I:$I, MATCH( INDEX(Pack_Master!$B:$B, MATCH($D81, Pack_Master!$A:$A, 0)), Product_Master!$B:$B, 0) )) * VALUE( INDEX(Pack_Master!$C:$C, MATCH($D81, Pack_Master!$A:$A, 0)) ) + VALUE( INDEX(Pack_Master!$D:$D, MATCH($D81, Pack_Master!$A:$A, 0)) ), "")} -> 253 | G81: {=IFERROR( ( INDEX(Pack_Master!E:E, MATCH($D81, Pack_Master!A:A, 0)) * INDEX(Pack_Master!F:F, MATCH($D81, Pack_Master!A:A, 0)) * INDEX(Pack_Master!G:G, MATCH($D81, Pack_Master!A:A, 0)) ) / INDEX(Config!C:C, MATCH($A81, Config!A:A, 0)), "")} -> 1.6 | H81: {=MAX( INDEX(Pack_Master!H:H, MATCH($D81, Pack_Master!A:A, 0)), IFERROR(G81, 0) )} -> 1.6 | I81: =IFERROR(__xludf.DUMMYFUNCTION("IFERROR( INDEX( FILTER(Shipping_Rate_Card!B:F, Shipping_Rate_Card!A:A=$A81), MATCH($H81, FILTER(Shipping_Rate_Card!B:B, Shipping_Rate_Card!A:A=$A81), 1), IF( INDEX(Config!B:B, MATCH($A81, Config!A:A, 0))=""Local"", 2, IF( INDEX(Config!B:B, "&"MATCH($A81, Config!A:A, 0))=""Regional"", 3, 4 ) ) ), """") "),138.0) -> 138 | J81: =IFERROR(__xludf.DUMMYFUNCTION("IFERROR( ( E81 * INDEX(FILTER(Pricing_Rules!E:E, Pricing_Rules!A:A=A81, Pricing_Rules!B:B=B81, Pricing_Rules!C:C<=E81, Pricing_Rules!D:D>=E81), 1) + INDEX(FILTER(Pricing_Rules!F:F, Pricing_Rules!A:A=A81, Pricing_Rules!B:B=B81, Pricing_Rules!C:C<=E81, "&"Pricing_Rules!D:D>=E81), 1) ) * (1 + IFERROR( INDEX(Config!D:D, MATCH(A81, Config!A:A, 0)), 0 )), """") "),179.21839999999997) -> 179.2184 | K81: =IFERROR(E81 - F81 - I81 - J81, "") -> 428.7816 | L81: =IFERROR(K81 / E81, "") -> 0.42921081
A82: Flipkart | B82: {=IF(D82="","", INDEX(Product_Master!A:A, MATCH( INDEX(Pack_Master!B:B, MATCH(D82, Pack_Master!A:A, 0)), Product_Master!B:B, 0 ) ))} -> Kitchen_Containers | C82: CONTAINER-DELUXE888-PO2 | D82: CONTAINER-DELUXE888-PK2 | E82: 999 | F82: {=IFERROR( VALUE( INDEX(Product_Master!$I:$I, MATCH( INDEX(Pack_Master!$B:$B, MATCH($D82, Pack_Master!$A:$A, 0)), Product_Master!$B:$B, 0) )) * VALUE( INDEX(Pack_Master!$C:$C, MATCH($D82, Pack_Master!$A:$A, 0)) ) + VALUE( INDEX(Pack_Master!$D:$D, MATCH($D82, Pack_Master!$A:$A, 0)) ), "")} -> 253 | G82: {=IFERROR( ( INDEX(Pack_Master!E:E, MATCH($D82, Pack_Master!A:A, 0)) * INDEX(Pack_Master!F:F, MATCH($D82, Pack_Master!A:A, 0)) * INDEX(Pack_Master!G:G, MATCH($D82, Pack_Master!A:A, 0)) ) / INDEX(Config!C:C, MATCH($A82, Config!A:A, 0)), "")} -> 1.6 | H82: {=MAX( INDEX(Pack_Master!H:H, MATCH($D82, Pack_Master!A:A, 0)), IFERROR(G82, 0) )} -> 1.6 | I82: =IFERROR(__xludf.DUMMYFUNCTION("IFERROR( INDEX( FILTER(Shipping_Rate_Card!B:F, Shipping_Rate_Card!A:A=$A82), MATCH($H82, FILTER(Shipping_Rate_Card!B:B, Shipping_Rate_Card!A:A=$A82), 1), IF( INDEX(Config!B:B, MATCH($A82, Config!A:A, 0))=""Local"", 2, IF( INDEX(Config!B:B, "&"MATCH($A82, Config!A:A, 0))=""Regional"", 3, 4 ) ) ), """") "),138.0) -> 138 | J82: =IFERROR(__xludf.DUMMYFUNCTION("IFERROR( ( E82 * INDEX(FILTER(Pricing_Rules!E:E, Pricing_Rules!A:A=A82, Pricing_Rules!B:B=B82, Pricing_Rules!C:C<=E82, Pricing_Rules!D:D>=E82), 1) + INDEX(FILTER(Pricing_Rules!F:F, Pricing_Rules!A:A=A82, Pricing_Rules!B:B=B82, Pricing_Rules!C:C<=E82, "&"Pricing_Rules!D:D>=E82), 1) ) * (1 + IFERROR( INDEX(Config!D:D, MATCH(A82, Config!A:A, 0)), 0 )), """") "),179.21839999999997) -> 179.2184 | K82: =IFERROR(E82 - F82 - I82 - J82, "") -> 428.7816 | L82: =IFERROR(K82 / E82, "") -> 0.42921081
A83: Flipkart | B83: {=IF(D83="","", INDEX(Product_Master!A:A, MATCH( INDEX(Pack_Master!B:B, MATCH(D83, Pack_Master!A:A, 0)), Product_Master!B:B, 0 ) ))} -> Kitchen_Containers | C83: CONTAINER-DELUXE888-PO6 | D83: CONTAINER-DELUXE888-PK6 | E83: 999 | F83: {=IFERROR( VALUE( INDEX(Product_Master!$I:$I, MATCH( INDEX(Pack_Master!$B:$B, MATCH($D83, Pack_Master!$A:$A, 0)), Product_Master!$B:$B, 0) )) * VALUE( INDEX(Pack_Master!$C:$C, MATCH($D83, Pack_Master!$A:$A, 0)) ) + VALUE( INDEX(Pack_Master!$D:$D, MATCH($D83, Pack_Master!$A:$A, 0)) ), "")} -> 709 | G83: {=IFERROR( ( INDEX(Pack_Master!E:E, MATCH($D83, Pack_Master!A:A, 0)) * INDEX(Pack_Master!F:F, MATCH($D83, Pack_Master!A:A, 0)) * INDEX(Pack_Master!G:G, MATCH($D83, Pack_Master!A:A, 0)) ) / INDEX(Config!C:C, MATCH($A83, Config!A:A, 0)), "")} -> 1.6 | H83: {=MAX( INDEX(Pack_Master!H:H, MATCH($D83, Pack_Master!A:A, 0)), IFERROR(G83, 0) )} -> 1.6 | I83: =IFERROR(__xludf.DUMMYFUNCTION("IFERROR( INDEX( FILTER(Shipping_Rate_Card!B:F, Shipping_Rate_Card!A:A=$A83), MATCH($H83, FILTER(Shipping_Rate_Card!B:B, Shipping_Rate_Card!A:A=$A83), 1), IF( INDEX(Config!B:B, MATCH($A83, Config!A:A, 0))=""Local"", 2, IF( INDEX(Config!B:B, "&"MATCH($A83, Config!A:A, 0))=""Regional"", 3, 4 ) ) ), """") "),138.0) -> 138 | J83: =IFERROR(__xludf.DUMMYFUNCTION("IFERROR( ( E83 * INDEX(FILTER(Pricing_Rules!E:E, Pricing_Rules!A:A=A83, Pricing_Rules!B:B=B83, Pricing_Rules!C:C<=E83, Pricing_Rules!D:D>=E83), 1) + INDEX(FILTER(Pricing_Rules!F:F, Pricing_Rules!A:A=A83, Pricing_Rules!B:B=B83, Pricing_Rules!C:C<=E83, "&"Pricing_Rules!D:D>=E83), 1) ) * (1 + IFERROR( INDEX(Config!D:D, MATCH(A83, Config!A:A, 0)), 0 )), """") "),179.21839999999997) -> 179.2184 | K83: =IFERROR(E83 - F83 - I83 - J83, "") -> -27.2184 | L83: =IFERROR(K83 / E83, "") -> -0.027245646
A84: Flipkart | B84: {=IF(D84="","", INDEX(Product_Master!A:A, MATCH( INDEX(Pack_Master!B:B, MATCH(D84, Pack_Master!A:A, 0)), Product_Master!B:B, 0 ) ))} -> Kitchen_Containers | C84: CONTAINER-DELUXE888-PO6 | D84: CONTAINER-DELUXE888-PK6 | E84: 999 | F84: {=IFERROR( VALUE( INDEX(Product_Master!$I:$I, MATCH( INDEX(Pack_Master!$B:$B, MATCH($D84, Pack_Master!$A:$A, 0)), Product_Master!$B:$B, 0) )) * VALUE( INDEX(Pack_Master!$C:$C, MATCH($D84, Pack_Master!$A:$A, 0)) ) + VALUE( INDEX(Pack_Master!$D:$D, MATCH($D84, Pack_Master!$A:$A, 0)) ), "")} -> 709 | G84: {=IFERROR( ( INDEX(Pack_Master!E:E, MATCH($D84, Pack_Master!A:A, 0)) * INDEX(Pack_Master!F:F, MATCH($D84, Pack_Master!A:A, 0)) * INDEX(Pack_Master!G:G, MATCH($D84, Pack_Master!A:A, 0)) ) / INDEX(Config!C:C, MATCH($A84, Config!A:A, 0)), "")} -> 1.6 | H84: {=MAX( INDEX(Pack_Master!H:H, MATCH($D84, Pack_Master!A:A, 0)), IFERROR(G84, 0) )} -> 1.6 | I84: =IFERROR(__xludf.DUMMYFUNCTION("IFERROR( INDEX( FILTER(Shipping_Rate_Card!B:F, Shipping_Rate_Card!A:A=$A84), MATCH($H84, FILTER(Shipping_Rate_Card!B:B, Shipping_Rate_Card!A:A=$A84), 1), IF( INDEX(Config!B:B, MATCH($A84, Config!A:A, 0))=""Local"", 2, IF( INDEX(Config!B:B, "&"MATCH($A84, Config!A:A, 0))=""Regional"", 3, 4 ) ) ), """") "),138.0) -> 138 | J84: =IFERROR(__xludf.DUMMYFUNCTION("IFERROR( ( E84 * INDEX(FILTER(Pricing_Rules!E:E, Pricing_Rules!A:A=A84, Pricing_Rules!B:B=B84, Pricing_Rules!C:C<=E84, Pricing_Rules!D:D>=E84), 1) + INDEX(FILTER(Pricing_Rules!F:F, Pricing_Rules!A:A=A84, Pricing_Rules!B:B=B84, Pricing_Rules!C:C<=E84, "&"Pricing_Rules!D:D>=E84), 1) ) * (1 + IFERROR( INDEX(Config!D:D, MATCH(A84, Config!A:A, 0)), 0 )), """") "),179.21839999999997) -> 179.2184 | K84: =IFERROR(E84 - F84 - I84 - J84, "") -> -27.2184 | L84: =IFERROR(K84 / E84, "") -> -0.027245646
A85: Flipkart | B85: {=IF(D85="","", INDEX(Product_Master!A:A, MATCH( INDEX(Pack_Master!B:B, MATCH(D85, Pack_Master!A:A, 0)), Product_Master!B:B, 0 ) ))} -> Garden_Planters | C85: PLANTER-ROUNDORCHID-SAUCER10-01 | D85: PLANTER-ROUNDORCHID-SAUCER10-PK1 | E85: 299 | F85: {=IFERROR( VALUE( INDEX(Product_Master!$I:$I, MATCH( INDEX(Pack_Master!$B:$B, MATCH($D85, Pack_Master!$A:$A, 0)), Product_Master!$B:$B, 0) )) * VALUE( INDEX(Pack_Master!$C:$C, MATCH($D85, Pack_Master!$A:$A, 0)) ) + VALUE( INDEX(Pack_Master!$D:$D, MATCH($D85, Pack_Master!$A:$A, 0)) ), "")} -> 86.5 | G85: {=IFERROR( ( INDEX(Pack_Master!E:E, MATCH($D85, Pack_Master!A:A, 0)) * INDEX(Pack_Master!F:F, MATCH($D85, Pack_Master!A:A, 0)) * INDEX(Pack_Master!G:G, MATCH($D85, Pack_Master!A:A, 0)) ) / INDEX(Config!C:C, MATCH($A85, Config!A:A, 0)), "")} -> 2.8392 | H85: {=MAX( INDEX(Pack_Master!H:H, MATCH($D85, Pack_Master!A:A, 0)), IFERROR(G85, 0) )} -> 2.8392 | I85: =IFERROR(__xludf.DUMMYFUNCTION("IFERROR( INDEX( FILTER(Shipping_Rate_Card!B:F, Shipping_Rate_Card!A:A=$A85), MATCH($H85, FILTER(Shipping_Rate_Card!B:B, Shipping_Rate_Card!A:A=$A85), 1), IF( INDEX(Config!B:B, MATCH($A85, Config!A:A, 0))=""Local"", 2, IF( INDEX(Config!B:B, "&"MATCH($A85, Config!A:A, 0))=""Regional"", 3, 4 ) ) ), """") "),173.0) -> 173 | J85: =IFERROR(__xludf.DUMMYFUNCTION("IFERROR( ( E85 * INDEX(FILTER(Pricing_Rules!E:E, Pricing_Rules!A:A=A85, Pricing_Rules!B:B=B85, Pricing_Rules!C:C<=E85, Pricing_Rules!D:D>=E85), 1) + INDEX(FILTER(Pricing_Rules!F:F, Pricing_Rules!A:A=A85, Pricing_Rules!B:B=B85, Pricing_Rules!C:C<=E85, "&"Pricing_Rules!D:D>=E85), 1) ) * (1 + IFERROR( INDEX(Config!D:D, MATCH(A85, Config!A:A, 0)), 0 )), """") "),15.34) -> 15.34 | K85: =IFERROR(E85 - F85 - I85 - J85, "") -> 24.16 | L85: =IFERROR(K85 / E85, "") -> 0.080802676
A86: Flipkart | B86: {=IF(D86="","", INDEX(Product_Master!A:A, MATCH( INDEX(Pack_Master!B:B, MATCH(D86, Pack_Master!A:A, 0)), Product_Master!B:B, 0 ) ))} -> Garden_Planters | C86: PLANTER-ROUNDORCHID-SAUCER10-01 | D86: PLANTER-ROUNDORCHID-SAUCER10-PK1 | E86: 299 | F86: {=IFERROR( VALUE( INDEX(Product_Master!$I:$I, MATCH( INDEX(Pack_Master!$B:$B, MATCH($D86, Pack_Master!$A:$A, 0)), Product_Master!$B:$B, 0) )) * VALUE( INDEX(Pack_Master!$C:$C, MATCH($D86, Pack_Master!$A:$A, 0)) ) + VALUE( INDEX(Pack_Master!$D:$D, MATCH($D86, Pack_Master!$A:$A, 0)) ), "")} -> 86.5 | G86: {=IFERROR( ( INDEX(Pack_Master!E:E, MATCH($D86, Pack_Master!A:A, 0)) * INDEX(Pack_Master!F:F, MATCH($D86, Pack_Master!A:A, 0)) * INDEX(Pack_Master!G:G, MATCH($D86, Pack_Master!A:A, 0)) ) / INDEX(Config!C:C, MATCH($A86, Config!A:A, 0)), "")} -> 2.8392 | H86: {=MAX( INDEX(Pack_Master!H:H, MATCH($D86, Pack_Master!A:A, 0)), IFERROR(G86, 0) )} -> 2.8392 | I86: =IFERROR(__xludf.DUMMYFUNCTION("IFERROR( INDEX( FILTER(Shipping_Rate_Card!B:F, Shipping_Rate_Card!A:A=$A86), MATCH($H86, FILTER(Shipping_Rate_Card!B:B, Shipping_Rate_Card!A:A=$A86), 1), IF( INDEX(Config!B:B, MATCH($A86, Config!A:A, 0))=""Local"", 2, IF( INDEX(Config!B:B, "&"MATCH($A86, Config!A:A, 0))=""Regional"", 3, 4 ) ) ), """") "),173.0) -> 173 | J86: =IFERROR(__xludf.DUMMYFUNCTION("IFERROR( ( E86 * INDEX(FILTER(Pricing_Rules!E:E, Pricing_Rules!A:A=A86, Pricing_Rules!B:B=B86, Pricing_Rules!C:C<=E86, Pricing_Rules!D:D>=E86), 1) + INDEX(FILTER(Pricing_Rules!F:F, Pricing_Rules!A:A=A86, Pricing_Rules!B:B=B86, Pricing_Rules!C:C<=E86, "&"Pricing_Rules!D:D>=E86), 1) ) * (1 + IFERROR( INDEX(Config!D:D, MATCH(A86, Config!A:A, 0)), 0 )), """") "),15.34) -> 15.34 | K86: =IFERROR(E86 - F86 - I86 - J86, "") -> 24.16 | L86: =IFERROR(K86 / E86, "") -> 0.080802676
A87: Flipkart | B87: {=IF(D87="","", INDEX(Product_Master!A:A, MATCH( INDEX(Pack_Master!B:B, MATCH(D87, Pack_Master!A:A, 0)), Product_Master!B:B, 0 ) ))} -> Garden_Planters | C87: PLANTER-ROUNDORCHID-SAUCER10-12 | D87: PLANTER-ROUNDORCHID-SAUCER10-PK12 | E87: 1449 | F87: {=IFERROR( VALUE( INDEX(Product_Master!$I:$I, MATCH( INDEX(Pack_Master!$B:$B, MATCH($D87, Pack_Master!$A:$A, 0)), Product_Master!$B:$B, 0) )) * VALUE( INDEX(Pack_Master!$C:$C, MATCH($D87, Pack_Master!$A:$A, 0)) ) + VALUE( INDEX(Pack_Master!$D:$D, MATCH($D87, Pack_Master!$A:$A, 0)) ), "")} -> 488 | G87: {=IFERROR( ( INDEX(Pack_Master!E:E, MATCH($D87, Pack_Master!A:A, 0)) * INDEX(Pack_Master!F:F, MATCH($D87, Pack_Master!A:A, 0)) * INDEX(Pack_Master!G:G, MATCH($D87, Pack_Master!A:A, 0)) ) / INDEX(Config!C:C, MATCH($A87, Config!A:A, 0)), "")} -> 6.2192 | H87: {=MAX( INDEX(Pack_Master!H:H, MATCH($D87, Pack_Master!A:A, 0)), IFERROR(G87, 0) )} -> 6.2192 | I87: =IFERROR(__xludf.DUMMYFUNCTION("IFERROR( INDEX( FILTER(Shipping_Rate_Card!B:F, Shipping_Rate_Card!A:A=$A87), MATCH($H87, FILTER(Shipping_Rate_Card!B:B, Shipping_Rate_Card!A:A=$A87), 1), IF( INDEX(Config!B:B, MATCH($A87, Config!A:A, 0))=""Local"", 2, IF( INDEX(Config!B:B, "&"MATCH($A87, Config!A:A, 0))=""Regional"", 3, 4 ) ) ), """") "),383.0) -> 383 | J87: =IFERROR(__xludf.DUMMYFUNCTION("IFERROR( ( E87 * INDEX(FILTER(Pricing_Rules!E:E, Pricing_Rules!A:A=A87, Pricing_Rules!B:B=B87, Pricing_Rules!C:C<=E87, Pricing_Rules!D:D>=E87), 1) + INDEX(FILTER(Pricing_Rules!F:F, Pricing_Rules!A:A=A87, Pricing_Rules!B:B=B87, Pricing_Rules!C:C<=E87, "&"Pricing_Rules!D:D>=E87), 1) ) * (1 + IFERROR( INDEX(Config!D:D, MATCH(A87, Config!A:A, 0)), 0 )), """") "),242.93839999999997) -> 242.9384 | K87: =IFERROR(E87 - F87 - I87 - J87, "") -> 335.0616 | L87: =IFERROR(K87 / E87, "") -> 0.23123644
